{"name":"Evde Hasta Bakımı","slug":"evde-hasta-bakimi-2-yillik-2024-taban-puanlari-ve-basari-siralamasi","level":"2yillik","scoreType":"TYT","url":"https://www.basarisiralamalari.com/evde-hasta-bakimi-2-yillik-2024-taban-puanlari-ve-basari-siralamasi/","rows":[{"university":"MARDİN ARTUKLU ÜNİVERSİTESİ","faculty":"Sağlık Hizmetleri Meslek Yüksekokulu","city":"MARDİN","sector":"Devlet","program":"Evde Hasta Bakımı","programRaw":"Evde Hasta Bakımı (2 Yıllık)","scoreType":"TYT","years":[{"year":2025,"quota":"40","placed":"40","rank":"571.379","rankNumeric":571379,"score":"326,9473","scoreNumeric":326.9473},{"year":2024,"quota":"40","placed":"40","rank":"459.560","rankNumeric":459560,"score":"342,9056","scoreNumeric":342.9056},{"year":2023,"quota":"40","placed":"40","rank":"524.166","rankNumeric":524166,"score":"336,20949","scoreNumeric":336.20949},{"year":2022,"quota":"40","placed":"41","rank":"911.331","rankNumeric":911331,"score":"290,29589","scoreNumeric":290.29589}]},{"university":"İNÖNÜ ÜNİVERSİTESİ","faculty":"Sağlık Hizmetleri Meslek Yüksekokulu","city":"MALATYA","sector":"Devlet","program":"Evde Hasta Bakımı","programRaw":"Evde Hasta Bakımı (2 Yıllık)","scoreType":"TYT","years":[{"year":2025,"quota":"65","placed":"65","rank":"591.056","rankNumeric":591056,"score":"324,7413","scoreNumeric":324.7413},{"year":2024,"quota":"65","placed":"65","rank":"586.095","rankNumeric":586095,"score":"327,11509","scoreNumeric":327.11509},{"year":2023,"quota":"65","placed":"67","rank":"747.555","rankNumeric":747555,"score":"311,97455","scoreNumeric":311.97455},{"year":2022,"quota":"65","placed":"67","rank":"836.748","rankNumeric":836748,"score":"296,69238","scoreNumeric":296.69238}]},{"university":"SAĞLIK BİLİMLERİ ÜNİVERSİTESİ","faculty":"Hamidiye Sağlık Hizmetleri Meslek Yüksekokulu","city":"İSTANBUL","sector":"Devlet","program":"Evde Hasta Bakımı","programRaw":"Evde Hasta Bakımı (2 Yıllık)","scoreType":"TYT","years":[{"year":2025,"quota":"50","placed":"52","rank":"635.830","rankNumeric":635830,"score":"319,93203","scoreNumeric":319.93203},{"year":2024,"quota":"60","placed":"62","rank":"657.158","rankNumeric":657158,"score":"319,7296","scoreNumeric":319.7296},{"year":2023,"quota":"60","placed":"61","rank":"861.014","rankNumeric":861014,"score":"301,80944","scoreNumeric":301.80944},{"year":2022,"quota":"60","placed":"62","rank":"957.490","rankNumeric":957490,"score":"286,51294","scoreNumeric":286.51294}]},{"university":"BİNGÖL ÜNİVERSİTESİ","faculty":"Sağlık Hizmetleri Meslek Yüksekokulu","city":"BİNGÖL","sector":"Devlet","program":"Evde Hasta Bakımı","programRaw":"Evde Hasta Bakımı (2 Yıllık)","scoreType":"TYT","years":[{"year":2025,"quota":"40","placed":"41","rank":"640.723","rankNumeric":640723,"score":"319,42615","scoreNumeric":319.42615},{"year":2024,"quota":"40","placed":"41","rank":"591.211","rankNumeric":591211,"score":"326,55953","scoreNumeric":326.55953},{"year":2023,"quota":"30","placed":"31","rank":"725.710","rankNumeric":725710,"score":"314,07069","scoreNumeric":314.07069},{"year":2022,"quota":"30","placed":"31","rank":"1.058.406","rankNumeric":1058406,"score":"278,78706","scoreNumeric":278.78706}]},{"university":"AYDIN ADNAN MENDERES ÜNİVERSİTESİ","faculty":"Söke Sağlık Hizmetleri Meslek Yüksekokulu","city":"AYDIN","sector":"Devlet","program":"Evde Hasta Bakımı","programRaw":"Evde Hasta Bakımı (2 Yıllık)","scoreType":"TYT","years":[{"year":2025,"quota":"40","placed":"41","rank":"678.250","rankNumeric":678250,"score":"315,60998","scoreNumeric":315.60998},{"year":2024,"quota":"40","placed":"40","rank":"662.976","rankNumeric":662976,"score":"319,15716","scoreNumeric":319.15716},{"year":2023,"quota":"40","placed":"41","rank":"902.516","rankNumeric":902516,"score":"298,33391","scoreNumeric":298.33391},{"year":2022,"quota":"40","placed":"41","rank":"1.056.245","rankNumeric":1056245,"score":"278,95186","scoreNumeric":278.95186}]},{"university":"HATAY MUSTAFA KEMAL ÜNİVERSİTESİ","faculty":"Kırıkhan Meslek Yüksekokulu","city":"HATAY","sector":"Devlet","program":"Evde Hasta Bakımı","programRaw":"Evde Hasta Bakımı (2 Yıllık)","scoreType":"TYT","years":[{"year":2025,"quota":"20","placed":"21","rank":"687.021","rankNumeric":687021,"score":"314,7552","scoreNumeric":314.7552},{"year":2024,"quota":"20","placed":"20","rank":"636.652","rankNumeric":636652,"score":"321,77822","scoreNumeric":321.77822},{"year":2023,"quota":"20","placed":"21","rank":"877.792","rankNumeric":877792,"score":"300,39587","scoreNumeric":300.39587},{"year":2022,"quota":"40","placed":"41","rank":"1.194.933","rankNumeric":1194933,"score":"269,21448","scoreNumeric":269.21448}]},{"university":"FIRAT ÜNİVERSİTESİ","faculty":"Kovancılar Meslek Yüksekokulu","city":"ELAZIĞ","sector":"Devlet","program":"Evde Hasta Bakımı","programRaw":"Evde Hasta Bakımı (2 Yıllık)","scoreType":"TYT","years":[{"year":2025,"quota":"30","placed":"30","rank":"688.142","rankNumeric":688142,"score":"314,63666","scoreNumeric":314.63666},{"year":2024,"quota":"30","placed":"31","rank":"658.732","rankNumeric":658732,"score":"319,57382","scoreNumeric":319.57382},{"year":2023,"quota":"30","placed":"31","rank":"918.463","rankNumeric":918463,"score":"297,0494","scoreNumeric":297.0494},{"year":2022,"quota":"—","placed":"—","rank":"—","rankNumeric":null,"score":"—","scoreNumeric":null}]},{"university":"ŞIRNAK ÜNİVERSİTESİ","faculty":"Sağlık Hizmetleri Meslek Yüksekokulu","city":"ŞIRNAK","sector":"Devlet","program":"Evde Hasta Bakımı","programRaw":"Evde Hasta Bakımı (2 Yıllık)","scoreType":"TYT","years":[{"year":2025,"quota":"30","placed":"31","rank":"713.933","rankNumeric":713933,"score":"312,17298","scoreNumeric":312.17298},{"year":2024,"quota":"—","placed":"—","rank":"—","rankNumeric":null,"score":"—","scoreNumeric":null},{"year":2023,"quota":"—","placed":"—","rank":"—","rankNumeric":null,"score":"—","scoreNumeric":null},{"year":2022,"quota":"—","placed":"—","rank":"—","rankNumeric":null,"score":"—","scoreNumeric":null}]},{"university":"BARTIN ÜNİVERSİTESİ","faculty":"Bartın Sağlık Hizmetleri Meslek Yüksekokulu","city":"BARTIN","sector":"Devlet","program":"Evde Hasta Bakımı","programRaw":"Evde Hasta Bakımı (2 Yıllık)","scoreType":"TYT","years":[{"year":2025,"quota":"50","placed":"51","rank":"720.878","rankNumeric":720878,"score":"311,51769","scoreNumeric":311.51769},{"year":2024,"quota":"50","placed":"52","rank":"774.183","rankNumeric":774183,"score":"308,93009","scoreNumeric":308.93009},{"year":2023,"quota":"50","placed":"52","rank":"1.044.324","rankNumeric":1044324,"score":"287,25855","scoreNumeric":287.25855},{"year":2022,"quota":"50","placed":"52","rank":"1.221.431","rankNumeric":1221431,"score":"267,46459","scoreNumeric":267.46459}]},{"university":"AYDIN ADNAN MENDERES ÜNİVERSİTESİ","faculty":"Nazilli Sağlık Hizmetleri Meslek Yüksekokulu","city":"AYDIN","sector":"Devlet","program":"Evde Hasta Bakımı","programRaw":"Evde Hasta Bakımı (2 Yıllık)","scoreType":"TYT","years":[{"year":2025,"quota":"70","placed":"72","rank":"733.708","rankNumeric":733708,"score":"310,3179","scoreNumeric":310.3179},{"year":2024,"quota":"70","placed":"71","rank":"689.228","rankNumeric":689228,"score":"316,61483","scoreNumeric":316.61483},{"year":2023,"quota":"70","placed":"71","rank":"891.377","rankNumeric":891377,"score":"299,2628","scoreNumeric":299.2628},{"year":2022,"quota":"70","placed":"72","rank":"1.070.521","rankNumeric":1070521,"score":"277,90589","scoreNumeric":277.90589}]},{"university":"MUNZUR ÜNİVERSİTESİ","faculty":"Tunceli Meslek Yüksekokulu","city":"TUNCELİ","sector":"Devlet","program":"Evde Hasta Bakımı","programRaw":"Evde Hasta Bakımı (2 Yıllık)","scoreType":"TYT","years":[{"year":2025,"quota":"30","placed":"30","rank":"735.682","rankNumeric":735682,"score":"310,13493","scoreNumeric":310.13493},{"year":2024,"quota":"—","placed":"—","rank":"—","rankNumeric":null,"score":"—","scoreNumeric":null},{"year":2023,"quota":"—","placed":"—","rank":"—","rankNumeric":null,"score":"—","scoreNumeric":null},{"year":2022,"quota":"—","placed":"—","rank":"—","rankNumeric":null,"score":"—","scoreNumeric":null}]},{"university":"KARAMANOĞLU MEHMETBEY ÜNİVERSİTESİ","faculty":"Sağlık Hizmetleri Meslek Yüksekokulu","city":"KARAMAN","sector":"Devlet","program":"Evde Hasta Bakımı","programRaw":"Evde Hasta Bakımı (2 Yıllık)","scoreType":"TYT","years":[{"year":2025,"quota":"55","placed":"57","rank":"745.742","rankNumeric":745742,"score":"309,21304","scoreNumeric":309.21304},{"year":2024,"quota":"55","placed":"57","rank":"750.074","rankNumeric":750074,"score":"311,02064","scoreNumeric":311.02064},{"year":2023,"quota":"55","placed":"57","rank":"985.856","rankNumeric":985856,"score":"291,70087","scoreNumeric":291.70087},{"year":2022,"quota":"55","placed":"57","rank":"1.252.231","rankNumeric":1252231,"score":"265,45341","scoreNumeric":265.45341}]},{"university":"KIRIKKALE ÜNİVERSİTESİ","faculty":"Sağlık Hizmetleri Meslek Yüksekokulu","city":"KIRIKKALE","sector":"Devlet","program":"Evde Hasta Bakımı","programRaw":"Evde Hasta Bakımı (2 Yıllık)","scoreType":"TYT","years":[{"year":2025,"quota":"50","placed":"52","rank":"752.872","rankNumeric":752872,"score":"308,56989","scoreNumeric":308.56989},{"year":2024,"quota":"50","placed":"50","rank":"771.352","rankNumeric":771352,"score":"309,17694","scoreNumeric":309.17694},{"year":2023,"quota":"50","placed":"52","rank":"1.103.651","rankNumeric":1103651,"score":"282,91749","scoreNumeric":282.91749},{"year":2022,"quota":"—","placed":"—","rank":"—","rankNumeric":null,"score":"—","scoreNumeric":null}]},{"university":"ERZİNCAN BİNALİ YILDIRIM ÜNİVERSİTESİ","faculty":"Sağlık Hizmetleri Meslek Yüksekokulu","city":"ERZİNCAN","sector":"Devlet","program":"Evde Hasta Bakımı","programRaw":"Evde Hasta Bakımı (2 Yıllık)","scoreType":"TYT","years":[{"year":2025,"quota":"65","placed":"67","rank":"758.487","rankNumeric":758487,"score":"308,06144","scoreNumeric":308.06144},{"year":2024,"quota":"65","placed":"66","rank":"731.047","rankNumeric":731047,"score":"312,74044","scoreNumeric":312.74044},{"year":2023,"quota":"65","placed":"67","rank":"969.719","rankNumeric":969719,"score":"292,95502","scoreNumeric":292.95502},{"year":2022,"quota":"65","placed":"67","rank":"1.215.694","rankNumeric":1215694,"score":"267,84814","scoreNumeric":267.84814}]},{"university":"ÜSKÜDAR ÜNİVERSİTESİ","faculty":"Sağlık Hizmetleri Meslek Yüksekokulu","city":"İSTANBUL","sector":"Vakıf","program":"Evde Hasta Bakımı (Burslu)","programRaw":"Evde Hasta Bakımı (Burslu) (2 Yıllık)","scoreType":"TYT","years":[{"year":2025,"quota":"5","placed":"5","rank":"764.821","rankNumeric":764821,"score":"307,48768","scoreNumeric":307.48768},{"year":2024,"quota":"4","placed":"4","rank":"545.889","rankNumeric":545889,"score":"331,72385","scoreNumeric":331.72385},{"year":2023,"quota":"3","placed":"3","rank":"798.173","rankNumeric":798173,"score":"307,3094","scoreNumeric":307.3094},{"year":2022,"quota":"3","placed":"3","rank":"947.042","rankNumeric":947042,"score":"287,36068","scoreNumeric":287.36068}]},{"university":"İSTANBUL ESENYURT ÜNİVERSİTESİ","faculty":"Sağlık Hizmetleri Meslek Yüksekokulu","city":"İSTANBUL","sector":"Vakıf","program":"Evde Hasta Bakımı (Burslu)","programRaw":"Evde Hasta Bakımı (Burslu) (2 Yıllık)","scoreType":"TYT","years":[{"year":2025,"quota":"7","placed":"7","rank":"780.507","rankNumeric":780507,"score":"306,07948","scoreNumeric":306.07948},{"year":2024,"quota":"—","placed":"—","rank":"—","rankNumeric":null,"score":"—","scoreNumeric":null},{"year":2023,"quota":"—","placed":"—","rank":"—","rankNumeric":null,"score":"—","scoreNumeric":null},{"year":2022,"quota":"—","placed":"—","rank":"—","rankNumeric":null,"score":"—","scoreNumeric":null}]},{"university":"TOKAT GAZİOSMANPAŞA ÜNİVERSİTESİ","faculty":"Erbaa Sağlık Hizmetleri Meslek Yüksekokulu","city":"TOKAT","sector":"Devlet","program":"Evde Hasta Bakımı","programRaw":"Evde Hasta Bakımı (2 Yıllık)","scoreType":"TYT","years":[{"year":2025,"quota":"40","placed":"41","rank":"784.632","rankNumeric":784632,"score":"305,70993","scoreNumeric":305.70993},{"year":2024,"quota":"40","placed":"41","rank":"824.247","rankNumeric":824247,"score":"304,68505","scoreNumeric":304.68505},{"year":2023,"quota":"40","placed":"41","rank":"1.047.892","rankNumeric":1047892,"score":"286,99537","scoreNumeric":286.99537},{"year":2022,"quota":"40","placed":"41","rank":"1.301.040","rankNumeric":1301040,"score":"262,35931","scoreNumeric":262.35931}]},{"university":"KAFKAS ÜNİVERSİTESİ","faculty":"Atatürk Sağlık Hizmetleri Meslek Yüksekokulu","city":"KARS","sector":"Devlet","program":"Evde Hasta Bakımı","programRaw":"Evde Hasta Bakımı (2 Yıllık)","scoreType":"TYT","years":[{"year":2025,"quota":"70","placed":"71","rank":"793.417","rankNumeric":793417,"score":"304,94441","scoreNumeric":304.94441},{"year":2024,"quota":"70","placed":"72","rank":"786.683","rankNumeric":786683,"score":"307,84388","scoreNumeric":307.84388},{"year":2023,"quota":"70","placed":"71","rank":"1.070.484","rankNumeric":1070484,"score":"285,32511","scoreNumeric":285.32511},{"year":2022,"quota":"70","placed":"72","rank":"1.349.033","rankNumeric":1349033,"score":"259,41676","scoreNumeric":259.41676}]},{"university":"IĞDIR ÜNİVERSİTESİ","faculty":"Sağlık Hizmetleri Meslek Yüksekokulu","city":"IĞDIR","sector":"Devlet","program":"Evde Hasta Bakımı","programRaw":"Evde Hasta Bakımı (2 Yıllık)","scoreType":"TYT","years":[{"year":2025,"quota":"50","placed":"51","rank":"796.646","rankNumeric":796646,"score":"304,66399","scoreNumeric":304.66399},{"year":2024,"quota":"50","placed":"52","rank":"718.022","rankNumeric":718022,"score":"313,94393","scoreNumeric":313.94393},{"year":2023,"quota":"50","placed":"52","rank":"1.005.839","rankNumeric":1005839,"score":"290,18033","scoreNumeric":290.18033},{"year":2022,"quota":"50","placed":"52","rank":"1.316.433","rankNumeric":1316433,"score":"261,40448","scoreNumeric":261.40448}]},{"university":"MUŞ ALPARSLAN ÜNİVERSİTESİ","faculty":"Malazgirt Meslek Yüksekokulu","city":"MUŞ","sector":"Devlet","program":"Evde Hasta Bakımı","programRaw":"Evde Hasta Bakımı (2 Yıllık)","scoreType":"TYT","years":[{"year":2025,"quota":"60","placed":"62","rank":"807.696","rankNumeric":807696,"score":"303,70066","scoreNumeric":303.70066},{"year":2024,"quota":"60","placed":"61","rank":"757.418","rankNumeric":757418,"score":"310,3682","scoreNumeric":310.3682},{"year":2023,"quota":"60","placed":"62","rank":"1.036.764","rankNumeric":1036764,"score":"287,81985","scoreNumeric":287.81985},{"year":2022,"quota":"60","placed":"62","rank":"1.430.425","rankNumeric":1430425,"score":"254,62245","scoreNumeric":254.62245}]},{"university":"AĞRI İBRAHİM ÇEÇEN ÜNİVERSİTESİ","faculty":"Doğubayazıt Ahmed-İ Hani Meslek Yüksekokulu","city":"AĞRI","sector":"Devlet","program":"Evde Hasta Bakımı","programRaw":"Evde Hasta Bakımı (2 Yıllık)","scoreType":"TYT","years":[{"year":2025,"quota":"40","placed":"41","rank":"811.990","rankNumeric":811990,"score":"303,33226","scoreNumeric":303.33226},{"year":2024,"quota":"40","placed":"41","rank":"793.257","rankNumeric":793257,"score":"307,28623","scoreNumeric":307.28623},{"year":2023,"quota":"40","placed":"41","rank":"1.063.915","rankNumeric":1063915,"score":"285,8107","scoreNumeric":285.8107},{"year":2022,"quota":"40","placed":"41","rank":"1.464.585","rankNumeric":1464585,"score":"252,6709","scoreNumeric":252.6709}]},{"university":"BURDUR MEHMET AKİF ERSOY ÜNİVERSİTESİ","faculty":"Gölhisar Sağlık Hizmetleri Meslek Yüksekokulu","city":"BURDUR","sector":"Devlet","program":"Evde Hasta Bakımı","programRaw":"Evde Hasta Bakımı (2 Yıllık)","scoreType":"TYT","years":[{"year":2025,"quota":"30","placed":"31","rank":"812.071","rankNumeric":812071,"score":"303,32541","scoreNumeric":303.32541},{"year":2024,"quota":"—","placed":"—","rank":"—","rankNumeric":null,"score":"—","scoreNumeric":null},{"year":2023,"quota":"—","placed":"—","rank":"—","rankNumeric":null,"score":"—","scoreNumeric":null},{"year":2022,"quota":"—","placed":"—","rank":"—","rankNumeric":null,"score":"—","scoreNumeric":null}]},{"university":"TRABZON ÜNİVERSİTESİ","faculty":"Tonya Meslek Yüksekokulu","city":"TRABZON","sector":"Devlet","program":"Evde Hasta Bakımı","programRaw":"Evde Hasta Bakımı (2 Yıllık)","scoreType":"TYT","years":[{"year":2025,"quota":"50","placed":"52","rank":"816.127","rankNumeric":816127,"score":"302,97898","scoreNumeric":302.97898},{"year":2024,"quota":"50","placed":"52","rank":"854.720","rankNumeric":854720,"score":"302,19911","scoreNumeric":302.19911},{"year":2023,"quota":"50","placed":"52","rank":"1.154.388","rankNumeric":1154388,"score":"279,30263","scoreNumeric":279.30263},{"year":2022,"quota":"50","placed":"52","rank":"1.332.695","rankNumeric":1332695,"score":"260,41174","scoreNumeric":260.41174}]},{"university":"ISPARTA UYGULAMALI BİLİMLER ÜNİVERSİTESİ","faculty":"Uluborlu Selahattin Karasoy Meslek Yüksekokulu","city":"ISPARTA","sector":"Devlet","program":"Evde Hasta Bakımı","programRaw":"Evde Hasta Bakımı (2 Yıllık)","scoreType":"TYT","years":[{"year":2025,"quota":"55","placed":"57","rank":"822.148","rankNumeric":822148,"score":"302,46101","scoreNumeric":302.46101},{"year":2024,"quota":"55","placed":"57","rank":"789.682","rankNumeric":789682,"score":"307,5905","scoreNumeric":307.5905},{"year":2023,"quota":"55","placed":"57","rank":"1.140.796","rankNumeric":1140796,"score":"280,25522","scoreNumeric":280.25522},{"year":2022,"quota":"55","placed":"57","rank":"1.390.654","rankNumeric":1390654,"score":"256,92624","scoreNumeric":256.92624}]},{"university":"ARTVİN ÇORUH ÜNİVERSİTESİ","faculty":"Yusufeli Meslek Yüksekokulu","city":"ARTVİN","sector":"Devlet","program":"Evde Hasta Bakımı","programRaw":"Evde Hasta Bakımı (2 Yıllık)","scoreType":"TYT","years":[{"year":2025,"quota":"30","placed":"31","rank":"829.599","rankNumeric":829599,"score":"301,83315","scoreNumeric":301.83315},{"year":2024,"quota":"30","placed":"31","rank":"856.966","rankNumeric":856966,"score":"302,01678","scoreNumeric":302.01678},{"year":2023,"quota":"30","placed":"31","rank":"1.304.183","rankNumeric":1304183,"score":"269,11157","scoreNumeric":269.11157},{"year":2022,"quota":"—","placed":"—","rank":"—","rankNumeric":null,"score":"—","scoreNumeric":null}]},{"university":"BİLECİK ŞEYH EDEBALİ ÜNİVERSİTESİ","faculty":"Osmaneli Meslek Yüksekokulu","city":"BİLECİK","sector":"Devlet","program":"Evde Hasta Bakımı","programRaw":"Evde Hasta Bakımı (2 Yıllık)","scoreType":"TYT","years":[{"year":2025,"quota":"40","placed":"41","rank":"849.644","rankNumeric":849644,"score":"300,14402","scoreNumeric":300.14402},{"year":2024,"quota":"40","placed":"41","rank":"862.283","rankNumeric":862283,"score":"301,5907","scoreNumeric":301.5907},{"year":2023,"quota":"30","placed":"31","rank":"1.150.441","rankNumeric":1150441,"score":"279,58105","scoreNumeric":279.58105},{"year":2022,"quota":"30","placed":"31","rank":"1.535.124","rankNumeric":1535124,"score":"248,78055","scoreNumeric":248.78055}]},{"university":"SİNOP ÜNİVERSİTESİ","faculty":"Türkeli Meslek Yüksekokulu","city":"SİNOP","sector":"Devlet","program":"Evde Hasta Bakımı","programRaw":"Evde Hasta Bakımı (2 Yıllık)","scoreType":"TYT","years":[{"year":2025,"quota":"60","placed":"62","rank":"854.144","rankNumeric":854144,"score":"299,77328","scoreNumeric":299.77328},{"year":2024,"quota":"60","placed":"61","rank":"874.779","rankNumeric":874779,"score":"300,61216","scoreNumeric":300.61216},{"year":2023,"quota":"60","placed":"62","rank":"1.216.786","rankNumeric":1216786,"score":"274,94508","scoreNumeric":274.94508},{"year":2022,"quota":"60","placed":"62","rank":"1.561.889","rankNumeric":1561889,"score":"247,34324","scoreNumeric":247.34324}]},{"university":"YOZGAT BOZOK ÜNİVERSİTESİ","faculty":"Çekerek Fuat Oktay Sağlık Hizmetleri Meslek Yüksekokulu","city":"YOZGAT","sector":"Devlet","program":"Evde Hasta Bakımı","programRaw":"Evde Hasta Bakımı (2 Yıllık)","scoreType":"TYT","years":[{"year":2025,"quota":"20","placed":"21","rank":"859.092","rankNumeric":859092,"score":"299,34906","scoreNumeric":299.34906},{"year":2024,"quota":"20","placed":"21","rank":"891.837","rankNumeric":891837,"score":"299,28418","scoreNumeric":299.28418},{"year":2023,"quota":"—","placed":"—","rank":"—","rankNumeric":null,"score":"—","scoreNumeric":null},{"year":2022,"quota":"—","placed":"—","rank":"—","rankNumeric":null,"score":"—","scoreNumeric":null}]},{"university":"TOKAT GAZİOSMANPAŞA ÜNİVERSİTESİ","faculty":"Pazar Meslek Yüksekokulu","city":"TOKAT","sector":"Devlet","program":"Evde Hasta Bakımı","programRaw":"Evde Hasta Bakımı (2 Yıllık)","scoreType":"TYT","years":[{"year":2025,"quota":"40","placed":"41","rank":"868.263","rankNumeric":868263,"score":"298,59435","scoreNumeric":298.59435},{"year":2024,"quota":"40","placed":"41","rank":"885.417","rankNumeric":885417,"score":"299,77785","scoreNumeric":299.77785},{"year":2023,"quota":"40","placed":"41","rank":"1.192.996","rankNumeric":1192996,"score":"276,60747","scoreNumeric":276.60747},{"year":2022,"quota":"40","placed":"41","rank":"1.482.986","rankNumeric":1482986,"score":"251,64022","scoreNumeric":251.64022}]},{"university":"ARDAHAN ÜNİVERSİTESİ","faculty":"Posof Meslek Yüksekokulu","city":"ARDAHAN","sector":"Devlet","program":"Evde Hasta Bakımı","programRaw":"Evde Hasta Bakımı (2 Yıllık)","scoreType":"TYT","years":[{"year":2025,"quota":"30","placed":"31","rank":"870.405","rankNumeric":870405,"score":"298,41301","scoreNumeric":298.41301},{"year":2024,"quota":"30","placed":"31","rank":"873.505","rankNumeric":873505,"score":"300,71607","scoreNumeric":300.71607},{"year":2023,"quota":"30","placed":"31","rank":"1.184.725","rankNumeric":1184725,"score":"277,19058","scoreNumeric":277.19058},{"year":2022,"quota":"30","placed":"31","rank":"1.515.595","rankNumeric":1515595,"score":"249,84492","scoreNumeric":249.84492}]},{"university":"KASTAMONU ÜNİVERSİTESİ","faculty":"Tosya Meslek Yüksekokulu","city":"KASTAMONU","sector":"Devlet","program":"Evde Hasta Bakımı","programRaw":"Evde Hasta Bakımı (2 Yıllık)","scoreType":"TYT","years":[{"year":2025,"quota":"60","placed":"62","rank":"873.011","rankNumeric":873011,"score":"298,20042","scoreNumeric":298.20042},{"year":2024,"quota":"60","placed":"61","rank":"889.892","rankNumeric":889892,"score":"299,43379","scoreNumeric":299.43379},{"year":2023,"quota":"60","placed":"62","rank":"1.279.192","rankNumeric":1279192,"score":"270,7718","scoreNumeric":270.7718},{"year":2022,"quota":"60","placed":"62","rank":"1.613.536","rankNumeric":1613536,"score":"244,6539","scoreNumeric":244.6539}]},{"university":"ÇANKIRI KARATEKİN ÜNİVERSİTESİ","faculty":"Çerkeş Meslek Yüksekokulu","city":"ÇANKIRI","sector":"Devlet","program":"Evde Hasta Bakımı","programRaw":"Evde Hasta Bakımı (2 Yıllık)","scoreType":"TYT","years":[{"year":2025,"quota":"50","placed":"52","rank":"885.429","rankNumeric":885429,"score":"297,19227","scoreNumeric":297.19227},{"year":2024,"quota":"50","placed":"52","rank":"912.190","rankNumeric":912190,"score":"297,72873","scoreNumeric":297.72873},{"year":2023,"quota":"50","placed":"52","rank":"1.266.009","rankNumeric":1266009,"score":"271,6396","scoreNumeric":271.6396},{"year":2022,"quota":"50","placed":"52","rank":"1.660.333","rankNumeric":1660333,"score":"242,26413","scoreNumeric":242.26413}]},{"university":"İSTANBUL RUMELİ ÜNİVERSİTESİ","faculty":"Sağlık Hizmetleri Meslek Yüksekokulu","city":"İSTANBUL","sector":"Vakıf","program":"Evde Hasta Bakımı (Burslu)","programRaw":"Evde Hasta Bakımı (Burslu) (2 Yıllık)","scoreType":"TYT","years":[{"year":2025,"quota":"4","placed":"4","rank":"893.715","rankNumeric":893715,"score":"296,51339","scoreNumeric":296.51339},{"year":2024,"quota":"4","placed":"4","rank":"622.442","rankNumeric":622442,"score":"323,23799","scoreNumeric":323.23799},{"year":2023,"quota":"10","placed":"10","rank":"957.663","rankNumeric":957663,"score":"293,8953","scoreNumeric":293.8953},{"year":2022,"quota":"10","placed":"10","rank":"1.064.216","rankNumeric":1064216,"score":"278,36147","scoreNumeric":278.36147}]},{"university":"ÜSKÜDAR ÜNİVERSİTESİ","faculty":"Sağlık Hizmetleri Meslek Yüksekokulu","city":"İSTANBUL","sector":"Vakıf","program":"Evde Hasta Bakımı (%50 İndirimli)","programRaw":"Evde Hasta Bakımı (%50 İndirimli) (2 Yıllık)","scoreType":"TYT","years":[{"year":2025,"quota":"37","placed":"37","rank":"2.211.561","rankNumeric":2211561,"score":"199,01787","scoreNumeric":199.01787},{"year":2024,"quota":"19","placed":"19","rank":"1.069.462","rankNumeric":1069462,"score":"286,31944","scoreNumeric":286.31944},{"year":2023,"quota":"15","placed":"15","rank":"1.584.188","rankNumeric":1584188,"score":"251,77515","scoreNumeric":251.77515},{"year":2022,"quota":"17","placed":"17","rank":"2.216.610","rankNumeric":2216610,"score":"217,70568","scoreNumeric":217.70568}]},{"university":"İSTANBUL ESENYURT ÜNİVERSİTESİ","faculty":"Sağlık Hizmetleri Meslek Yüksekokulu","city":"İSTANBUL","sector":"Vakıf","program":"Evde Hasta Bakımı (%50 İndirimli)","programRaw":"Evde Hasta Bakımı (%50 İndirimli) (2 Yıllık)","scoreType":"TYT","years":[{"year":2025,"quota":"42","placed":"8","rank":"Dolmadı","rankNumeric":null,"score":"Dolmadı","scoreNumeric":null},{"year":2024,"quota":"—","placed":"—","rank":"—","rankNumeric":null,"score":"—","scoreNumeric":null},{"year":2023,"quota":"—","placed":"—","rank":"—","rankNumeric":null,"score":"—","scoreNumeric":null},{"year":2022,"quota":"—","placed":"—","rank":"—","rankNumeric":null,"score":"—","scoreNumeric":null}]},{"university":"İSTANBUL RUMELİ ÜNİVERSİTESİ","faculty":"Sağlık Hizmetleri Meslek Yüksekokulu","city":"İSTANBUL","sector":"Vakıf","program":"Evde Hasta Bakımı (%50 İndirimli)","programRaw":"Evde Hasta Bakımı (%50 İndirimli) (2 Yıllık)","scoreType":"TYT","years":[{"year":2025,"quota":"21","placed":"6","rank":"Dolmadı","rankNumeric":null,"score":"Dolmadı","scoreNumeric":null},{"year":2024,"quota":"21","placed":"21","rank":"1.918.409","rankNumeric":1918409,"score":"235,07325","scoreNumeric":235.07325},{"year":2023,"quota":"10","placed":"10","rank":"2.329.751","rankNumeric":2329751,"score":"212,37269","scoreNumeric":212.37269},{"year":2022,"quota":"10","placed":"10","rank":"2.635.659","rankNumeric":2635659,"score":"200,15955","scoreNumeric":200.15955}]},{"university":"AYDIN ADNAN MENDERES ÜNİVERSİTESİ","faculty":"Nazilli Sağlık Hizmetleri Meslek Yüksekokulu","city":"AYDIN","sector":"Devlet","program":"Evde Hasta Bakımı (KKTC Uyruklu)","programRaw":"Evde Hasta Bakımı (KKTC Uyruklu) (2 Yıllık)","scoreType":"TYT","years":[{"year":2025,"quota":"1","placed":"0","rank":"Dolmadı","rankNumeric":null,"score":"Dolmadı","scoreNumeric":null},{"year":2024,"quota":"—","placed":"—","rank":"—","rankNumeric":null,"score":"—","scoreNumeric":null},{"year":2023,"quota":"—","placed":"—","rank":"—","rankNumeric":null,"score":"—","scoreNumeric":null},{"year":2022,"quota":"—","placed":"—","rank":"—","rankNumeric":null,"score":"—","scoreNumeric":null}]}],"warnings":[]}