{"name":"Grafik Sanatlar","slug":"grafik-sanatlar-2024-taban-puanlari-ve-basari-siralamasi","level":"4yillik","scoreType":"EA","url":"https://www.basarisiralamalari.com/grafik-sanatlar-2024-taban-puanlari-ve-basari-siralamasi/","rows":[{"university":"ATATÜRK ÜNİVERSİTESİ (ERZURUM) (DEVLET) Açık ve Uzaktan Öğretim Fakültesi","faculty":null,"city":"ERZURUM","sector":"DEVLET","program":"Grafik Sanatlar (Açıköğretim)","programRaw":"Grafik Sanatlar (Açıköğretim)","scoreType":"EA","years":[{"year":2025,"quota":"2000","placed":"2050","rank":"1.339.000","rankNumeric":1339000,"score":"201,76172","scoreNumeric":201.76172},{"year":2024,"quota":"2000","placed":"2050","rank":"1.492.559","rankNumeric":1492559,"score":"201,57255","scoreNumeric":201.57255},{"year":2023,"quota":"400","placed":"420","rank":"1.100.416","rankNumeric":1100416,"score":"233,23862","scoreNumeric":233.23862},{"year":2022,"quota":"400","placed":"410","rank":"1.094.863","rankNumeric":1094863,"score":"233,54718","scoreNumeric":233.54718}]}],"warnings":[]}