{"name":"İlköğretim Matematik Öğretmenliği","slug":"ilkogretim-matematik-ogretmenligi-2024-taban-puanlari-ve-basari-siralamasi","level":"4yillik","scoreType":"SAY","url":"https://www.basarisiralamalari.com/ilkogretim-matematik-ogretmenligi-2024-taban-puanlari-ve-basari-siralamasi/","rows":[{"university":"BOĞAZİÇİ ÜNİVERSİTESİ","faculty":"Eğitim Fakültesi","city":"İSTANBUL","sector":"Devlet","program":"İlköğretim Matematik Öğretmenliği (İngilizce)","programRaw":"İlköğretim Matematik Öğretmenliği (İngilizce) (4 Yıllık)","scoreType":"SAY","years":[{"year":2025,"quota":"20","placed":"21","rank":"73.504","rankNumeric":73504,"score":"422,30005","scoreNumeric":422.30005},{"year":2024,"quota":"45","placed":"47","rank":"79.211","rankNumeric":79211,"score":"403,26389","scoreNumeric":403.26389},{"year":2023,"quota":"40","placed":"41","rank":"58.409","rankNumeric":58409,"score":"449,77854","scoreNumeric":449.77854},{"year":2022,"quota":"50","placed":"52","rank":"50.928","rankNumeric":50928,"score":"456,51754","scoreNumeric":456.51754}]},{"university":"ORTA DOĞU TEKNİK ÜNİVERSİTESİ","faculty":"Eğitim Fakültesi","city":"ANKARA","sector":"Devlet","program":"İlköğretim Matematik Öğretmenliği (İngilizce)","programRaw":"İlköğretim Matematik Öğretmenliği (İngilizce) (4 Yıllık)","scoreType":"SAY","years":[{"year":2025,"quota":"40","placed":"41","rank":"78.249","rankNumeric":78249,"score":"418,01212","scoreNumeric":418.01212},{"year":2024,"quota":"40","placed":"41","rank":"68.682","rankNumeric":68682,"score":"413,93437","scoreNumeric":413.93437},{"year":2023,"quota":"40","placed":"41","rank":"53.707","rankNumeric":53707,"score":"454,84282","scoreNumeric":454.84282},{"year":2022,"quota":"50","placed":"52","rank":"49.727","rankNumeric":49727,"score":"457,93896","scoreNumeric":457.93896}]},{"university":"HACETTEPE ÜNİVERSİTESİ","faculty":"Eğitim Fakültesi","city":"ANKARA","sector":"Devlet","program":"İlköğretim Matematik Öğretmenliği","programRaw":"İlköğretim Matematik Öğretmenliği (4 Yıllık)","scoreType":"SAY","years":[{"year":2025,"quota":"45","placed":"47","rank":"93.933","rankNumeric":93933,"score":"404,07889","scoreNumeric":404.07889},{"year":2024,"quota":"45","placed":"47","rank":"76.169","rankNumeric":76169,"score":"406,26767","scoreNumeric":406.26767},{"year":2023,"quota":"40","placed":"41","rank":"54.491","rankNumeric":54491,"score":"453,96219","scoreNumeric":453.96219},{"year":2022,"quota":"60","placed":"62","rank":"54.599","rankNumeric":54599,"score":"452,30916","scoreNumeric":452.30916}]},{"university":"YILDIZ TEKNİK ÜNİVERSİTESİ","faculty":"Eğitim Fakültesi","city":"İSTANBUL","sector":"Devlet","program":"İlköğretim Matematik Öğretmenliği","programRaw":"İlköğretim Matematik Öğretmenliği (4 Yıllık)","scoreType":"SAY","years":[{"year":2025,"quota":"30","placed":"31","rank":"110.109","rankNumeric":110109,"score":"391,05573","scoreNumeric":391.05573},{"year":2024,"quota":"30","placed":"31","rank":"99.182","rankNumeric":99182,"score":"385,07530","scoreNumeric":385.0753},{"year":2023,"quota":"60","placed":"62","rank":"78.355","rankNumeric":78355,"score":"428,86933","scoreNumeric":428.86933},{"year":2022,"quota":"60","placed":"62","rank":"68.151","rankNumeric":68151,"score":"437,16823","scoreNumeric":437.16823}]},{"university":"GAZİ ÜNİVERSİTESİ","faculty":"Gazi Eğitim Fakültesi","city":"ANKARA","sector":"Devlet","program":"İlköğretim Matematik Öğretmenliği","programRaw":"İlköğretim Matematik Öğretmenliği (4 Yıllık)","scoreType":"SAY","years":[{"year":2025,"quota":"50","placed":"52","rank":"124.318","rankNumeric":124318,"score":"380,47493","scoreNumeric":380.47493},{"year":2024,"quota":"50","placed":"52","rank":"90.718","rankNumeric":90718,"score":"392,51530","scoreNumeric":392.5153},{"year":2023,"quota":"80","placed":"82","rank":"61.713","rankNumeric":61713,"score":"446,15217","scoreNumeric":446.15217},{"year":2022,"quota":"70","placed":"72","rank":"59.843","rankNumeric":59843,"score":"446,37132","scoreNumeric":446.37132}]},{"university":"BAŞKENT ÜNİVERSİTESİ","faculty":"Eğitim Fakültesi","city":"ANKARA","sector":"Vakıf","program":"İlköğretim Matematik Öğretmenliği (Burslu)","programRaw":"İlköğretim Matematik Öğretmenliği (Burslu) (4 Yıllık)","scoreType":"SAY","years":[{"year":2025,"quota":"3","placed":"4","rank":"128.793","rankNumeric":128793,"score":"377,37369","scoreNumeric":377.37369},{"year":2024,"quota":"4","placed":"5","rank":"166.541","rankNumeric":166541,"score":"339,57616","scoreNumeric":339.57616},{"year":2023,"quota":"4","placed":"6","rank":"67.993","rankNumeric":67993,"score":"439,47147","scoreNumeric":439.47147},{"year":2022,"quota":"5","placed":"5","rank":"67.071","rankNumeric":67071,"score":"438,35514","scoreNumeric":438.35514}]},{"university":"MARMARA ÜNİVERSİTESİ","faculty":"Atatürk Eğitim Fakültesi","city":"İSTANBUL","sector":"Devlet","program":"İlköğretim Matematik Öğretmenliği","programRaw":"İlköğretim Matematik Öğretmenliği (4 Yıllık)","scoreType":"SAY","years":[{"year":2025,"quota":"40","placed":"41","rank":"136.842","rankNumeric":136842,"score":"371,80105","scoreNumeric":371.80105},{"year":2024,"quota":"40","placed":"41","rank":"132.715","rankNumeric":132715,"score":"359,64651","scoreNumeric":359.64651},{"year":2023,"quota":"60","placed":"62","rank":"72.557","rankNumeric":72557,"score":"434,61661","scoreNumeric":434.61661},{"year":2022,"quota":"60","placed":"62","rank":"65.030","rankNumeric":65030,"score":"440,63384","scoreNumeric":440.63384}]},{"university":"YEDİTEPE ÜNİVERSİTESİ","faculty":"Eğitim Fakültesi","city":"İSTANBUL","sector":"Vakıf","program":"İlköğretim Matematik Öğretmenliği (İngilizce) (Burslu)","programRaw":"İlköğretim Matematik Öğretmenliği (İngilizce) (Burslu) (4 Yıllık)","scoreType":"SAY","years":[{"year":2025,"quota":"5","placed":"6","rank":"144.379","rankNumeric":144379,"score":"366,94083","scoreNumeric":366.94083},{"year":2024,"quota":"2","placed":"3","rank":"95.255","rankNumeric":95255,"score":"388,52538","scoreNumeric":388.52538},{"year":2023,"quota":"3","placed":"4","rank":"82.786","rankNumeric":82786,"score":"424,58319","scoreNumeric":424.58319},{"year":2022,"quota":"4","placed":"4","rank":"75.194","rankNumeric":75194,"score":"429,62806","scoreNumeric":429.62806}]},{"university":"İSTANBUL MEDİPOL ÜNİVERSİTESİ","faculty":"Eğitim Fakültesi","city":"İSTANBUL","sector":"Vakıf","program":"İlköğretim Matematik Öğretmenliği (Burslu)","programRaw":"İlköğretim Matematik Öğretmenliği (Burslu) (4 Yıllık)","scoreType":"SAY","years":[{"year":2025,"quota":"4","placed":"5","rank":"165.558","rankNumeric":165558,"score":"354,61361","scoreNumeric":354.61361},{"year":2024,"quota":"7","placed":"7","rank":"171.286","rankNumeric":171286,"score":"337,11552","scoreNumeric":337.11552},{"year":2023,"quota":"7","placed":"9","rank":"103.108","rankNumeric":103108,"score":"406,20201","scoreNumeric":406.20201},{"year":2022,"quota":"8","placed":"8","rank":"82.906","rankNumeric":82906,"score":"421,89021","scoreNumeric":421.89021}]},{"university":"İSTANBUL SABAHATTİN ZAİM ÜNİVERSİTESİ","faculty":"Eğitim Fakültesi","city":"İSTANBUL","sector":"Vakıf","program":"İlköğretim Matematik Öğretmenliği (Burslu)","programRaw":"İlköğretim Matematik Öğretmenliği (Burslu) (4 Yıllık)","scoreType":"SAY","years":[{"year":2025,"quota":"4","placed":"5","rank":"168.142","rankNumeric":168142,"score":"353,22225","scoreNumeric":353.22225},{"year":2024,"quota":"6","placed":"7","rank":"218.621","rankNumeric":218621,"score":"316,00219","scoreNumeric":316.00219},{"year":2023,"quota":"6","placed":"7","rank":"95.423","rankNumeric":95423,"score":"412,85478","scoreNumeric":412.85478},{"year":2022,"quota":"7","placed":"7","rank":"92.098","rankNumeric":92098,"score":"412,90449","scoreNumeric":412.90449}]},{"university":"BİRUNİ ÜNİVERSİTESİ","faculty":"Eğitim Fakültesi","city":"İSTANBUL","sector":"Vakıf","program":"İlköğretim Matematik Öğretmenliği (Burslu)","programRaw":"İlköğretim Matematik Öğretmenliği (Burslu) (4 Yıllık)","scoreType":"SAY","years":[{"year":2025,"quota":"5","placed":"6","rank":"171.882","rankNumeric":171882,"score":"351,25535","scoreNumeric":351.25535},{"year":2024,"quota":"4","placed":"4","rank":"143.928","rankNumeric":143928,"score":"352,58410","scoreNumeric":352.5841},{"year":2023,"quota":"7","placed":"8","rank":"107.169","rankNumeric":107169,"score":"402,81587","scoreNumeric":402.81587},{"year":2022,"quota":"8","placed":"8","rank":"91.023","rankNumeric":91023,"score":"413,90301","scoreNumeric":413.90301}]},{"university":"AKDENİZ ÜNİVERSİTESİ","faculty":"Eğitim Fakültesi","city":"ANTALYA","sector":"Devlet","program":"İlköğretim Matematik Öğretmenliği","programRaw":"İlköğretim Matematik Öğretmenliği (4 Yıllık)","scoreType":"SAY","years":[{"year":2025,"quota":"40","placed":"41","rank":"175.784","rankNumeric":175784,"score":"349,26748","scoreNumeric":349.26748},{"year":2024,"quota":"40","placed":"41","rank":"130.728","rankNumeric":130728,"score":"361,00441","scoreNumeric":361.00441},{"year":2023,"quota":"50","placed":"52","rank":"74.459","rankNumeric":74459,"score":"432,67663","scoreNumeric":432.67663},{"year":2022,"quota":"50","placed":"52","rank":"65.675","rankNumeric":65675,"score":"439,92067","scoreNumeric":439.92067}]},{"university":"DOKUZ EYLÜL ÜNİVERSİTESİ","faculty":"Buca Eğitim Fakültesi","city":"İZMİR","sector":"Devlet","program":"İlköğretim Matematik Öğretmenliği","programRaw":"İlköğretim Matematik Öğretmenliği (4 Yıllık)","scoreType":"SAY","years":[{"year":2025,"quota":"50","placed":"52","rank":"183.577","rankNumeric":183577,"score":"345,2642","scoreNumeric":345.2642},{"year":2024,"quota":"50","placed":"52","rank":"163.894","rankNumeric":163894,"score":"340,95336","scoreNumeric":340.95336},{"year":2023,"quota":"70","placed":"72","rank":"76.980","rankNumeric":76980,"score":"430,19393","scoreNumeric":430.19393},{"year":2022,"quota":"70","placed":"72","rank":"69.738","rankNumeric":69738,"score":"435,44080","scoreNumeric":435.4408}]},{"university":"ANADOLU ÜNİVERSİTESİ","faculty":"Eğitim Fakültesi","city":"ESKİŞEHİR","sector":"Devlet","program":"İlköğretim Matematik Öğretmenliği","programRaw":"İlköğretim Matematik Öğretmenliği (4 Yıllık)","scoreType":"SAY","years":[{"year":2025,"quota":"50","placed":"52","rank":"188.056","rankNumeric":188056,"score":"343,10151","scoreNumeric":343.10151},{"year":2024,"quota":"50","placed":"52","rank":"180.713","rankNumeric":180713,"score":"332,34414","scoreNumeric":332.34414},{"year":2023,"quota":"60","placed":"62","rank":"69.871","rankNumeric":69871,"score":"437,45751","scoreNumeric":437.45751},{"year":2022,"quota":"60","placed":"62","rank":"68.328","rankNumeric":68328,"score":"436,98032","scoreNumeric":436.98032}]},{"university":"ÇUKUROVA ÜNİVERSİTESİ","faculty":"Eğitim Fakültesi","city":"ADANA","sector":"Devlet","program":"İlköğretim Matematik Öğretmenliği","programRaw":"İlköğretim Matematik Öğretmenliği (4 Yıllık)","scoreType":"SAY","years":[{"year":2025,"quota":"45","placed":"52","rank":"188.202","rankNumeric":188202,"score":"343,03752","scoreNumeric":343.03752},{"year":2024,"quota":"45","placed":"58","rank":"129.751","rankNumeric":129751,"score":"361,66757","scoreNumeric":361.66757},{"year":2023,"quota":"40","placed":"51","rank":"66.792","rankNumeric":66792,"score":"440,71974","scoreNumeric":440.71974},{"year":2022,"quota":"40","placed":"41","rank":"64.092","rankNumeric":64092,"score":"441,64703","scoreNumeric":441.64703}]},{"university":"GAZİANTEP ÜNİVERSİTESİ","faculty":"Gaziantep Eğitim Fakültesi","city":"GAZİANTEP","sector":"Devlet","program":"İlköğretim Matematik Öğretmenliği","programRaw":"İlköğretim Matematik Öğretmenliği (4 Yıllık)","scoreType":"SAY","years":[{"year":2025,"quota":"50","placed":"57","rank":"190.397","rankNumeric":190397,"score":"341,99606","scoreNumeric":341.99606},{"year":2024,"quota":"50","placed":"65","rank":"138.403","rankNumeric":138403,"score":"355,94253","scoreNumeric":355.94253},{"year":2023,"quota":"50","placed":"65","rank":"76.270","rankNumeric":76270,"score":"430,90143","scoreNumeric":430.90143},{"year":2022,"quota":"50","placed":"52","rank":"75.045","rankNumeric":75045,"score":"429,79322","scoreNumeric":429.79322}]},{"university":"İSTANBUL AYDIN ÜNİVERSİTESİ","faculty":"Eğitim Fakültesi","city":"İSTANBUL","sector":"Vakıf","program":"İlköğretim Matematik Öğretmenliği (Burslu)","programRaw":"İlköğretim Matematik Öğretmenliği (Burslu) (4 Yıllık)","scoreType":"SAY","years":[{"year":2025,"quota":"4","placed":"5","rank":"191.667","rankNumeric":191667,"score":"341,40225","scoreNumeric":341.40225},{"year":2024,"quota":"4","placed":"5","rank":"155.190","rankNumeric":155190,"score":"345,79270","scoreNumeric":345.7927},{"year":2023,"quota":"7","placed":"8","rank":"104.206","rankNumeric":104206,"score":"405,28649","scoreNumeric":405.28649},{"year":2022,"quota":"8","placed":"8","rank":"95.437","rankNumeric":95437,"score":"409,77245","scoreNumeric":409.77245}]},{"university":"MALTEPE ÜNİVERSİTESİ","faculty":"Eğitim Fakültesi","city":"İSTANBUL","sector":"Vakıf","program":"İlköğretim Matematik Öğretmenliği (Burslu)","programRaw":"İlköğretim Matematik Öğretmenliği (Burslu) (4 Yıllık)","scoreType":"SAY","years":[{"year":2025,"quota":"2","placed":"3","rank":"192.836","rankNumeric":192836,"score":"340,8745","scoreNumeric":340.8745},{"year":2024,"quota":"2","placed":"2","rank":"142.187","rankNumeric":142187,"score":"353,62846","scoreNumeric":353.62846},{"year":2023,"quota":"3","placed":"4","rank":"108.468","rankNumeric":108468,"score":"401,78531","scoreNumeric":401.78531},{"year":2022,"quota":"7","placed":"7","rank":"98.267","rankNumeric":98267,"score":"407,13156","scoreNumeric":407.13156}]},{"university":"BURSA ULUDAĞ ÜNİVERSİTESİ","faculty":"Eğitim Fakültesi","city":"BURSA","sector":"Devlet","program":"İlköğretim Matematik Öğretmenliği","programRaw":"İlköğretim Matematik Öğretmenliği (4 Yıllık)","scoreType":"SAY","years":[{"year":2025,"quota":"45","placed":"47","rank":"200.890","rankNumeric":200890,"score":"337,22763","scoreNumeric":337.22763},{"year":2024,"quota":"45","placed":"47","rank":"206.596","rankNumeric":206596,"score":"320,78107","scoreNumeric":320.78107},{"year":2023,"quota":"40","placed":"41","rank":"76.784","rankNumeric":76784,"score":"430,39848","scoreNumeric":430.39848},{"year":2022,"quota":"40","placed":"41","rank":"70.592","rankNumeric":70592,"score":"434,48255","scoreNumeric":434.48255}]},{"university":"SELÇUK ÜNİVERSİTESİ","faculty":"Eğitim Fakültesi","city":"KONYA","sector":"Devlet","program":"İlköğretim Matematik Öğretmenliği","programRaw":"İlköğretim Matematik Öğretmenliği (4 Yıllık)","scoreType":"SAY","years":[{"year":2025,"quota":"45","placed":"47","rank":"210.703","rankNumeric":210703,"score":"332,96348","scoreNumeric":332.96348},{"year":2024,"quota":"45","placed":"47","rank":"199.555","rankNumeric":199555,"score":"323,75422","scoreNumeric":323.75422},{"year":2023,"quota":"40","placed":"41","rank":"77.861","rankNumeric":77861,"score":"429,34900","scoreNumeric":429.349},{"year":2022,"quota":"40","placed":"41","rank":"76.391","rankNumeric":76391,"score":"428,39980","scoreNumeric":428.3998}]},{"university":"İSTANBUL ÜNİVERSİTESİ-CERRAHPAŞA Hasan Ali Yücel Eğitim Fakültesi","faculty":null,"city":"İSTANBUL","sector":"Devlet","program":"İlköğretim Matematik Öğretmenliği","programRaw":"İlköğretim Matematik Öğretmenliği (4 Yıllık)","scoreType":"SAY","years":[{"year":2025,"quota":"50","placed":"52","rank":"216.849","rankNumeric":216849,"score":"330,37043","scoreNumeric":330.37043},{"year":2024,"quota":"50","placed":"52","rank":"246.389","rankNumeric":246389,"score":"305,95754","scoreNumeric":305.95754},{"year":2023,"quota":"60","placed":"62","rank":"95.032","rankNumeric":95032,"score":"413,16943","scoreNumeric":413.16943},{"year":2022,"quota":"60","placed":"62","rank":"81.011","rankNumeric":81011,"score":"423,76501","scoreNumeric":423.76501}]},{"university":"İSTANBUL 29 MAYIS ÜNİVERSİTESİ","faculty":"Eğitim Fakültesi","city":"İSTANBUL","sector":"Vakıf","program":"İlköğretim Matematik Öğretmenliği (Burslu)","programRaw":"İlköğretim Matematik Öğretmenliği (Burslu) (4 Yıllık)","scoreType":"SAY","years":[{"year":2025,"quota":"5","placed":"6","rank":"217.705","rankNumeric":217705,"score":"330,03339","scoreNumeric":330.03339},{"year":2024,"quota":"7","placed":"7","rank":"281.620","rankNumeric":281620,"score":"295,18131","scoreNumeric":295.18131},{"year":2023,"quota":"9","placed":"10","rank":"104.264","rankNumeric":104264,"score":"405,23654","scoreNumeric":405.23654},{"year":2022,"quota":"6","placed":"6","rank":"101.166","rankNumeric":101166,"score":"404,43009","scoreNumeric":404.43009}]},{"university":"ONDOKUZ MAYIS ÜNİVERSİTESİ","faculty":"Eğitim Fakültesi","city":"SAMSUN","sector":"Devlet","program":"İlköğretim Matematik Öğretmenliği","programRaw":"İlköğretim Matematik Öğretmenliği (4 Yıllık)","scoreType":"SAY","years":[{"year":2025,"quota":"50","placed":"52","rank":"225.142","rankNumeric":225142,"score":"327,06618","scoreNumeric":327.06618},{"year":2024,"quota":"50","placed":"52","rank":"225.453","rankNumeric":225453,"score":"313,40850","scoreNumeric":313.4085},{"year":2023,"quota":"50","placed":"52","rank":"80.697","rankNumeric":80697,"score":"426,60201","scoreNumeric":426.60201},{"year":2022,"quota":"50","placed":"52","rank":"75.285","rankNumeric":75285,"score":"429,53802","scoreNumeric":429.53802}]},{"university":"ERCİYES ÜNİVERSİTESİ","faculty":"Eğitim Fakültesi","city":"KAYSERİ","sector":"Devlet","program":"İlköğretim Matematik Öğretmenliği","programRaw":"İlköğretim Matematik Öğretmenliği (4 Yıllık)","scoreType":"SAY","years":[{"year":2025,"quota":"50","placed":"52","rank":"226.330","rankNumeric":226330,"score":"326,60837","scoreNumeric":326.60837},{"year":2024,"quota":"50","placed":"52","rank":"219.411","rankNumeric":219411,"score":"315,69033","scoreNumeric":315.69033},{"year":2023,"quota":"60","placed":"62","rank":"76.605","rankNumeric":76605,"score":"430,58504","scoreNumeric":430.58504},{"year":2022,"quota":"60","placed":"62","rank":"74.947","rankNumeric":74947,"score":"429,89474","scoreNumeric":429.89474}]},{"university":"MERSİN ÜNİVERSİTESİ","faculty":"Eğitim Fakültesi","city":"MERSİN","sector":"Devlet","program":"İlköğretim Matematik Öğretmenliği","programRaw":"İlköğretim Matematik Öğretmenliği (4 Yıllık)","scoreType":"SAY","years":[{"year":2025,"quota":"50","placed":"52","rank":"226.383","rankNumeric":226383,"score":"326,58483","scoreNumeric":326.58483},{"year":2024,"quota":"50","placed":"52","rank":"269.153","rankNumeric":269153,"score":"298,77692","scoreNumeric":298.77692},{"year":2023,"quota":"50","placed":"52","rank":"79.365","rankNumeric":79365,"score":"427,88821","scoreNumeric":427.88821},{"year":2022,"quota":"50","placed":"52","rank":"72.529","rankNumeric":72529,"score":"432,41946","scoreNumeric":432.41946}]},{"university":"PAMUKKALE ÜNİVERSİTESİ","faculty":"Eğitim Fakültesi","city":"DENİZLİ","sector":"Devlet","program":"İlköğretim Matematik Öğretmenliği","programRaw":"İlköğretim Matematik Öğretmenliği (4 Yıllık)","scoreType":"SAY","years":[{"year":2025,"quota":"45","placed":"47","rank":"226.919","rankNumeric":226919,"score":"326,37478","scoreNumeric":326.37478},{"year":2024,"quota":"45","placed":"47","rank":"214.144","rankNumeric":214144,"score":"317,75423","scoreNumeric":317.75423},{"year":2023,"quota":"40","placed":"41","rank":"82.970","rankNumeric":82970,"score":"424,39538","scoreNumeric":424.39538},{"year":2022,"quota":"40","placed":"41","rank":"76.595","rankNumeric":76595,"score":"428,19207","scoreNumeric":428.19207}]},{"university":"DİCLE ÜNİVERSİTESİ","faculty":"Ziya Gökalp Eğitim Fakültesi","city":"DİYARBAKIR","sector":"Devlet","program":"İlköğretim Matematik Öğretmenliği","programRaw":"İlköğretim Matematik Öğretmenliği (4 Yıllık)","scoreType":"SAY","years":[{"year":2025,"quota":"45","placed":"52","rank":"228.653","rankNumeric":228653,"score":"325,72016","scoreNumeric":325.72016},{"year":2024,"quota":"45","placed":"58","rank":"182.858","rankNumeric":182858,"score":"331,31734","scoreNumeric":331.31734},{"year":2023,"quota":"40","placed":"51","rank":"72.669","rankNumeric":72669,"score":"434,50367","scoreNumeric":434.50367},{"year":2022,"quota":"40","placed":"41","rank":"67.807","rankNumeric":67807,"score":"437,52535","scoreNumeric":437.52535}]},{"university":"NECMETTİN ERBAKAN ÜNİVERSİTESİ","faculty":"Ahmet Keleşoğlu Eğitim Fakültesi","city":"KONYA","sector":"Devlet","program":"İlköğretim Matematik Öğretmenliği","programRaw":"İlköğretim Matematik Öğretmenliği (4 Yıllık)","scoreType":"SAY","years":[{"year":2025,"quota":"30","placed":"31","rank":"229.799","rankNumeric":229799,"score":"325,30582","scoreNumeric":325.30582},{"year":2024,"quota":"30","placed":"31","rank":"204.090","rankNumeric":204090,"score":"321,83492","scoreNumeric":321.83492},{"year":2023,"quota":"60","placed":"62","rank":"85.303","rankNumeric":85303,"score":"422,22402","scoreNumeric":422.22402},{"year":2022,"quota":"60","placed":"62","rank":"83.538","rankNumeric":83538,"score":"421,23298","scoreNumeric":421.23298}]},{"university":"İSTANBUL MEDENİYET ÜNİVERSİTESİ","faculty":"Eğitim Bilimleri Fakültesi","city":"İSTANBUL","sector":"Devlet","program":"İlköğretim Matematik Öğretmenliği","programRaw":"İlköğretim Matematik Öğretmenliği (4 Yıllık)","scoreType":"SAY","years":[{"year":2025,"quota":"50","placed":"52","rank":"232.484","rankNumeric":232484,"score":"324,29083","scoreNumeric":324.29083},{"year":2024,"quota":"50","placed":"45","rank":"Dolmadı","rankNumeric":null,"score":"Dolmadı","scoreNumeric":null},{"year":2023,"quota":"50","placed":"52","rank":"103.068","rankNumeric":103068,"score":"406,22859","scoreNumeric":406.22859},{"year":2022,"quota":"50","placed":"52","rank":"88.858","rankNumeric":88858,"score":"415,89598","scoreNumeric":415.89598}]},{"university":"ESKİŞEHİR OSMANGAZİ ÜNİVERSİTESİ","faculty":"Eğitim Fakültesi","city":"ESKİŞEHİR","sector":"Devlet","program":"İlköğretim Matematik Öğretmenliği","programRaw":"İlköğretim Matematik Öğretmenliği (4 Yıllık)","scoreType":"SAY","years":[{"year":2025,"quota":"50","placed":"52","rank":"233.959","rankNumeric":233959,"score":"323,76437","scoreNumeric":323.76437},{"year":2024,"quota":"50","placed":"41","rank":"Dolmadı","rankNumeric":null,"score":"Dolmadı","scoreNumeric":null},{"year":2023,"quota":"50","placed":"52","rank":"80.021","rankNumeric":80021,"score":"427,25800","scoreNumeric":427.258},{"year":2022,"quota":"50","placed":"52","rank":"73.651","rankNumeric":73651,"score":"431,28687","scoreNumeric":431.28687}]},{"university":"MUĞLA SITKI KOÇMAN ÜNİVERSİTESİ","faculty":"Eğitim Fakültesi","city":"MUĞLA","sector":"Devlet","program":"İlköğretim Matematik Öğretmenliği","programRaw":"İlköğretim Matematik Öğretmenliği (4 Yıllık)","scoreType":"SAY","years":[{"year":2025,"quota":"20","placed":"21","rank":"249.654","rankNumeric":249654,"score":"318,071","scoreNumeric":318.071},{"year":2024,"quota":"45","placed":"13","rank":"Dolmadı","rankNumeric":null,"score":"Dolmadı","scoreNumeric":null},{"year":2023,"quota":"40","placed":"41","rank":"89.993","rankNumeric":89993,"score":"417,74724","scoreNumeric":417.74724},{"year":2022,"quota":"40","placed":"41","rank":"84.822","rankNumeric":84822,"score":"419,84894","scoreNumeric":419.84894}]},{"university":"KOCAELİ ÜNİVERSİTESİ","faculty":"Eğitim Fakültesi","city":"KOCAELİ","sector":"Devlet","program":"İlköğretim Matematik Öğretmenliği","programRaw":"İlköğretim Matematik Öğretmenliği (4 Yıllık)","scoreType":"SAY","years":[{"year":2025,"quota":"40","placed":"41","rank":"250.894","rankNumeric":250894,"score":"317,63983","scoreNumeric":317.63983},{"year":2024,"quota":"50","placed":"32","rank":"Dolmadı","rankNumeric":null,"score":"Dolmadı","scoreNumeric":null},{"year":2023,"quota":"50","placed":"52","rank":"92.646","rankNumeric":92646,"score":"415,31145","scoreNumeric":415.31145},{"year":2022,"quota":"50","placed":"52","rank":"87.010","rankNumeric":87010,"score":"417,74554","scoreNumeric":417.74554}]},{"university":"ATATÜRK ÜNİVERSİTESİ","faculty":"Kazım Karabekir Eğitim Fakültesi","city":"ERZURUM","sector":"Devlet","program":"İlköğretim Matematik Öğretmenliği","programRaw":"İlköğretim Matematik Öğretmenliği (4 Yıllık)","scoreType":"SAY","years":[{"year":2025,"quota":"50","placed":"52","rank":"253.096","rankNumeric":253096,"score":"316,87684","scoreNumeric":316.87684},{"year":2024,"quota":"50","placed":"52","rank":"260.323","rankNumeric":260323,"score":"301,44105","scoreNumeric":301.44105},{"year":2023,"quota":"70","placed":"72","rank":"107.027","rankNumeric":107027,"score":"402,93851","scoreNumeric":402.93851},{"year":2022,"quota":"60","placed":"62","rank":"99.461","rankNumeric":99461,"score":"406,04248","scoreNumeric":406.04248}]},{"university":"İNÖNÜ ÜNİVERSİTESİ","faculty":"Eğitim Fakültesi","city":"MALATYA","sector":"Devlet","program":"İlköğretim Matematik Öğretmenliği","programRaw":"İlköğretim Matematik Öğretmenliği (4 Yıllık)","scoreType":"SAY","years":[{"year":2025,"quota":"50","placed":"57","rank":"261.222","rankNumeric":261222,"score":"314,169","scoreNumeric":314.169},{"year":2024,"quota":"50","placed":"50","rank":"Dolmadı","rankNumeric":null,"score":"Dolmadı","scoreNumeric":null},{"year":2023,"quota":"50","placed":"65","rank":"93.913","rankNumeric":93913,"score":"414,16397","scoreNumeric":414.16397},{"year":2022,"quota":"50","placed":"52","rank":"76.800","rankNumeric":76800,"score":"427,98024","scoreNumeric":427.98024}]},{"university":"BALIKESİR ÜNİVERSİTESİ","faculty":"Necatibey Eğitim Fakültesi","city":"BALIKESİR","sector":"Devlet","program":"İlköğretim Matematik Öğretmenliği","programRaw":"İlköğretim Matematik Öğretmenliği (4 Yıllık)","scoreType":"SAY","years":[{"year":2025,"quota":"40","placed":"41","rank":"265.186","rankNumeric":265186,"score":"312,86961","scoreNumeric":312.86961},{"year":2024,"quota":"50","placed":"29","rank":"Dolmadı","rankNumeric":null,"score":"Dolmadı","scoreNumeric":null},{"year":2023,"quota":"60","placed":"62","rank":"99.344","rankNumeric":99344,"score":"409,42254","scoreNumeric":409.42254},{"year":2022,"quota":"50","placed":"52","rank":"91.338","rankNumeric":91338,"score":"413,61753","scoreNumeric":413.61753}]},{"university":"ÇANAKKALE ONSEKİZ MART ÜNİVERSİTESİ","faculty":"Eğitim Fakültesi","city":"ÇANAKKALE","sector":"Devlet","program":"İlköğretim Matematik Öğretmenliği","programRaw":"İlköğretim Matematik Öğretmenliği (4 Yıllık)","scoreType":"SAY","years":[{"year":2025,"quota":"40","placed":"41","rank":"265.676","rankNumeric":265676,"score":"312,71243","scoreNumeric":312.71243},{"year":2024,"quota":"45","placed":"29","rank":"Dolmadı","rankNumeric":null,"score":"Dolmadı","scoreNumeric":null},{"year":2023,"quota":"40","placed":"41","rank":"90.619","rankNumeric":90619,"score":"417,17973","scoreNumeric":417.17973},{"year":2022,"quota":"40","placed":"41","rank":"86.418","rankNumeric":86418,"score":"418,32905","scoreNumeric":418.32905}]},{"university":"SÜLEYMAN DEMİREL ÜNİVERSİTESİ","faculty":"Eğitim Fakültesi","city":"ISPARTA","sector":"Devlet","program":"İlköğretim Matematik Öğretmenliği","programRaw":"İlköğretim Matematik Öğretmenliği (4 Yıllık)","scoreType":"SAY","years":[{"year":2025,"quota":"30","placed":"31","rank":"268.627","rankNumeric":268627,"score":"311,78007","scoreNumeric":311.78007},{"year":2024,"quota":"30","placed":"24","rank":"Dolmadı","rankNumeric":null,"score":"Dolmadı","scoreNumeric":null},{"year":2023,"quota":"50","placed":"52","rank":"87.569","rankNumeric":87569,"score":"420,00579","scoreNumeric":420.00579},{"year":2022,"quota":"50","placed":"52","rank":"88.881","rankNumeric":88881,"score":"415,86885","scoreNumeric":415.86885}]},{"university":"AYDIN ADNAN MENDERES ÜNİVERSİTESİ","faculty":"Eğitim Fakültesi","city":"AYDIN","sector":"Devlet","program":"İlköğretim Matematik Öğretmenliği","programRaw":"İlköğretim Matematik Öğretmenliği (4 Yıllık)","scoreType":"SAY","years":[{"year":2025,"quota":"25","placed":"26","rank":"268.641","rankNumeric":268641,"score":"311,77645","scoreNumeric":311.77645},{"year":2024,"quota":"45","placed":"20","rank":"Dolmadı","rankNumeric":null,"score":"Dolmadı","scoreNumeric":null},{"year":2023,"quota":"40","placed":"41","rank":"85.603","rankNumeric":85603,"score":"421,94170","scoreNumeric":421.9417},{"year":2022,"quota":"40","placed":"41","rank":"80.480","rankNumeric":80480,"score":"424,28729","scoreNumeric":424.28729}]},{"university":"ALANYA ALAADDİN KEYKUBAT ÜNİVERSİTESİ","faculty":"Eğitim Fakültesi","city":"ANTALYA","sector":"Devlet","program":"İlköğretim Matematik Öğretmenliği","programRaw":"İlköğretim Matematik Öğretmenliği (4 Yıllık)","scoreType":"SAY","years":[{"year":2025,"quota":"35","placed":"36","rank":"270.962","rankNumeric":270962,"score":"311,0634","scoreNumeric":311.0634},{"year":2024,"quota":"50","placed":"28","rank":"Dolmadı","rankNumeric":null,"score":"Dolmadı","scoreNumeric":null},{"year":2023,"quota":"50","placed":"52","rank":"101.045","rankNumeric":101045,"score":"407,98192","scoreNumeric":407.98192},{"year":2022,"quota":"50","placed":"52","rank":"96.037","rankNumeric":96037,"score":"409,19931","scoreNumeric":409.19931}]},{"university":"FIRAT ÜNİVERSİTESİ","faculty":"Eğitim Fakültesi","city":"ELAZIĞ","sector":"Devlet","program":"İlköğretim Matematik Öğretmenliği","programRaw":"İlköğretim Matematik Öğretmenliği (4 Yıllık)","scoreType":"SAY","years":[{"year":2025,"quota":"40","placed":"45","rank":"272.802","rankNumeric":272802,"score":"310,45793","scoreNumeric":310.45793},{"year":2024,"quota":"50","placed":"34","rank":"Dolmadı","rankNumeric":null,"score":"Dolmadı","scoreNumeric":null},{"year":2023,"quota":"50","placed":"65","rank":"98.037","rankNumeric":98037,"score":"410,59641","scoreNumeric":410.59641},{"year":2022,"quota":"50","placed":"52","rank":"84.737","rankNumeric":84737,"score":"419,92384","scoreNumeric":419.92384}]},{"university":"NİĞDE ÖMER HALİSDEMİR ÜNİVERSİTESİ","faculty":"Eğitim Fakültesi","city":"NİĞDE","sector":"Devlet","program":"İlköğretim Matematik Öğretmenliği","programRaw":"İlköğretim Matematik Öğretmenliği (4 Yıllık)","scoreType":"SAY","years":[{"year":2025,"quota":"25","placed":"26","rank":"273.246","rankNumeric":273246,"score":"310,31659","scoreNumeric":310.31659},{"year":2024,"quota":"50","placed":"17","rank":"Dolmadı","rankNumeric":null,"score":"Dolmadı","scoreNumeric":null},{"year":2023,"quota":"50","placed":"52","rank":"100.965","rankNumeric":100965,"score":"408,06068","scoreNumeric":408.06068},{"year":2022,"quota":"50","placed":"52","rank":"98.215","rankNumeric":98215,"score":"407,17938","scoreNumeric":407.17938}]},{"university":"HARRAN ÜNİVERSİTESİ","faculty":"Eğitim Fakültesi","city":"ŞANLIURFA","sector":"Devlet","program":"İlköğretim Matematik Öğretmenliği","programRaw":"İlköğretim Matematik Öğretmenliği (4 Yıllık)","scoreType":"SAY","years":[{"year":2025,"quota":"50","placed":"57","rank":"273.293","rankNumeric":273293,"score":"310,30155","scoreNumeric":310.30155},{"year":2024,"quota":"50","placed":"58","rank":"281.040","rankNumeric":281040,"score":"295,33768","scoreNumeric":295.33768},{"year":2023,"quota":"50","placed":"65","rank":"100.033","rankNumeric":100033,"score":"408,85217","scoreNumeric":408.85217},{"year":2022,"quota":"50","placed":"52","rank":"95.642","rankNumeric":95642,"score":"409,57869","scoreNumeric":409.57869}]},{"university":"BOLU ABANT İZZET BAYSAL ÜNİVERSİTESİ","faculty":"Eğitim Fakültesi","city":"BOLU","sector":"Devlet","program":"İlköğretim Matematik Öğretmenliği","programRaw":"İlköğretim Matematik Öğretmenliği (4 Yıllık)","scoreType":"SAY","years":[{"year":2025,"quota":"35","placed":"36","rank":"273.973","rankNumeric":273973,"score":"310,09238","scoreNumeric":310.09238},{"year":2024,"quota":"40","placed":"31","rank":"Dolmadı","rankNumeric":null,"score":"Dolmadı","scoreNumeric":null},{"year":2023,"quota":"50","placed":"52","rank":"100.372","rankNumeric":100372,"score":"408,55776","scoreNumeric":408.55776},{"year":2022,"quota":"50","placed":"52","rank":"95.924","rankNumeric":95924,"score":"409,31554","scoreNumeric":409.31554}]},{"university":"HATAY MUSTAFA KEMAL ÜNİVERSİTESİ","faculty":"Eğitim Fakültesi","city":"HATAY","sector":"Devlet","program":"İlköğretim Matematik Öğretmenliği","programRaw":"İlköğretim Matematik Öğretmenliği (4 Yıllık)","scoreType":"SAY","years":[{"year":2025,"quota":"35","placed":"40","rank":"277.629","rankNumeric":277629,"score":"308,97985","scoreNumeric":308.97985},{"year":2024,"quota":"35","placed":"36","rank":"288.999","rankNumeric":288999,"score":"293,09348","scoreNumeric":293.09348},{"year":2023,"quota":"30","placed":"39","rank":"130.355","rankNumeric":130355,"score":"385,02277","scoreNumeric":385.02277},{"year":2022,"quota":"40","placed":"41","rank":"85.738","rankNumeric":85738,"score":"418,97352","scoreNumeric":418.97352}]},{"university":"DÜZCE ÜNİVERSİTESİ","faculty":"Eğitim Fakültesi","city":"DÜZCE","sector":"Devlet","program":"İlköğretim Matematik Öğretmenliği","programRaw":"İlköğretim Matematik Öğretmenliği (4 Yıllık)","scoreType":"SAY","years":[{"year":2025,"quota":"15","placed":"16","rank":"279.770","rankNumeric":279770,"score":"308,31533","scoreNumeric":308.31533},{"year":2024,"quota":"50","placed":"12","rank":"Dolmadı","rankNumeric":null,"score":"Dolmadı","scoreNumeric":null},{"year":2023,"quota":"50","placed":"52","rank":"121.747","rankNumeric":121747,"score":"391,33787","scoreNumeric":391.33787},{"year":2022,"quota":"50","placed":"52","rank":"112.189","rankNumeric":112189,"score":"394,67012","scoreNumeric":394.67012}]},{"university":"KIRIKKALE ÜNİVERSİTESİ","faculty":"Eğitim Fakültesi","city":"KIRIKKALE","sector":"Devlet","program":"İlköğretim Matematik Öğretmenliği","programRaw":"İlköğretim Matematik Öğretmenliği (4 Yıllık)","scoreType":"SAY","years":[{"year":2025,"quota":"25","placed":"26","rank":"279.913","rankNumeric":279913,"score":"308,28422","scoreNumeric":308.28422},{"year":2024,"quota":"45","placed":"22","rank":"Dolmadı","rankNumeric":null,"score":"Dolmadı","scoreNumeric":null},{"year":2023,"quota":"40","placed":"41","rank":"106.330","rankNumeric":106330,"score":"403,52876","scoreNumeric":403.52876},{"year":2022,"quota":"40","placed":"41","rank":"99.053","rankNumeric":99053,"score":"406,43235","scoreNumeric":406.43235}]},{"university":"TRAKYA ÜNİVERSİTESİ","faculty":"Eğitim Fakültesi","city":"EDİRNE","sector":"Devlet","program":"İlköğretim Matematik Öğretmenliği","programRaw":"İlköğretim Matematik Öğretmenliği (4 Yıllık)","scoreType":"SAY","years":[{"year":2025,"quota":"20","placed":"21","rank":"283.389","rankNumeric":283389,"score":"307,22227","scoreNumeric":307.22227},{"year":2024,"quota":"45","placed":"16","rank":"Dolmadı","rankNumeric":null,"score":"Dolmadı","scoreNumeric":null},{"year":2023,"quota":"40","placed":"41","rank":"117.501","rankNumeric":117501,"score":"394,62062","scoreNumeric":394.62062},{"year":2022,"quota":"40","placed":"41","rank":"108.924","rankNumeric":108924,"score":"397,51509","scoreNumeric":397.51509}]},{"university":"TRABZON ÜNİVERSİTESİ","faculty":"Fatih Eğitim Fakültesi","city":"TRABZON","sector":"Devlet","program":"İlköğretim Matematik Öğretmenliği","programRaw":"İlköğretim Matematik Öğretmenliği (4 Yıllık)","scoreType":"SAY","years":[{"year":2025,"quota":"25","placed":"26","rank":"283.975","rankNumeric":283975,"score":"307,04567","scoreNumeric":307.04567},{"year":2024,"quota":"50","placed":"20","rank":"Dolmadı","rankNumeric":null,"score":"Dolmadı","scoreNumeric":null},{"year":2023,"quota":"50","placed":"52","rank":"112.972","rankNumeric":112972,"score":"398,16017","scoreNumeric":398.16017},{"year":2022,"quota":"50","placed":"52","rank":"101.684","rankNumeric":101684,"score":"403,96416","scoreNumeric":403.96416}]},{"university":"AFYON KOCATEPE ÜNİVERSİTESİ","faculty":"Eğitim Fakültesi","city":"AFYONKARAHİSAR","sector":"Devlet","program":"İlköğretim Matematik Öğretmenliği","programRaw":"İlköğretim Matematik Öğretmenliği (4 Yıllık)","scoreType":"SAY","years":[{"year":2025,"quota":"20","placed":"21","rank":"284.239","rankNumeric":284239,"score":"306,96559","scoreNumeric":306.96559},{"year":2024,"quota":"50","placed":"18","rank":"Dolmadı","rankNumeric":null,"score":"Dolmadı","scoreNumeric":null},{"year":2023,"quota":"50","placed":"52","rank":"101.959","rankNumeric":101959,"score":"407,15659","scoreNumeric":407.15659},{"year":2022,"quota":"50","placed":"52","rank":"98.048","rankNumeric":98048,"score":"407,32092","scoreNumeric":407.32092}]},{"university":"ORDU ÜNİVERSİTESİ","faculty":"Eğitim Fakültesi","city":"ORDU","sector":"Devlet","program":"İlköğretim Matematik Öğretmenliği","programRaw":"İlköğretim Matematik Öğretmenliği (4 Yıllık)","scoreType":"SAY","years":[{"year":2025,"quota":"15","placed":"16","rank":"285.334","rankNumeric":285334,"score":"306,63926","scoreNumeric":306.63926},{"year":2024,"quota":"40","placed":"11","rank":"Dolmadı","rankNumeric":null,"score":"Dolmadı","scoreNumeric":null},{"year":2023,"quota":"50","placed":"52","rank":"112.252","rankNumeric":112252,"score":"398,74745","scoreNumeric":398.74745},{"year":2022,"quota":"50","placed":"52","rank":"104.527","rankNumeric":104527,"score":"401,38025","scoreNumeric":401.38025}]},{"university":"VAN YÜZÜNCÜ YIL ÜNİVERSİTESİ","faculty":"Eğitim Fakültesi","city":"VAN","sector":"Devlet","program":"İlköğretim Matematik Öğretmenliği","programRaw":"İlköğretim Matematik Öğretmenliği (4 Yıllık)","scoreType":"SAY","years":[{"year":2025,"quota":"45","placed":"47","rank":"286.659","rankNumeric":286659,"score":"306,24945","scoreNumeric":306.24945},{"year":2024,"quota":"45","placed":"39","rank":"Dolmadı","rankNumeric":null,"score":"Dolmadı","scoreNumeric":null},{"year":2023,"quota":"40","placed":"41","rank":"89.659","rankNumeric":89659,"score":"418,04377","scoreNumeric":418.04377},{"year":2022,"quota":"40","placed":"41","rank":"86.958","rankNumeric":86958,"score":"417,79336","scoreNumeric":417.79336}]},{"university":"KAHRAMANMARAŞ SÜTÇÜ İMAM ÜNİVERSİTESİ","faculty":"Eğitim Fakültesi","city":"KAHRAMANMARAŞ","sector":"Devlet","program":"İlköğretim Matematik Öğretmenliği","programRaw":"İlköğretim Matematik Öğretmenliği (4 Yıllık)","scoreType":"SAY","years":[{"year":2025,"quota":"40","placed":"45","rank":"287.895","rankNumeric":287895,"score":"305,89082","scoreNumeric":305.89082},{"year":2024,"quota":"45","placed":"35","rank":"Dolmadı","rankNumeric":null,"score":"Dolmadı","scoreNumeric":null},{"year":2023,"quota":"40","placed":"51","rank":"102.085","rankNumeric":102085,"score":"407,05329","scoreNumeric":407.05329},{"year":2022,"quota":"40","placed":"41","rank":"81.612","rankNumeric":81612,"score":"423,19999","scoreNumeric":423.19999}]},{"university":"ADIYAMAN ÜNİVERSİTESİ","faculty":"Eğitim Fakültesi","city":"ADIYAMAN","sector":"Devlet","program":"İlköğretim Matematik Öğretmenliği","programRaw":"İlköğretim Matematik Öğretmenliği (4 Yıllık)","scoreType":"SAY","years":[{"year":2025,"quota":"30","placed":"34","rank":"288.533","rankNumeric":288533,"score":"305,69571","scoreNumeric":305.69571},{"year":2024,"quota":"30","placed":"25","rank":"Dolmadı","rankNumeric":null,"score":"Dolmadı","scoreNumeric":null},{"year":2023,"quota":"25","placed":"32","rank":"108.842","rankNumeric":108842,"score":"401,46606","scoreNumeric":401.46606},{"year":2022,"quota":"50","placed":"52","rank":"94.183","rankNumeric":94183,"score":"410,95769","scoreNumeric":410.95769}]},{"university":"SAKARYA ÜNİVERSİTESİ","faculty":"Eğitim Fakültesi (Hendek)","city":"SAKARYA","sector":"Devlet","program":"İlköğretim Matematik Öğretmenliği","programRaw":"İlköğretim Matematik Öğretmenliği (4 Yıllık)","scoreType":"SAY","years":[{"year":2025,"quota":"35","placed":"36","rank":"290.154","rankNumeric":290154,"score":"305,22396","scoreNumeric":305.22396},{"year":2024,"quota":"50","placed":"29","rank":"Dolmadı","rankNumeric":null,"score":"Dolmadı","scoreNumeric":null},{"year":2023,"quota":"52","placed":"54","rank":"110.899","rankNumeric":110899,"score":"399,82259","scoreNumeric":399.82259},{"year":2022,"quota":"50","placed":"52","rank":"100.554","rankNumeric":100554,"score":"404,99452","scoreNumeric":404.99452}]},{"university":"BURDUR MEHMET AKİF ERSOY ÜNİVERSİTESİ","faculty":"Eğitim Fakültesi","city":"BURDUR","sector":"Devlet","program":"İlköğretim Matematik Öğretmenliği","programRaw":"İlköğretim Matematik Öğretmenliği (4 Yıllık)","scoreType":"SAY","years":[{"year":2025,"quota":"20","placed":"21","rank":"291.527","rankNumeric":291527,"score":"304,82098","scoreNumeric":304.82098},{"year":2024,"quota":"50","placed":"15","rank":"Dolmadı","rankNumeric":null,"score":"Dolmadı","scoreNumeric":null},{"year":2023,"quota":"60","placed":"62","rank":"118.883","rankNumeric":118883,"score":"393,55890","scoreNumeric":393.5589},{"year":2022,"quota":"50","placed":"52","rank":"106.289","rankNumeric":106289,"score":"399,81263","scoreNumeric":399.81263}]},{"university":"NEVŞEHİR HACI BEKTAŞ VELİ ÜNİVERSİTESİ","faculty":"Eğitim Fakültesi","city":"NEVŞEHİR","sector":"Devlet","program":"İlköğretim Matematik Öğretmenliği","programRaw":"İlköğretim Matematik Öğretmenliği (4 Yıllık)","scoreType":"SAY","years":[{"year":2025,"quota":"25","placed":"26","rank":"292.311","rankNumeric":292311,"score":"304,58977","scoreNumeric":304.58977},{"year":2024,"quota":"45","placed":"14","rank":"Dolmadı","rankNumeric":null,"score":"Dolmadı","scoreNumeric":null},{"year":2023,"quota":"40","placed":"41","rank":"90.453","rankNumeric":90453,"score":"417,33375","scoreNumeric":417.33375},{"year":2022,"quota":"40","placed":"41","rank":"91.186","rankNumeric":91186,"score":"413,76215","scoreNumeric":413.76215}]},{"university":"AKSARAY ÜNİVERSİTESİ","faculty":"Eğitim Fakültesi","city":"AKSARAY","sector":"Devlet","program":"İlköğretim Matematik Öğretmenliği","programRaw":"İlköğretim Matematik Öğretmenliği (4 Yıllık)","scoreType":"SAY","years":[{"year":2025,"quota":"15","placed":"16","rank":"292.864","rankNumeric":292864,"score":"304,4444","scoreNumeric":304.4444},{"year":2024,"quota":"40","placed":"12","rank":"Dolmadı","rankNumeric":null,"score":"Dolmadı","scoreNumeric":null},{"year":2023,"quota":"50","placed":"52","rank":"113.916","rankNumeric":113916,"score":"397,45174","scoreNumeric":397.45174},{"year":2022,"quota":"50","placed":"52","rank":"104.589","rankNumeric":104589,"score":"401,32391","scoreNumeric":401.32391}]},{"university":"ZONGULDAK BÜLENT ECEVİT ÜNİVERSİTESİ","faculty":"Ereğli Eğitim Fakültesi","city":"ZONGULDAK","sector":"Devlet","program":"İlköğretim Matematik Öğretmenliği","programRaw":"İlköğretim Matematik Öğretmenliği (4 Yıllık)","scoreType":"SAY","years":[{"year":2025,"quota":"10","placed":"11","rank":"297.291","rankNumeric":297291,"score":"303,18872","scoreNumeric":303.18872},{"year":2024,"quota":"50","placed":"10","rank":"Dolmadı","rankNumeric":null,"score":"Dolmadı","scoreNumeric":null},{"year":2023,"quota":"50","placed":"52","rank":"128.232","rankNumeric":128232,"score":"386,56166","scoreNumeric":386.56166},{"year":2022,"quota":"50","placed":"52","rank":"121.296","rankNumeric":121296,"score":"387,10146","scoreNumeric":387.10146}]},{"university":"UŞAK ÜNİVERSİTESİ","faculty":"Eğitim Fakültesi","city":"UŞAK","sector":"Devlet","program":"İlköğretim Matematik Öğretmenliği","programRaw":"İlköğretim Matematik Öğretmenliği (4 Yıllık)","scoreType":"SAY","years":[{"year":2025,"quota":"20","placed":"20","rank":"297.511","rankNumeric":297511,"score":"303,12774","scoreNumeric":303.12774},{"year":2024,"quota":"40","placed":"16","rank":"Dolmadı","rankNumeric":null,"score":"Dolmadı","scoreNumeric":null},{"year":2023,"quota":"50","placed":"52","rank":"110.648","rankNumeric":110648,"score":"400,01839","scoreNumeric":400.01839},{"year":2022,"quota":"50","placed":"52","rank":"102.306","rankNumeric":102306,"score":"403,38529","scoreNumeric":403.38529}]},{"university":"ERZİNCAN BİNALİ YILDIRIM ÜNİVERSİTESİ","faculty":"Eğitim Fakültesi","city":"ERZİNCAN","sector":"Devlet","program":"İlköğretim Matematik Öğretmenliği","programRaw":"İlköğretim Matematik Öğretmenliği (4 Yıllık)","scoreType":"SAY","years":[{"year":2025,"quota":"10","placed":"10","rank":"299.040","rankNumeric":299040,"score":"302,69552","scoreNumeric":302.69552},{"year":2024,"quota":"50","placed":"10","rank":"Dolmadı","rankNumeric":null,"score":"Dolmadı","scoreNumeric":null},{"year":2023,"quota":"50","placed":"52","rank":"129.966","rankNumeric":129966,"score":"385,29463","scoreNumeric":385.29463},{"year":2022,"quota":"50","placed":"52","rank":"120.193","rankNumeric":120193,"score":"387,97857","scoreNumeric":387.97857}]},{"university":"KÜTAHYA DUMLUPINAR ÜNİVERSİTESİ","faculty":"Eğitim Fakültesi","city":"KÜTAHYA","sector":"Devlet","program":"İlköğretim Matematik Öğretmenliği","programRaw":"İlköğretim Matematik Öğretmenliği (4 Yıllık)","scoreType":"SAY","years":[{"year":2025,"quota":"25","placed":"26","rank":"299.276","rankNumeric":299276,"score":"302,63029","scoreNumeric":302.63029},{"year":2024,"quota":"46","placed":"17","rank":"Dolmadı","rankNumeric":null,"score":"Dolmadı","scoreNumeric":null},{"year":2023,"quota":"41","placed":"43","rank":"115.946","rankNumeric":115946,"score":"395,83516","scoreNumeric":395.83516},{"year":2022,"quota":"40","placed":"41","rank":"107.520","rankNumeric":107520,"score":"398,71652","scoreNumeric":398.71652}]},{"university":"GAZİANTEP ÜNİVERSİTESİ","faculty":"Nizip Eğitim Fakültesi","city":"GAZİANTEP","sector":"Devlet","program":"İlköğretim Matematik Öğretmenliği","programRaw":"İlköğretim Matematik Öğretmenliği (4 Yıllık)","scoreType":"SAY","years":[{"year":2025,"quota":"40","placed":"41","rank":"299.577","rankNumeric":299577,"score":"302,54441","scoreNumeric":302.54441},{"year":2024,"quota":"50","placed":"34","rank":"Dolmadı","rankNumeric":null,"score":"Dolmadı","scoreNumeric":null},{"year":2023,"quota":"50","placed":"65","rank":"121.481","rankNumeric":121481,"score":"391,54512","scoreNumeric":391.54512},{"year":2022,"quota":"50","placed":"52","rank":"108.934","rankNumeric":108934,"score":"397,50802","scoreNumeric":397.50802}]},{"university":"AĞRI İBRAHİM ÇEÇEN ÜNİVERSİTESİ","faculty":"Eğitim Fakültesi","city":"AĞRI","sector":"Devlet","program":"İlköğretim Matematik Öğretmenliği","programRaw":"İlköğretim Matematik Öğretmenliği (4 Yıllık)","scoreType":"SAY","years":[{"year":2025,"quota":"15","placed":"7","rank":"Dolmadı","rankNumeric":null,"score":"Dolmadı","scoreNumeric":null},{"year":2024,"quota":"50","placed":"12","rank":"Dolmadı","rankNumeric":null,"score":"Dolmadı","scoreNumeric":null},{"year":2023,"quota":"60","placed":"62","rank":"146.817","rankNumeric":146817,"score":"373,83599","scoreNumeric":373.83599},{"year":2022,"quota":"50","placed":"52","rank":"134.938","rankNumeric":134938,"score":"376,57005","scoreNumeric":376.57005}]},{"university":"AMASYA ÜNİVERSİTESİ","faculty":"Eğitim Fakültesi","city":"AMASYA","sector":"Devlet","program":"İlköğretim Matematik Öğretmenliği","programRaw":"İlköğretim Matematik Öğretmenliği (4 Yıllık)","scoreType":"SAY","years":[{"year":2025,"quota":"20","placed":"19","rank":"Dolmadı","rankNumeric":null,"score":"Dolmadı","scoreNumeric":null},{"year":2024,"quota":"40","placed":"15","rank":"Dolmadı","rankNumeric":null,"score":"Dolmadı","scoreNumeric":null},{"year":2023,"quota":"50","placed":"52","rank":"119.088","rankNumeric":119088,"score":"393,39602","scoreNumeric":393.39602},{"year":2022,"quota":"50","placed":"52","rank":"110.843","rankNumeric":110843,"score":"395,85068","scoreNumeric":395.85068}]},{"university":"ARTVİN ÇORUH ÜNİVERSİTESİ","faculty":"Eğitim Fakültesi","city":"ARTVİN","sector":"Devlet","program":"İlköğretim Matematik Öğretmenliği","programRaw":"İlköğretim Matematik Öğretmenliği (4 Yıllık)","scoreType":"SAY","years":[{"year":2025,"quota":"10","placed":"5","rank":"Dolmadı","rankNumeric":null,"score":"Dolmadı","scoreNumeric":null},{"year":2024,"quota":"50","placed":"4","rank":"Dolmadı","rankNumeric":null,"score":"Dolmadı","scoreNumeric":null},{"year":2023,"quota":"50","placed":"52","rank":"139.754","rankNumeric":139754,"score":"378,49106","scoreNumeric":378.49106},{"year":2022,"quota":"50","placed":"52","rank":"131.827","rankNumeric":131827,"score":"378,83512","scoreNumeric":378.83512}]},{"university":"BARTIN ÜNİVERSİTESİ","faculty":"Eğitim Fakültesi","city":"BARTIN","sector":"Devlet","program":"İlköğretim Matematik Öğretmenliği","programRaw":"İlköğretim Matematik Öğretmenliği (4 Yıllık)","scoreType":"SAY","years":[{"year":2025,"quota":"10","placed":"6","rank":"Dolmadı","rankNumeric":null,"score":"Dolmadı","scoreNumeric":null},{"year":2024,"quota":"50","placed":"7","rank":"Dolmadı","rankNumeric":null,"score":"Dolmadı","scoreNumeric":null},{"year":2023,"quota":"50","placed":"52","rank":"132.792","rankNumeric":132792,"score":"383,34483","scoreNumeric":383.34483},{"year":2022,"quota":"50","placed":"52","rank":"127.549","rankNumeric":127549,"score":"382,09786","scoreNumeric":382.09786}]},{"university":"BAŞKENT ÜNİVERSİTESİ","faculty":"Eğitim Fakültesi","city":"ANKARA","sector":"Vakıf","program":"İlköğretim Matematik Öğretmenliği (%50 İndirimli)","programRaw":"İlköğretim Matematik Öğretmenliği (%50 İndirimli) (4 Yıllık)","scoreType":"SAY","years":[{"year":2025,"quota":"15","placed":"1","rank":"Dolmadı","rankNumeric":null,"score":"Dolmadı","scoreNumeric":null},{"year":2024,"quota":"23","placed":"3","rank":"Dolmadı","rankNumeric":null,"score":"Dolmadı","scoreNumeric":null},{"year":2023,"quota":"23","placed":"21","rank":"Dolmadı","rankNumeric":null,"score":"Dolmadı","scoreNumeric":null},{"year":2022,"quota":"23","placed":"23","rank":"134.712","rankNumeric":134712,"score":"376,72909","scoreNumeric":376.72909}]},{"university":"BAYBURT ÜNİVERSİTESİ","faculty":"Eğitim Fakültesi","city":"BAYBURT","sector":"Devlet","program":"İlköğretim Matematik Öğretmenliği","programRaw":"İlköğretim Matematik Öğretmenliği (4 Yıllık)","scoreType":"SAY","years":[{"year":2025,"quota":"15","placed":"3","rank":"Dolmadı","rankNumeric":null,"score":"Dolmadı","scoreNumeric":null},{"year":2024,"quota":"50","placed":"14","rank":"Dolmadı","rankNumeric":null,"score":"Dolmadı","scoreNumeric":null},{"year":2023,"quota":"60","placed":"62","rank":"145.896","rankNumeric":145896,"score":"374,43836","scoreNumeric":374.43836},{"year":2022,"quota":"50","placed":"52","rank":"134.566","rankNumeric":134566,"score":"376,83444","scoreNumeric":376.83444}]},{"university":"BİRUNİ ÜNİVERSİTESİ","faculty":"Eğitim Fakültesi","city":"İSTANBUL","sector":"Vakıf","program":"İlköğretim Matematik Öğretmenliği (%50 İndirimli)","programRaw":"İlköğretim Matematik Öğretmenliği (%50 İndirimli) (4 Yıllık)","scoreType":"SAY","years":[{"year":2025,"quota":"34","placed":"1","rank":"Dolmadı","rankNumeric":null,"score":"Dolmadı","scoreNumeric":null},{"year":2024,"quota":"25","placed":"4","rank":"Dolmadı","rankNumeric":null,"score":"Dolmadı","scoreNumeric":null},{"year":2023,"quota":"42","placed":"19","rank":"Dolmadı","rankNumeric":null,"score":"Dolmadı","scoreNumeric":null},{"year":2022,"quota":"42","placed":"42","rank":"212.326","rankNumeric":212326,"score":"331,40877","scoreNumeric":331.40877}]},{"university":"GİRESUN ÜNİVERSİTESİ","faculty":"Eğitim Fakültesi","city":"GİRESUN","sector":"Devlet","program":"İlköğretim Matematik Öğretmenliği","programRaw":"İlköğretim Matematik Öğretmenliği (4 Yıllık)","scoreType":"SAY","years":[{"year":2025,"quota":"20","placed":"9","rank":"Dolmadı","rankNumeric":null,"score":"Dolmadı","scoreNumeric":null},{"year":2024,"quota":"40","placed":"15","rank":"Dolmadı","rankNumeric":null,"score":"Dolmadı","scoreNumeric":null},{"year":2023,"quota":"50","placed":"52","rank":"131.870","rankNumeric":131870,"score":"383,96090","scoreNumeric":383.9609},{"year":2022,"quota":"50","placed":"52","rank":"126.104","rankNumeric":126104,"score":"383,24331","scoreNumeric":383.24331}]},{"university":"HAKKARİ ÜNİVERSİTESİ","faculty":"Eğitim Fakültesi","city":"HAKKARİ","sector":"Devlet","program":"İlköğretim Matematik Öğretmenliği","programRaw":"İlköğretim Matematik Öğretmenliği (4 Yıllık)","scoreType":"SAY","years":[{"year":2025,"quota":"15","placed":"1","rank":"Dolmadı","rankNumeric":null,"score":"Dolmadı","scoreNumeric":null},{"year":2024,"quota":"50","placed":"12","rank":"Dolmadı","rankNumeric":null,"score":"Dolmadı","scoreNumeric":null},{"year":2023,"quota":"50","placed":"52","rank":"158.546","rankNumeric":158546,"score":"366,49301","scoreNumeric":366.49301},{"year":2022,"quota":"50","placed":"52","rank":"149.654","rankNumeric":149654,"score":"366,26506","scoreNumeric":366.26506}]},{"university":"İSTANBUL 29 MAYIS ÜNİVERSİTESİ","faculty":"Eğitim Fakültesi","city":"İSTANBUL","sector":"Vakıf","program":"İlköğretim Matematik Öğretmenliği (%50 İndirimli)","programRaw":"İlköğretim Matematik Öğretmenliği (%50 İndirimli) (4 Yıllık)","scoreType":"SAY","years":[{"year":2025,"quota":"34","placed":"5","rank":"Dolmadı","rankNumeric":null,"score":"Dolmadı","scoreNumeric":null},{"year":2024,"quota":"42","placed":"16","rank":"Dolmadı","rankNumeric":null,"score":"Dolmadı","scoreNumeric":null},{"year":2023,"quota":"51","placed":"51","rank":"218.891","rankNumeric":218891,"score":"336,15678","scoreNumeric":336.15678},{"year":2022,"quota":"34","placed":"34","rank":"214.382","rankNumeric":214382,"score":"330,44676","scoreNumeric":330.44676}]},{"university":"İSTANBUL SABAHATTİN ZAİM ÜNİVERSİTESİ","faculty":"Eğitim Fakültesi","city":"İSTANBUL","sector":"Vakıf","program":"İlköğretim Matematik Öğretmenliği (%50 İndirimli)","programRaw":"İlköğretim Matematik Öğretmenliği (%50 İndirimli) (4 Yıllık)","scoreType":"SAY","years":[{"year":2025,"quota":"30","placed":"4","rank":"Dolmadı","rankNumeric":null,"score":"Dolmadı","scoreNumeric":null},{"year":2024,"quota":"42","placed":"16","rank":"Dolmadı","rankNumeric":null,"score":"Dolmadı","scoreNumeric":null},{"year":2023,"quota":"42","placed":"42","rank":"294.570","rankNumeric":294570,"score":"309,25243","scoreNumeric":309.25243},{"year":2022,"quota":"43","placed":"43","rank":"283.003","rankNumeric":283003,"score":"303,47565","scoreNumeric":303.47565}]},{"university":"İZMİR DEMOKRASİ ÜNİVERSİTESİ","faculty":"Eğitim Fakültesi","city":"İZMİR","sector":"Devlet","program":"İlköğretim Matematik Öğretmenliği (İngilizce)","programRaw":"İlköğretim Matematik Öğretmenliği (İngilizce) (4 Yıllık)","scoreType":"SAY","years":[{"year":2025,"quota":"25","placed":"24","rank":"Dolmadı","rankNumeric":null,"score":"Dolmadı","scoreNumeric":null},{"year":2024,"quota":"45","placed":"17","rank":"Dolmadı","rankNumeric":null,"score":"Dolmadı","scoreNumeric":null},{"year":2023,"quota":"40","placed":"41","rank":"116.825","rankNumeric":116825,"score":"395,15454","scoreNumeric":395.15454},{"year":2022,"quota":"—","placed":"—","rank":"—","rankNumeric":null,"score":"—","scoreNumeric":null}]},{"university":"KAFKAS ÜNİVERSİTESİ","faculty":"Dede Korkut Eğitim Fakültesi","city":"KARS","sector":"Devlet","program":"İlköğretim Matematik Öğretmenliği","programRaw":"İlköğretim Matematik Öğretmenliği (4 Yıllık)","scoreType":"SAY","years":[{"year":2025,"quota":"20","placed":"5","rank":"Dolmadı","rankNumeric":null,"score":"Dolmadı","scoreNumeric":null},{"year":2024,"quota":"50","placed":"15","rank":"Dolmadı","rankNumeric":null,"score":"Dolmadı","scoreNumeric":null},{"year":2023,"quota":"50","placed":"52","rank":"149.271","rankNumeric":149271,"score":"372,23063","scoreNumeric":372.23063},{"year":2022,"quota":"50","placed":"52","rank":"137.187","rankNumeric":137187,"score":"374,98463","scoreNumeric":374.98463}]},{"university":"KARAMANOĞLU MEHMETBEY ÜNİVERSİTESİ","faculty":"Eğitim Fakültesi","city":"KARAMAN","sector":"Devlet","program":"İlköğretim Matematik Öğretmenliği","programRaw":"İlköğretim Matematik Öğretmenliği (4 Yıllık)","scoreType":"SAY","years":[{"year":2025,"quota":"25","placed":"18","rank":"Dolmadı","rankNumeric":null,"score":"Dolmadı","scoreNumeric":null},{"year":2024,"quota":"50","placed":"17","rank":"Dolmadı","rankNumeric":null,"score":"Dolmadı","scoreNumeric":null},{"year":2023,"quota":"50","placed":"52","rank":"121.160","rankNumeric":121160,"score":"391,80520","scoreNumeric":391.8052},{"year":2022,"quota":"50","placed":"52","rank":"113.548","rankNumeric":113548,"score":"393,54386","scoreNumeric":393.54386}]},{"university":"KASTAMONU ÜNİVERSİTESİ","faculty":"Eğitim Fakültesi","city":"KASTAMONU","sector":"Devlet","program":"İlköğretim Matematik Öğretmenliği","programRaw":"İlköğretim Matematik Öğretmenliği (4 Yıllık)","scoreType":"SAY","years":[{"year":2025,"quota":"20","placed":"12","rank":"Dolmadı","rankNumeric":null,"score":"Dolmadı","scoreNumeric":null},{"year":2024,"quota":"50","placed":"15","rank":"Dolmadı","rankNumeric":null,"score":"Dolmadı","scoreNumeric":null},{"year":2023,"quota":"50","placed":"52","rank":"131.527","rankNumeric":131527,"score":"384,20784","scoreNumeric":384.20784},{"year":2022,"quota":"50","placed":"52","rank":"122.835","rankNumeric":122835,"score":"385,86860","scoreNumeric":385.8686}]},{"university":"KIRŞEHİR AHİ EVRAN ÜNİVERSİTESİ","faculty":"Eğitim Fakültesi","city":"KIRŞEHİR","sector":"Devlet","program":"İlköğretim Matematik Öğretmenliği","programRaw":"İlköğretim Matematik Öğretmenliği (4 Yıllık)","scoreType":"SAY","years":[{"year":2025,"quota":"25","placed":"16","rank":"Dolmadı","rankNumeric":null,"score":"Dolmadı","scoreNumeric":null},{"year":2024,"quota":"50","placed":"18","rank":"Dolmadı","rankNumeric":null,"score":"Dolmadı","scoreNumeric":null},{"year":2023,"quota":"50","placed":"52","rank":"116.995","rankNumeric":116995,"score":"395,02545","scoreNumeric":395.02545},{"year":2022,"quota":"50","placed":"52","rank":"110.338","rankNumeric":110338,"score":"396,30227","scoreNumeric":396.30227}]},{"university":"KİLİS 7 ARALIK ÜNİVERSİTESİ","faculty":"Kilisli Muallim Rıfat Eğitim Fakültesi","city":"KİLİS","sector":"Devlet","program":"İlköğretim Matematik Öğretmenliği","programRaw":"İlköğretim Matematik Öğretmenliği (4 Yıllık)","scoreType":"SAY","years":[{"year":2025,"quota":"15","placed":"10","rank":"Dolmadı","rankNumeric":null,"score":"Dolmadı","scoreNumeric":null},{"year":2024,"quota":"50","placed":"12","rank":"Dolmadı","rankNumeric":null,"score":"Dolmadı","scoreNumeric":null},{"year":2023,"quota":"50","placed":"65","rank":"133.206","rankNumeric":133206,"score":"383,06162","scoreNumeric":383.06162},{"year":2022,"quota":"40","placed":"41","rank":"121.151","rankNumeric":121151,"score":"387,21704","scoreNumeric":387.21704}]},{"university":"MALTEPE ÜNİVERSİTESİ","faculty":"Eğitim Fakültesi","city":"İSTANBUL","sector":"Vakıf","program":"İlköğretim Matematik Öğretmenliği (%50 İndirimli)","programRaw":"İlköğretim Matematik Öğretmenliği (%50 İndirimli) (4 Yıllık)","scoreType":"SAY","years":[{"year":2025,"quota":"8","placed":"1","rank":"Dolmadı","rankNumeric":null,"score":"Dolmadı","scoreNumeric":null},{"year":2024,"quota":"4","placed":"—","rank":"Dolmadı","rankNumeric":null,"score":"Dolmadı","scoreNumeric":null},{"year":2023,"quota":"—","placed":"—","rank":"—","rankNumeric":null,"score":"—","scoreNumeric":null},{"year":2022,"quota":"—","placed":"—","rank":"—","rankNumeric":null,"score":"—","scoreNumeric":null}]},{"university":"MANİSA CELÂL BAYAR ÜNİVERSİTESİ","faculty":"Eğitim Fakültesi (Demirci)","city":"MANİSA","sector":"Devlet","program":"İlköğretim Matematik Öğretmenliği","programRaw":"İlköğretim Matematik Öğretmenliği (4 Yıllık)","scoreType":"SAY","years":[{"year":2025,"quota":"30","placed":"27","rank":"Dolmadı","rankNumeric":null,"score":"Dolmadı","scoreNumeric":null},{"year":2024,"quota":"50","placed":"25","rank":"Dolmadı","rankNumeric":null,"score":"Dolmadı","scoreNumeric":null},{"year":2023,"quota":"60","placed":"62","rank":"121.233","rankNumeric":121233,"score":"391,74739","scoreNumeric":391.74739},{"year":2022,"quota":"50","placed":"52","rank":"104.729","rankNumeric":104729,"score":"401,17281","scoreNumeric":401.17281}]},{"university":"MUŞ ALPARSLAN ÜNİVERSİTESİ","faculty":"Eğitim Fakültesi","city":"MUŞ","sector":"Devlet","program":"İlköğretim Matematik Öğretmenliği","programRaw":"İlköğretim Matematik Öğretmenliği (4 Yıllık)","scoreType":"SAY","years":[{"year":2025,"quota":"15","placed":"2","rank":"Dolmadı","rankNumeric":null,"score":"Dolmadı","scoreNumeric":null},{"year":2024,"quota":"45","placed":"10","rank":"Dolmadı","rankNumeric":null,"score":"Dolmadı","scoreNumeric":null},{"year":2023,"quota":"40","placed":"41","rank":"137.813","rankNumeric":137813,"score":"379,80099","scoreNumeric":379.80099},{"year":2022,"quota":"40","placed":"41","rank":"122.207","rankNumeric":122207,"score":"386,37773","scoreNumeric":386.37773}]},{"university":"NECMETTİN ERBAKAN ÜNİVERSİTESİ","faculty":"Ereğli Eğitim Fakültesi","city":"KONYA","sector":"Devlet","program":"İlköğretim Matematik Öğretmenliği","programRaw":"İlköğretim Matematik Öğretmenliği (4 Yıllık)","scoreType":"SAY","years":[{"year":2025,"quota":"20","placed":"12","rank":"Dolmadı","rankNumeric":null,"score":"Dolmadı","scoreNumeric":null},{"year":2024,"quota":"45","placed":"13","rank":"Dolmadı","rankNumeric":null,"score":"Dolmadı","scoreNumeric":null},{"year":2023,"quota":"40","placed":"41","rank":"121.415","rankNumeric":121415,"score":"391,59711","scoreNumeric":391.59711},{"year":2022,"quota":"40","placed":"41","rank":"109.979","rankNumeric":109979,"score":"396,61584","scoreNumeric":396.61584}]},{"university":"RECEP TAYYİP ERDOĞAN ÜNİVERSİTESİ","faculty":"Eğitim Fakültesi (Çayeli)","city":"RİZE","sector":"Devlet","program":"İlköğretim Matematik Öğretmenliği","programRaw":"İlköğretim Matematik Öğretmenliği (4 Yıllık)","scoreType":"SAY","years":[{"year":2025,"quota":"20","placed":"7","rank":"Dolmadı","rankNumeric":null,"score":"Dolmadı","scoreNumeric":null},{"year":2024,"quota":"50","placed":"15","rank":"Dolmadı","rankNumeric":null,"score":"Dolmadı","scoreNumeric":null},{"year":2023,"quota":"50","placed":"52","rank":"134.442","rankNumeric":134442,"score":"382,21049","scoreNumeric":382.21049},{"year":2022,"quota":"50","placed":"52","rank":"125.763","rankNumeric":125763,"score":"383,52512","scoreNumeric":383.52512}]},{"university":"SİİRT ÜNİVERSİTESİ","faculty":"Eğitim Fakültesi","city":"SİİRT","sector":"Devlet","program":"İlköğretim Matematik Öğretmenliği","programRaw":"İlköğretim Matematik Öğretmenliği (4 Yıllık)","scoreType":"SAY","years":[{"year":2025,"quota":"20","placed":"8","rank":"Dolmadı","rankNumeric":null,"score":"Dolmadı","scoreNumeric":null},{"year":2024,"quota":"50","placed":"14","rank":"Dolmadı","rankNumeric":null,"score":"Dolmadı","scoreNumeric":null},{"year":2023,"quota":"60","placed":"62","rank":"132.750","rankNumeric":132750,"score":"383,38257","scoreNumeric":383.38257},{"year":2022,"quota":"50","placed":"52","rank":"113.174","rankNumeric":113174,"score":"393,84920","scoreNumeric":393.8492}]},{"university":"SİNOP ÜNİVERSİTESİ","faculty":"Eğitim Fakültesi","city":"SİNOP","sector":"Devlet","program":"İlköğretim Matematik Öğretmenliği","programRaw":"İlköğretim Matematik Öğretmenliği (4 Yıllık)","scoreType":"SAY","years":[{"year":2025,"quota":"10","placed":"7","rank":"Dolmadı","rankNumeric":null,"score":"Dolmadı","scoreNumeric":null},{"year":2024,"quota":"45","placed":"4","rank":"Dolmadı","rankNumeric":null,"score":"Dolmadı","scoreNumeric":null},{"year":2023,"quota":"40","placed":"41","rank":"126.607","rankNumeric":126607,"score":"387,75891","scoreNumeric":387.75891},{"year":2022,"quota":"40","placed":"41","rank":"120.792","rankNumeric":120792,"score":"387,50483","scoreNumeric":387.50483}]},{"university":"SİVAS CUMHURİYET ÜNİVERSİTESİ","faculty":"Eğitim Fakültesi","city":"SİVAS","sector":"Devlet","program":"İlköğretim Matematik Öğretmenliği","programRaw":"İlköğretim Matematik Öğretmenliği (4 Yıllık)","scoreType":"SAY","years":[{"year":2025,"quota":"40","placed":"39","rank":"Dolmadı","rankNumeric":null,"score":"Dolmadı","scoreNumeric":null},{"year":2024,"quota":"50","placed":"31","rank":"Dolmadı","rankNumeric":null,"score":"Dolmadı","scoreNumeric":null},{"year":2023,"quota":"55","placed":"71","rank":"102.208","rankNumeric":102208,"score":"406,94890","scoreNumeric":406.9489},{"year":2022,"quota":"50","placed":"52","rank":"96.710","rankNumeric":96710,"score":"408,58532","scoreNumeric":408.58532}]},{"university":"TOKAT GAZİOSMANPAŞA ÜNİVERSİTESİ","faculty":"Eğitim Fakültesi","city":"TOKAT","sector":"Devlet","program":"İlköğretim Matematik Öğretmenliği","programRaw":"İlköğretim Matematik Öğretmenliği (4 Yıllık)","scoreType":"SAY","years":[{"year":2025,"quota":"15","placed":"11","rank":"Dolmadı","rankNumeric":null,"score":"Dolmadı","scoreNumeric":null},{"year":2024,"quota":"50","placed":"11","rank":"Dolmadı","rankNumeric":null,"score":"Dolmadı","scoreNumeric":null},{"year":2023,"quota":"50","placed":"52","rank":"122.624","rankNumeric":122624,"score":"390,69015","scoreNumeric":390.69015},{"year":2022,"quota":"50","placed":"52","rank":"115.292","rankNumeric":115292,"score":"392,03420","scoreNumeric":392.0342}]},{"university":"YOZGAT BOZOK ÜNİVERSİTESİ","faculty":"Eğitim Fakültesi","city":"YOZGAT","sector":"Devlet","program":"İlköğretim Matematik Öğretmenliği","programRaw":"İlköğretim Matematik Öğretmenliği (4 Yıllık)","scoreType":"SAY","years":[{"year":2025,"quota":"10","placed":"4","rank":"Dolmadı","rankNumeric":null,"score":"Dolmadı","scoreNumeric":null},{"year":2024,"quota":"50","placed":"10","rank":"Dolmadı","rankNumeric":null,"score":"Dolmadı","scoreNumeric":null},{"year":2023,"quota":"50","placed":"52","rank":"132.964","rankNumeric":132964,"score":"383,21544","scoreNumeric":383.21544},{"year":2022,"quota":"50","placed":"52","rank":"122.849","rankNumeric":122849,"score":"385,86032","scoreNumeric":385.86032}]},{"university":"BAŞKENT ÜNİVERSİTESİ","faculty":"Eğitim Fakültesi","city":"ANKARA","sector":"Vakıf","program":"İlköğretim Matematik Öğretmenliği (Ücretli)","programRaw":"İlköğretim Matematik Öğretmenliği (Ücretli) (4 Yıllık)","scoreType":"SAY","years":[{"year":2025,"quota":"2","placed":"—","rank":"Dolmadı","rankNumeric":null,"score":"Dolmadı","scoreNumeric":null},{"year":2024,"quota":"2","placed":"—","rank":"Dolmadı","rankNumeric":null,"score":"Dolmadı","scoreNumeric":null},{"year":2023,"quota":"2","placed":"2","rank":"287.598","rankNumeric":287598,"score":"311,37255","scoreNumeric":311.37255},{"year":2022,"quota":"2","placed":"2","rank":"181.102","rankNumeric":181102,"score":"347,13345","scoreNumeric":347.13345}]},{"university":"DOĞU AKDENİZ ÜNİVERSİTESİ","faculty":"Eğitim Fakültesi (KKTC-GAZİMAĞUSA) (KKTC )","city":null,"sector":null,"program":"İlköğretim Matematik Öğretmenliği (Ücretli)","programRaw":"İlköğretim Matematik Öğretmenliği (Ücretli) (4 Yıllık)","scoreType":"SAY","years":[{"year":2025,"quota":"35","placed":"—","rank":"Dolmadı","rankNumeric":null,"score":"Dolmadı","scoreNumeric":null},{"year":2024,"quota":"35","placed":"3","rank":"Dolmadı","rankNumeric":null,"score":"Dolmadı","scoreNumeric":null},{"year":2023,"quota":"35","placed":"14","rank":"Dolmadı","rankNumeric":null,"score":"Dolmadı","scoreNumeric":null},{"year":2022,"quota":"25","placed":"25","rank":"244.559","rankNumeric":244559,"score":"317,55807","scoreNumeric":317.55807}]},{"university":"DOĞU AKDENİZ ÜNİVERSİTESİ","faculty":"Eğitim Fakültesi (KKTC-GAZİMAĞUSA) (KKTC )","city":null,"sector":null,"program":"İlköğretim Matematik Öğretmenliği (Burslu)","programRaw":"İlköğretim Matematik Öğretmenliği (Burslu) (4 Yıllık)","scoreType":"SAY","years":[{"year":2025,"quota":"8","placed":"—","rank":"Dolmadı","rankNumeric":null,"score":"Dolmadı","scoreNumeric":null},{"year":2024,"quota":"8","placed":"8","rank":"217.250","rankNumeric":217250,"score":"316,52014","scoreNumeric":316.52014},{"year":2023,"quota":"8","placed":"8","rank":"164.386","rankNumeric":164386,"score":"363,09441","scoreNumeric":363.09441},{"year":2022,"quota":"8","placed":"8","rank":"134.085","rankNumeric":134085,"score":"377,16909","scoreNumeric":377.16909}]},{"university":"DOĞU AKDENİZ ÜNİVERSİTESİ","faculty":"Eğitim Fakültesi (KKTC-GAZİMAĞUSA) (KKTC )","city":null,"sector":null,"program":"İlköğretim Matematik Öğretmenliği (%50 İndirimli)","programRaw":"İlköğretim Matematik Öğretmenliği (%50 İndirimli) (4 Yıllık)","scoreType":"SAY","years":[{"year":2025,"quota":"7","placed":"—","rank":"Dolmadı","rankNumeric":null,"score":"Dolmadı","scoreNumeric":null},{"year":2024,"quota":"7","placed":"—","rank":"Dolmadı","rankNumeric":null,"score":"Dolmadı","scoreNumeric":null},{"year":2023,"quota":"7","placed":"3","rank":"Dolmadı","rankNumeric":null,"score":"Dolmadı","scoreNumeric":null},{"year":2022,"quota":"17","placed":"1","rank":"Dolmadı","rankNumeric":null,"score":"Dolmadı","scoreNumeric":null}]},{"university":"İSTANBUL AYDIN ÜNİVERSİTESİ","faculty":"Eğitim Fakültesi","city":"İSTANBUL","sector":"Vakıf","program":"İlköğretim Matematik Öğretmenliği (%50 İndirimli)","programRaw":"İlköğretim Matematik Öğretmenliği (%50 İndirimli) (4 Yıllık)","scoreType":"SAY","years":[{"year":2025,"quota":"25","placed":"—","rank":"Dolmadı","rankNumeric":null,"score":"Dolmadı","scoreNumeric":null},{"year":2024,"quota":"21","placed":"12","rank":"Dolmadı","rankNumeric":null,"score":"Dolmadı","scoreNumeric":null},{"year":2023,"quota":"42","placed":"10","rank":"Dolmadı","rankNumeric":null,"score":"Dolmadı","scoreNumeric":null},{"year":2022,"quota":"42","placed":"42","rank":"171.215","rankNumeric":171215,"score":"352,65072","scoreNumeric":352.65072}]},{"university":"İSTANBUL MEDİPOL ÜNİVERSİTESİ","faculty":"Eğitim Fakültesi","city":"İSTANBUL","sector":"Vakıf","program":"İlköğretim Matematik Öğretmenliği (%50 İndirimli)","programRaw":"İlköğretim Matematik Öğretmenliği (%50 İndirimli) (4 Yıllık)","scoreType":"SAY","years":[{"year":2025,"quota":"21","placed":"—","rank":"Dolmadı","rankNumeric":null,"score":"Dolmadı","scoreNumeric":null},{"year":2024,"quota":"—","placed":"—","rank":"…","rankNumeric":null,"score":"—","scoreNumeric":null},{"year":2023,"quota":"—","placed":"—","rank":"—","rankNumeric":null,"score":"—","scoreNumeric":null},{"year":2022,"quota":"—","placed":"—","rank":"—","rankNumeric":null,"score":"—","scoreNumeric":null}]},{"university":"LEFKE AVRUPA ÜNİVERSİTESİ","faculty":"Dr. Fazıl Küçük Eğitim Fakültesi (KKTC-LEFKE) (KKTC )","city":null,"sector":null,"program":"İlköğretim Matematik Öğretmenliği (Burslu)","programRaw":"İlköğretim Matematik Öğretmenliği (Burslu) (4 Yıllık)","scoreType":"SAY","years":[{"year":2025,"quota":"12","placed":"—","rank":"Dolmadı","rankNumeric":null,"score":"Dolmadı","scoreNumeric":null},{"year":2024,"quota":"11","placed":"1","rank":"Dolmadı","rankNumeric":null,"score":"Dolmadı","scoreNumeric":null},{"year":2023,"quota":"11","placed":"11","rank":"149.196","rankNumeric":149196,"score":"372,28004","scoreNumeric":372.28004},{"year":2022,"quota":"8","placed":"8","rank":"140.088","rankNumeric":140088,"score":"372,86162","scoreNumeric":372.86162}]},{"university":"LEFKE AVRUPA ÜNİVERSİTESİ","faculty":"Dr. Fazıl Küçük Eğitim Fakültesi (KKTC-LEFKE) (KKTC )","city":null,"sector":null,"program":"İlköğretim Matematik Öğretmenliği (%50 İndirimli)","programRaw":"İlköğretim Matematik Öğretmenliği (%50 İndirimli) (4 Yıllık)","scoreType":"SAY","years":[{"year":2025,"quota":"38","placed":"—","rank":"Dolmadı","rankNumeric":null,"score":"Dolmadı","scoreNumeric":null},{"year":2024,"quota":"39","placed":"2","rank":"Dolmadı","rankNumeric":null,"score":"Dolmadı","scoreNumeric":null},{"year":2023,"quota":"39","placed":"25","rank":"Dolmadı","rankNumeric":null,"score":"Dolmadı","scoreNumeric":null},{"year":2022,"quota":"40","placed":"31","rank":"Dolmadı","rankNumeric":null,"score":"Dolmadı","scoreNumeric":null}]},{"university":"MALTEPE ÜNİVERSİTESİ","faculty":"Eğitim Fakültesi","city":"İSTANBUL","sector":"Vakıf","program":"İlköğretim Matematik Öğretmenliği (Ücretli)","programRaw":"İlköğretim Matematik Öğretmenliği (Ücretli) (4 Yıllık)","scoreType":"SAY","years":[{"year":2025,"quota":"1","placed":"—","rank":"Dolmadı","rankNumeric":null,"score":"Dolmadı","scoreNumeric":null},{"year":2024,"quota":"5","placed":"—","rank":"Dolmadı","rankNumeric":null,"score":"Dolmadı","scoreNumeric":null},{"year":2023,"quota":"10","placed":"—","rank":"Dolmadı","rankNumeric":null,"score":"Dolmadı","scoreNumeric":null},{"year":2022,"quota":"24","placed":"1","rank":"Dolmadı","rankNumeric":null,"score":"Dolmadı","scoreNumeric":null}]},{"university":"YAKIN DOĞU ÜNİVERSİTESİ","faculty":"Atatürk Eğitim Fakültesi (KKTC-LEFKOŞA) (KKTC )","city":null,"sector":null,"program":"İlköğretim Matematik Öğretmenliği (%50 İndirimli)","programRaw":"İlköğretim Matematik Öğretmenliği (%50 İndirimli) (4 Yıllık)","scoreType":"SAY","years":[{"year":2025,"quota":"35","placed":"—","rank":"Dolmadı","rankNumeric":null,"score":"Dolmadı","scoreNumeric":null},{"year":2024,"quota":"41","placed":"—","rank":"Dolmadı","rankNumeric":null,"score":"Dolmadı","scoreNumeric":null},{"year":2023,"quota":"41","placed":"2","rank":"Dolmadı","rankNumeric":null,"score":"Dolmadı","scoreNumeric":null},{"year":2022,"quota":"43","placed":"17","rank":"Dolmadı","rankNumeric":null,"score":"Dolmadı","scoreNumeric":null}]},{"university":"YAKIN DOĞU ÜNİVERSİTESİ","faculty":"Atatürk Eğitim Fakültesi (KKTC-LEFKOŞA) (KKTC )","city":null,"sector":null,"program":"İlköğretim Matematik Öğretmenliği (Burslu)","programRaw":"İlköğretim Matematik Öğretmenliği (Burslu) (4 Yıllık)","scoreType":"SAY","years":[{"year":2025,"quota":"15","placed":"—","rank":"Dolmadı","rankNumeric":null,"score":"Dolmadı","scoreNumeric":null},{"year":2024,"quota":"9","placed":"3","rank":"Dolmadı","rankNumeric":null,"score":"Dolmadı","scoreNumeric":null},{"year":2023,"quota":"9","placed":"9","rank":"189.538","rankNumeric":189538,"score":"349,62649","scoreNumeric":349.62649},{"year":2022,"quota":"7","placed":"7","rank":"144.189","rankNumeric":144189,"score":"369,94533","scoreNumeric":369.94533}]},{"university":"YEDİTEPE ÜNİVERSİTESİ","faculty":"Eğitim Fakültesi","city":"İSTANBUL","sector":"Vakıf","program":"İlköğretim Matematik Öğretmenliği (İngilizce) (%50 İndirimli)","programRaw":"İlköğretim Matematik Öğretmenliği (İngilizce) (%50 İndirimli) (4 Yıllık)","scoreType":"SAY","years":[{"year":2025,"quota":"7","placed":"—","rank":"Dolmadı","rankNumeric":null,"score":"Dolmadı","scoreNumeric":null},{"year":2024,"quota":"10","placed":"1","rank":"Dolmadı","rankNumeric":null,"score":"Dolmadı","scoreNumeric":null},{"year":2023,"quota":"20","placed":"4","rank":"Dolmadı","rankNumeric":null,"score":"Dolmadı","scoreNumeric":null},{"year":2022,"quota":"25","placed":"19","rank":"Dolmadı","rankNumeric":null,"score":"Dolmadı","scoreNumeric":null}]}],"warnings":["7/101 satırda il yok"]}