{"name":"Uluslararası İlişkiler","slug":"uluslararasi-iliskiler-2024-taban-puanlari-ve-basari-siralamasi","level":"4yillik","scoreType":"EA","url":"https://www.basarisiralamalari.com/uluslararasi-iliskiler-2024-taban-puanlari-ve-basari-siralamasi/","rows":[{"university":"KOÇ ÜNİVERSİTESİ","faculty":"İktisadi ve İdari Bilimler Fakültesi","city":"İSTANBUL","sector":"Vakıf","program":"Uluslararası İlişkiler (İngilizce) (Burslu)","programRaw":"Uluslararası İlişkiler (İngilizce) (Burslu) (4 Yıllık)","scoreType":"EA","years":[{"year":2025,"quota":"13","placed":"15","rank":"398","rankNumeric":398,"score":"503,20504","scoreNumeric":503.20504},{"year":2024,"quota":"10","placed":"13","rank":"651","rankNumeric":651,"score":"497,91293","scoreNumeric":497.91293},{"year":2023,"quota":"12","placed":"15","rank":"302","rankNumeric":302,"score":"524,47182","scoreNumeric":524.47182},{"year":2022,"quota":"15","placed":"15","rank":"436","rankNumeric":436,"score":"516,72888","scoreNumeric":516.72888}]},{"university":"İHSAN DOĞRAMACI BİLKENT ÜNİVERSİTESİ","faculty":"İktisadi, İdari ve Sosyal Bilimler Fakültesi","city":"ANKARA","sector":"Vakıf","program":"Uluslararası İlişkiler (İngilizce) (Burslu)","programRaw":"Uluslararası İlişkiler (İngilizce) (Burslu) (4 Yıllık)","scoreType":"EA","years":[{"year":2025,"quota":"18","placed":"22","rank":"1.050","rankNumeric":1050,"score":"481,64548","scoreNumeric":481.64548},{"year":2024,"quota":"18","placed":"22","rank":"756","rankNumeric":756,"score":"494,57446","scoreNumeric":494.57446},{"year":2023,"quota":"18","placed":"20","rank":"829","rankNumeric":829,"score":"506,64269","scoreNumeric":506.64269},{"year":2022,"quota":"21","placed":"21","rank":"1.589","rankNumeric":1589,"score":"493,72301","scoreNumeric":493.72301}]},{"university":"GALATASARAY ÜNİVERSİTESİ","faculty":"İktisadi ve İdari Bilimler Fakültesi","city":"İSTANBUL","sector":"Devlet","program":"Uluslararası İlişkiler (Fransızca)","programRaw":"Uluslararası İlişkiler (Fransızca) (4 Yıllık)","scoreType":"EA","years":[{"year":2025,"quota":"30","placed":"32","rank":"1.688","rankNumeric":1688,"score":"468,9837","scoreNumeric":468.9837},{"year":2024,"quota":"35","placed":"37","rank":"1.819","rankNumeric":1819,"score":"472,78185","scoreNumeric":472.78185},{"year":2023,"quota":"30","placed":"32","rank":"1.522","rankNumeric":1522,"score":"492,02201","scoreNumeric":492.02201},{"year":2022,"quota":"30","placed":"31","rank":"1.890","rankNumeric":1890,"score":"489,80386","scoreNumeric":489.80386}]},{"university":"ORTA DOĞU TEKNİK ÜNİVERSİTESİ","faculty":"İktisadi ve İdari Bilimler Fakültesi","city":"ANKARA","sector":"Devlet","program":"Uluslararası İlişkiler (İngilizce)","programRaw":"Uluslararası İlişkiler (İngilizce) (4 Yıllık)","scoreType":"EA","years":[{"year":2025,"quota":"65","placed":"67","rank":"1.969","rankNumeric":1969,"score":"465,09845","scoreNumeric":465.09845},{"year":2024,"quota":"75","placed":"77","rank":"2.149","rankNumeric":2149,"score":"467,93389","scoreNumeric":467.93389},{"year":2023,"quota":"70","placed":"73","rank":"2.267","rankNumeric":2267,"score":"481,21573","scoreNumeric":481.21573},{"year":2022,"quota":"80","placed":"82","rank":"3.923","rankNumeric":3923,"score":"471,87987","scoreNumeric":471.87987}]},{"university":"ÖZYEĞİN ÜNİVERSİTESİ","faculty":"Sosyal Bilimler Fakültesi","city":"İSTANBUL","sector":"Vakıf","program":"Uluslararası İlişkiler (İngilizce) (Burslu)","programRaw":"Uluslararası İlişkiler (İngilizce) (Burslu) (4 Yıllık)","scoreType":"EA","years":[{"year":2025,"quota":"8","placed":"10","rank":"2.069","rankNumeric":2069,"score":"463,9942","scoreNumeric":463.9942},{"year":2024,"quota":"6","placed":"8","rank":"1.657","rankNumeric":1657,"score":"475,21132","scoreNumeric":475.21132},{"year":2023,"quota":"7","placed":"8","rank":"1.812","rankNumeric":1812,"score":"487,39085","scoreNumeric":487.39085},{"year":2022,"quota":"7","placed":"7","rank":"2.102","rankNumeric":2102,"score":"487,36320","scoreNumeric":487.3632}]},{"university":"HACETTEPE ÜNİVERSİTESİ","faculty":"İktisadi ve İdari Bilimler Fakültesi","city":"ANKARA","sector":"Devlet","program":"Uluslararası İlişkiler (İngilizce)","programRaw":"Uluslararası İlişkiler (İngilizce) (4 Yıllık)","scoreType":"EA","years":[{"year":2025,"quota":"70","placed":"72","rank":"14.097","rankNumeric":14097,"score":"418,59509","scoreNumeric":418.59509},{"year":2024,"quota":"75","placed":"77","rank":"27.406","rankNumeric":27406,"score":"406,89776","scoreNumeric":406.89776},{"year":2023,"quota":"70","placed":"72","rank":"36.052","rankNumeric":36052,"score":"406,34107","scoreNumeric":406.34107},{"year":2022,"quota":"80","placed":"82","rank":"53.669","rankNumeric":53669,"score":"402,25098","scoreNumeric":402.25098}]},{"university":"İSTANBUL BİLGİ ÜNİVERSİTESİ","faculty":"Sosyal ve Beşeri Bilimler Fakültesi","city":"İSTANBUL","sector":"Vakıf","program":"Uluslararası İlişkiler (İngilizce) (Burslu)","programRaw":"Uluslararası İlişkiler (İngilizce) (Burslu) (4 Yıllık)","scoreType":"EA","years":[{"year":2025,"quota":"15","placed":"17","rank":"33.831","rankNumeric":33831,"score":"396,65236","scoreNumeric":396.65236},{"year":2024,"quota":"14","placed":"15","rank":"48.094","rankNumeric":48094,"score":"389,04204","scoreNumeric":389.04204},{"year":2023,"quota":"14","placed":"15","rank":"17.867","rankNumeric":17867,"score":"423,00419","scoreNumeric":423.00419},{"year":2022,"quota":"14","placed":"14","rank":"22.942","rankNumeric":22942,"score":"424,21534","scoreNumeric":424.21534}]},{"university":"ANKARA ÜNİVERSİTESİ","faculty":"Siyasal Bilgiler Fakültesi","city":"ANKARA","sector":"Devlet","program":"Uluslararası İlişkiler","programRaw":"Uluslararası İlişkiler (4 Yıllık)","scoreType":"EA","years":[{"year":2025,"quota":"50","placed":"52","rank":"34.315","rankNumeric":34315,"score":"396,23158","scoreNumeric":396.23158},{"year":2024,"quota":"65","placed":"67","rank":"56.924","rankNumeric":56924,"score":"383,04291","scoreNumeric":383.04291},{"year":2023,"quota":"60","placed":"63","rank":"61.763","rankNumeric":61763,"score":"390,14118","scoreNumeric":390.14118},{"year":2022,"quota":"60","placed":"62","rank":"86.281","rankNumeric":86281,"score":"385,11264","scoreNumeric":385.11264}]},{"university":"ANKARA SOSYAL BİLİMLER ÜNİVERSİTESİ","faculty":"Siyasal Bilgiler Fakültesi","city":"ANKARA","sector":"Devlet","program":"Uluslararası İlişkiler (İngilizce)","programRaw":"Uluslararası İlişkiler (İngilizce) (4 Yıllık)","scoreType":"EA","years":[{"year":2025,"quota":"30","placed":"32","rank":"47.670","rankNumeric":47670,"score":"386,40784","scoreNumeric":386.40784},{"year":2024,"quota":"65","placed":"69","rank":"86.580","rankNumeric":86580,"score":"366,48345","scoreNumeric":366.48345},{"year":2023,"quota":"60","placed":"62","rank":"96.131","rankNumeric":96131,"score":"373,62412","scoreNumeric":373.62412},{"year":2022,"quota":"60","placed":"62","rank":"125.947","rankNumeric":125947,"score":"367,88056","scoreNumeric":367.88056}]},{"university":"KOÇ ÜNİVERSİTESİ","faculty":"İktisadi ve İdari Bilimler Fakültesi","city":"İSTANBUL","sector":"Vakıf","program":"Uluslararası İlişkiler (İngilizce) (%50 İndirimli)","programRaw":"Uluslararası İlişkiler (İngilizce) (%50 İndirimli) (4 Yıllık)","scoreType":"EA","years":[{"year":2025,"quota":"10","placed":"10","rank":"52.365","rankNumeric":52365,"score":"383,3611","scoreNumeric":383.3611},{"year":2024,"quota":"—","placed":"—","rank":"…","rankNumeric":null,"score":"—","scoreNumeric":null},{"year":2023,"quota":"—","placed":"—","rank":"—","rankNumeric":null,"score":"—","scoreNumeric":null},{"year":2022,"quota":"—","placed":"—","rank":"—","rankNumeric":null,"score":"—","scoreNumeric":null}]},{"university":"YAŞAR ÜNİVERSİTESİ","faculty":"İnsan ve Toplum Bilimleri Fakültesi","city":"İZMİR","sector":"Vakıf","program":"Uluslararası İlişkiler (İngilizce) (Burslu)","programRaw":"Uluslararası İlişkiler (İngilizce) (Burslu) (4 Yıllık)","scoreType":"EA","years":[{"year":2025,"quota":"8","placed":"9","rank":"63.831","rankNumeric":63831,"score":"376,75066","scoreNumeric":376.75066},{"year":2024,"quota":"8","placed":"9","rank":"75.278","rankNumeric":75278,"score":"372,21877","scoreNumeric":372.21877},{"year":2023,"quota":"7","placed":"8","rank":"66.778","rankNumeric":66778,"score":"387,44090","scoreNumeric":387.4409},{"year":2022,"quota":"6","placed":"6","rank":"76.181","rankNumeric":76181,"score":"390,05670","scoreNumeric":390.0567}]},{"university":"ANKARA HACI BAYRAM VELİ ÜNİVERSİTESİ","faculty":"İktisadi ve İdari Bilimler Fakültesi","city":"ANKARA","sector":"Devlet","program":"Uluslararası İlişkiler (İngilizce)","programRaw":"Uluslararası İlişkiler (İngilizce) (4 Yıllık)","scoreType":"EA","years":[{"year":2025,"quota":"30","placed":"32","rank":"66.824","rankNumeric":66824,"score":"375,15038","scoreNumeric":375.15038},{"year":2024,"quota":"65","placed":"69","rank":"113.756","rankNumeric":113756,"score":"354,71610","scoreNumeric":354.7161},{"year":2023,"quota":"60","placed":"62","rank":"122.541","rankNumeric":122541,"score":"363,01260","scoreNumeric":363.0126},{"year":2022,"quota":"60","placed":"62","rank":"149.626","rankNumeric":149626,"score":"359,01759","scoreNumeric":359.01759}]},{"university":"ATILIM ÜNİVERSİTESİ","faculty":"İşletme Fakültesi","city":"ANKARA","sector":"Vakıf","program":"Uluslararası İlişkiler (İngilizce) (Burslu)","programRaw":"Uluslararası İlişkiler (İngilizce) (Burslu) (4 Yıllık)","scoreType":"EA","years":[{"year":2025,"quota":"4","placed":"5","rank":"70.769","rankNumeric":70769,"score":"373,03846","scoreNumeric":373.03846},{"year":2024,"quota":"4","placed":"6","rank":"107.025","rankNumeric":107025,"score":"357,41442","scoreNumeric":357.41442},{"year":2023,"quota":"4","placed":"5","rank":"110.729","rankNumeric":110729,"score":"367,52815","scoreNumeric":367.52815},{"year":2022,"quota":"4","placed":"4","rank":"130.272","rankNumeric":130272,"score":"366,20803","scoreNumeric":366.20803}]},{"university":"İHSAN DOĞRAMACI BİLKENT ÜNİVERSİTESİ","faculty":"İktisadi, İdari ve Sosyal Bilimler Fakültesi","city":"ANKARA","sector":"Vakıf","program":"Uluslararası İlişkiler (İngilizce) (%50 İndirimli)","programRaw":"Uluslararası İlişkiler (İngilizce) (%50 İndirimli) (4 Yıllık)","scoreType":"EA","years":[{"year":2025,"quota":"80","placed":"80","rank":"73.786","rankNumeric":73786,"score":"371,53878","scoreNumeric":371.53878},{"year":2024,"quota":"82","placed":"82","rank":"58.510","rankNumeric":58510,"score":"382,02124","scoreNumeric":382.02124},{"year":2023,"quota":"82","placed":"82","rank":"59.616","rankNumeric":59616,"score":"391,33184","scoreNumeric":391.33184},{"year":2022,"quota":"82","placed":"82","rank":"76.360","rankNumeric":76360,"score":"389,96029","scoreNumeric":389.96029}]},{"university":"MARMARA ÜNİVERSİTESİ","faculty":"Siyasal Bilgiler Fakültesi","city":"İSTANBUL","sector":"Devlet","program":"Uluslararası İlişkiler","programRaw":"Uluslararası İlişkiler (4 Yıllık)","scoreType":"EA","years":[{"year":2025,"quota":"50","placed":"52","rank":"79.570","rankNumeric":79570,"score":"368,73402","scoreNumeric":368.73402},{"year":2024,"quota":"75","placed":"77","rank":"124.298","rankNumeric":124298,"score":"350,70893","scoreNumeric":350.70893},{"year":2023,"quota":"70","placed":"73","rank":"134.020","rankNumeric":134020,"score":"358,87407","scoreNumeric":358.87407},{"year":2022,"quota":"70","placed":"72","rank":"153.982","rankNumeric":153982,"score":"357,48839","scoreNumeric":357.48839}]},{"university":"EGE ÜNİVERSİTESİ","faculty":"İktisadi ve İdari Bilimler Fakültesi","city":"İZMİR","sector":"Devlet","program":"Uluslararası İlişkiler","programRaw":"Uluslararası İlişkiler (4 Yıllık)","scoreType":"EA","years":[{"year":2025,"quota":"50","placed":"52","rank":"93.067","rankNumeric":93067,"score":"362,61416","scoreNumeric":362.61416},{"year":2024,"quota":"95","placed":"98","rank":"127.403","rankNumeric":127403,"score":"349,55187","scoreNumeric":349.55187},{"year":2023,"quota":"90","placed":"94","rank":"135.027","rankNumeric":135027,"score":"358,53593","scoreNumeric":358.53593},{"year":2022,"quota":"90","placed":"93","rank":"159.585","rankNumeric":159585,"score":"355,53870","scoreNumeric":355.5387}]},{"university":"İSTANBUL MEDENİYET ÜNİVERSİTESİ","faculty":"Siyasal Bilgiler Fakültesi","city":"İSTANBUL","sector":"Devlet","program":"Uluslararası İlişkiler (İngilizce)","programRaw":"Uluslararası İlişkiler (İngilizce) (4 Yıllık)","scoreType":"EA","years":[{"year":2025,"quota":"40","placed":"42","rank":"100.565","rankNumeric":100565,"score":"359,44715","scoreNumeric":359.44715},{"year":2024,"quota":"60","placed":"64","rank":"146.514","rankNumeric":146514,"score":"343,01611","scoreNumeric":343.01611},{"year":2023,"quota":"40","placed":"41","rank":"155.841","rankNumeric":155841,"score":"351,67476","scoreNumeric":351.67476},{"year":2022,"quota":"40","placed":"41","rank":"176.157","rankNumeric":176157,"score":"350,06189","scoreNumeric":350.06189}]},{"university":"BURSA ULUDAĞ ÜNİVERSİTESİ","faculty":"İktisadi ve İdari Bilimler Fakültesi","city":"BURSA","sector":"Devlet","program":"Uluslararası İlişkiler (İngilizce)","programRaw":"Uluslararası İlişkiler (İngilizce) (4 Yıllık)","scoreType":"EA","years":[{"year":2025,"quota":"50","placed":"52","rank":"105.908","rankNumeric":105908,"score":"357,28522","scoreNumeric":357.28522},{"year":2024,"quota":"60","placed":"62","rank":"136.023","rankNumeric":136023,"score":"346,50626","scoreNumeric":346.50626},{"year":2023,"quota":"60","placed":"63","rank":"149.190","rankNumeric":149190,"score":"353,75894","scoreNumeric":353.75894},{"year":2022,"quota":"60","placed":"62","rank":"170.289","rankNumeric":170289,"score":"351,94940","scoreNumeric":351.9494}]},{"university":"ANKARA YILDIRIM BEYAZIT ÜNİVERSİTESİ","faculty":"Siyasal Bilgiler Fakültesi","city":"ANKARA","sector":"Devlet","program":"Uluslararası İlişkiler (İngilizce)","programRaw":"Uluslararası İlişkiler (İngilizce) (4 Yıllık)","scoreType":"EA","years":[{"year":2025,"quota":"60","placed":"64","rank":"107.497","rankNumeric":107497,"score":"356,64747","scoreNumeric":356.64747},{"year":2024,"quota":"70","placed":"74","rank":"147.385","rankNumeric":147385,"score":"342,73152","scoreNumeric":342.73152},{"year":2023,"quota":"60","placed":"62","rank":"157.609","rankNumeric":157609,"score":"351,12235","scoreNumeric":351.12235},{"year":2022,"quota":"60","placed":"62","rank":"181.591","rankNumeric":181591,"score":"348,37740","scoreNumeric":348.3774}]},{"university":"ANKARA HACI BAYRAM VELİ ÜNİVERSİTESİ","faculty":"İktisadi ve İdari Bilimler Fakültesi","city":"ANKARA","sector":"Devlet","program":"Uluslararası İlişkiler","programRaw":"Uluslararası İlişkiler (4 Yıllık)","scoreType":"EA","years":[{"year":2025,"quota":"60","placed":"64","rank":"113.207","rankNumeric":113207,"score":"354,4401","scoreNumeric":354.4401},{"year":2024,"quota":"95","placed":"101","rank":"163.586","rankNumeric":163586,"score":"337,67610","scoreNumeric":337.6761},{"year":2023,"quota":"90","placed":"96","rank":"189.170","rankNumeric":189170,"score":"342,11450","scoreNumeric":342.1145},{"year":2022,"quota":"90","placed":"93","rank":"224.581","rankNumeric":224581,"score":"336,16525","scoreNumeric":336.16525}]},{"university":"ÇANAKKALE ONSEKİZ MART ÜNİVERSİTESİ","faculty":"Siyasal Bilgiler Fakültesi","city":"ÇANAKKALE","sector":"Devlet","program":"Uluslararası İlişkiler (İngilizce)","programRaw":"Uluslararası İlişkiler (İngilizce) (4 Yıllık)","scoreType":"EA","years":[{"year":2025,"quota":"40","placed":"41","rank":"126.873","rankNumeric":126873,"score":"349,46225","scoreNumeric":349.46225},{"year":2024,"quota":"50","placed":"54","rank":"160.657","rankNumeric":160657,"score":"338,56595","scoreNumeric":338.56595},{"year":2023,"quota":"40","placed":"41","rank":"173.538","rankNumeric":173538,"score":"346,40649","scoreNumeric":346.40649},{"year":2022,"quota":"40","placed":"41","rank":"210.164","rankNumeric":210164,"score":"339,99636","scoreNumeric":339.99636}]},{"university":"İSTİNYE ÜNİVERSİTESİ","faculty":"İktisadi, İdari ve Sosyal Bilimler Fakültesi","city":"İSTANBUL","sector":"Vakıf","program":"Uluslararası İlişkiler (İngilizce) (Burslu)","programRaw":"Uluslararası İlişkiler (İngilizce) (Burslu) (4 Yıllık)","scoreType":"EA","years":[{"year":2025,"quota":"5","placed":"6","rank":"129.025","rankNumeric":129025,"score":"348,716","scoreNumeric":348.716},{"year":2024,"quota":"4","placed":"5","rank":"156.795","rankNumeric":156795,"score":"339,73735","scoreNumeric":339.73735},{"year":2023,"quota":"4","placed":"5","rank":"162.761","rankNumeric":162761,"score":"349,56075","scoreNumeric":349.56075},{"year":2022,"quota":"5","placed":"5","rank":"179.858","rankNumeric":179858,"score":"348,89327","scoreNumeric":348.89327}]},{"university":"İSTANBUL MEDENİYET ÜNİVERSİTESİ","faculty":"Siyasal Bilgiler Fakültesi","city":"İSTANBUL","sector":"Devlet","program":"Uluslararası İlişkiler","programRaw":"Uluslararası İlişkiler (4 Yıllık)","scoreType":"EA","years":[{"year":2025,"quota":"40","placed":"42","rank":"136.549","rankNumeric":136549,"score":"346,17142","scoreNumeric":346.17142},{"year":2024,"quota":"65","placed":"69","rank":"184.129","rankNumeric":184129,"score":"332,00474","scoreNumeric":332.00474},{"year":2023,"quota":"60","placed":"64","rank":"207.074","rankNumeric":207074,"score":"337,59001","scoreNumeric":337.59001},{"year":2022,"quota":"60","placed":"62","rank":"240.425","rankNumeric":240425,"score":"332,23466","scoreNumeric":332.23466}]},{"university":"ESKİŞEHİR OSMANGAZİ ÜNİVERSİTESİ","faculty":"İktisadi ve İdari Bilimler Fakültesi","city":"ESKİŞEHİR","sector":"Devlet","program":"Uluslararası İlişkiler","programRaw":"Uluslararası İlişkiler (4 Yıllık)","scoreType":"EA","years":[{"year":2025,"quota":"40","placed":"42","rank":"140.023","rankNumeric":140023,"score":"345,03277","scoreNumeric":345.03277},{"year":2024,"quota":"70","placed":"74","rank":"188.721","rankNumeric":188721,"score":"330,80535","scoreNumeric":330.80535},{"year":2023,"quota":"60","placed":"62","rank":"207.234","rankNumeric":207234,"score":"337,55106","scoreNumeric":337.55106},{"year":2022,"quota":"60","placed":"62","rank":"241.743","rankNumeric":241743,"score":"331,92227","scoreNumeric":331.92227}]},{"university":"İSTANBUL BEYKENT ÜNİVERSİTESİ","faculty":"İktisadi ve İdari Bilimler Fakültesi","city":"İSTANBUL","sector":"Vakıf","program":"Uluslararası İlişkiler (İngilizce) (Burslu)","programRaw":"Uluslararası İlişkiler (İngilizce) (Burslu) (4 Yıllık)","scoreType":"EA","years":[{"year":2025,"quota":"5","placed":"6","rank":"144.697","rankNumeric":144697,"score":"343,54446","scoreNumeric":343.54446},{"year":2024,"quota":"7","placed":"8","rank":"176.093","rankNumeric":176093,"score":"334,14368","scoreNumeric":334.14368},{"year":2023,"quota":"5","placed":"6","rank":"181.909","rankNumeric":181909,"score":"344,06162","scoreNumeric":344.06162},{"year":2022,"quota":"5","placed":"5","rank":"167.421","rankNumeric":167421,"score":"352,92660","scoreNumeric":352.9266}]},{"university":"BURSA ULUDAĞ ÜNİVERSİTESİ","faculty":"İktisadi ve İdari Bilimler Fakültesi","city":"BURSA","sector":"Devlet","program":"Uluslararası İlişkiler","programRaw":"Uluslararası İlişkiler (4 Yıllık)","scoreType":"EA","years":[{"year":2025,"quota":"55","placed":"57","rank":"147.988","rankNumeric":147988,"score":"342,49044","scoreNumeric":342.49044},{"year":2024,"quota":"100","placed":"103","rank":"197.420","rankNumeric":197420,"score":"328,59104","scoreNumeric":328.59104},{"year":2023,"quota":"100","placed":"105","rank":"221.534","rankNumeric":221534,"score":"334,11234","scoreNumeric":334.11234},{"year":2022,"quota":"100","placed":"103","rank":"256.471","rankNumeric":256471,"score":"328,38689","scoreNumeric":328.38689}]},{"university":"AKDENİZ ÜNİVERSİTESİ","faculty":"İktisadi ve İdari Bilimler Fakültesi","city":"ANTALYA","sector":"Devlet","program":"Uluslararası İlişkiler","programRaw":"Uluslararası İlişkiler (4 Yıllık)","scoreType":"EA","years":[{"year":2025,"quota":"45","placed":"49","rank":"150.984","rankNumeric":150984,"score":"341,59267","scoreNumeric":341.59267},{"year":2024,"quota":"80","placed":"84","rank":"199.298","rankNumeric":199298,"score":"328,15082","scoreNumeric":328.15082},{"year":2023,"quota":"70","placed":"72","rank":"213.438","rankNumeric":213438,"score":"336,02242","scoreNumeric":336.02242},{"year":2022,"quota":"70","placed":"72","rank":"238.710","rankNumeric":238710,"score":"332,64150","scoreNumeric":332.6415}]},{"university":"IŞIK ÜNİVERSİTESİ","faculty":"İktisadi, İdari ve Sosyal Bilimler Fakültesi","city":"İSTANBUL","sector":"Vakıf","program":"Uluslararası İlişkiler (İngilizce) (Burslu)","programRaw":"Uluslararası İlişkiler (İngilizce) (Burslu) (4 Yıllık)","scoreType":"EA","years":[{"year":2025,"quota":"3","placed":"3","rank":"153.824","rankNumeric":153824,"score":"340,73407","scoreNumeric":340.73407},{"year":2024,"quota":"4","placed":"5","rank":"179.174","rankNumeric":179174,"score":"333,31979","scoreNumeric":333.31979},{"year":2023,"quota":"3","placed":"3","rank":"168.287","rankNumeric":168287,"score":"347,93139","scoreNumeric":347.93139},{"year":2022,"quota":"5","placed":"5","rank":"207.370","rankNumeric":207370,"score":"340,76440","scoreNumeric":340.7644}]},{"university":"DOĞUŞ ÜNİVERSİTESİ","faculty":"İktisadi ve İdari Bilimler Fakültesi","city":"İSTANBUL","sector":"Vakıf","program":"Uluslararası İlişkiler (İngilizce) (Burslu)","programRaw":"Uluslararası İlişkiler (İngilizce) (Burslu) (4 Yıllık)","scoreType":"EA","years":[{"year":2025,"quota":"6","placed":"7","rank":"157.925","rankNumeric":157925,"score":"339,5095","scoreNumeric":339.5095},{"year":2024,"quota":"7","placed":"8","rank":"190.335","rankNumeric":190335,"score":"330,37228","scoreNumeric":330.37228},{"year":2023,"quota":"5","placed":"6","rank":"205.117","rankNumeric":205117,"score":"338,07699","scoreNumeric":338.07699},{"year":2022,"quota":"5","placed":"5","rank":"218.004","rankNumeric":218004,"score":"337,88897","scoreNumeric":337.88897}]},{"university":"İZMİR KATİP ÇELEBİ ÜNİVERSİTESİ","faculty":"İktisadi ve İdari Bilimler Fakültesi","city":"İZMİR","sector":"Devlet","program":"Uluslararası İlişkiler (İngilizce)","programRaw":"Uluslararası İlişkiler (İngilizce) (4 Yıllık)","scoreType":"EA","years":[{"year":2025,"quota":"55","placed":"59","rank":"162.864","rankNumeric":162864,"score":"338,10463","scoreNumeric":338.10463},{"year":2024,"quota":"75","placed":"79","rank":"243.554","rankNumeric":243554,"score":"318,28377","scoreNumeric":318.28377},{"year":2023,"quota":"70","placed":"73","rank":"277.017","rankNumeric":277017,"score":"322,37495","scoreNumeric":322.37495},{"year":2022,"quota":"70","placed":"72","rank":"303.668","rankNumeric":303668,"score":"318,34106","scoreNumeric":318.34106}]},{"university":"ALTINBAŞ ÜNİVERSİTESİ","faculty":"İktisadi, İdari ve Sosyal Bilimler Fakültesi","city":"İSTANBUL","sector":"Vakıf","program":"Uluslararası İlişkiler (İngilizce) (Burslu)","programRaw":"Uluslararası İlişkiler (İngilizce) (Burslu) (4 Yıllık)","scoreType":"EA","years":[{"year":2025,"quota":"4","placed":"5","rank":"169.038","rankNumeric":169038,"score":"336,33717","scoreNumeric":336.33717},{"year":2024,"quota":"25","placed":"26","rank":"240.700","rankNumeric":240700,"score":"318,87563","scoreNumeric":318.87563},{"year":2023,"quota":"10","placed":"10","rank":"246.936","rankNumeric":246936,"score":"328,47588","scoreNumeric":328.47588},{"year":2022,"quota":"15","placed":"15","rank":"271.027","rankNumeric":271027,"score":"325,14731","scoreNumeric":325.14731}]},{"university":"AYDIN ADNAN MENDERES ÜNİVERSİTESİ","faculty":"Siyasal Bilgiler Fakültesi","city":"AYDIN","sector":"Devlet","program":"Uluslararası İlişkiler (İngilizce)","programRaw":"Uluslararası İlişkiler (İngilizce) (4 Yıllık)","scoreType":"EA","years":[{"year":2025,"quota":"50","placed":"52","rank":"186.529","rankNumeric":186529,"score":"331,62346","scoreNumeric":331.62346},{"year":2024,"quota":"70","placed":"74","rank":"246.212","rankNumeric":246212,"score":"317,74830","scoreNumeric":317.7483},{"year":2023,"quota":"60","placed":"62","rank":"243.221","rankNumeric":243221,"score":"329,27972","scoreNumeric":329.27972},{"year":2022,"quota":"60","placed":"62","rank":"272.677","rankNumeric":272677,"score":"324,78634","scoreNumeric":324.78634}]},{"university":"İSTANBUL KENT ÜNİVERSİTESİ","faculty":"İktisadi, İdari ve Sosyal Bilimler Fakültesi","city":"İSTANBUL","sector":"Vakıf","program":"Uluslararası İlişkiler (İngilizce) (Burslu)","programRaw":"Uluslararası İlişkiler (İngilizce) (Burslu) (4 Yıllık)","scoreType":"EA","years":[{"year":2025,"quota":"4","placed":"5","rank":"191.619","rankNumeric":191619,"score":"330,32612","scoreNumeric":330.32612},{"year":2024,"quota":"4","placed":"5","rank":"257.930","rankNumeric":257930,"score":"315,44037","scoreNumeric":315.44037},{"year":2023,"quota":"—","placed":"—","rank":"—","rankNumeric":null,"score":"—","scoreNumeric":null},{"year":2022,"quota":"—","placed":"—","rank":"—","rankNumeric":null,"score":"—","scoreNumeric":null}]},{"university":"İSTANBUL AREL ÜNİVERSİTESİ","faculty":"İktisadi ve İdari Bilimler Fakültesi","city":"İSTANBUL","sector":"Vakıf","program":"Uluslararası İlişkiler (Burslu)","programRaw":"Uluslararası İlişkiler (Burslu) (4 Yıllık)","scoreType":"EA","years":[{"year":2025,"quota":"4","placed":"4","rank":"195.103","rankNumeric":195103,"score":"329,46978","scoreNumeric":329.46978},{"year":2024,"quota":"4","placed":"5","rank":"291.537","rankNumeric":291537,"score":"309,36161","scoreNumeric":309.36161},{"year":2023,"quota":"—","placed":"—","rank":"—","rankNumeric":null,"score":"—","scoreNumeric":null},{"year":2022,"quota":"—","placed":"—","rank":"—","rankNumeric":null,"score":"—","scoreNumeric":null}]},{"university":"İSTANBUL NİŞANTAŞI ÜNİVERSİTESİ","faculty":"İktisadi, İdari ve Sosyal Bilimler Fakültesi","city":"İSTANBUL","sector":"Vakıf","program":"Uluslararası İlişkiler (İngilizce) (Burslu)","programRaw":"Uluslararası İlişkiler (İngilizce) (Burslu) (4 Yıllık)","scoreType":"EA","years":[{"year":2025,"quota":"10","placed":"11","rank":"195.985","rankNumeric":195985,"score":"329,23877","scoreNumeric":329.23877},{"year":2024,"quota":"8","placed":"8","rank":"197.391","rankNumeric":197391,"score":"328,60016","scoreNumeric":328.60016},{"year":2023,"quota":"7","placed":"8","rank":"205.919","rankNumeric":205919,"score":"337,87770","scoreNumeric":337.8777},{"year":2022,"quota":"6","placed":"6","rank":"236.290","rankNumeric":236290,"score":"333,20286","scoreNumeric":333.20286}]},{"university":"SELÇUK ÜNİVERSİTESİ","faculty":"İktisadi ve İdari Bilimler Fakültesi","city":"KONYA","sector":"Devlet","program":"Uluslararası İlişkiler (İngilizce)","programRaw":"Uluslararası İlişkiler (İngilizce) (4 Yıllık)","scoreType":"EA","years":[{"year":2025,"quota":"50","placed":"52","rank":"200.686","rankNumeric":200686,"score":"328,11066","scoreNumeric":328.11066},{"year":2024,"quota":"70","placed":"73","rank":"254.056","rankNumeric":254056,"score":"316,18452","scoreNumeric":316.18452},{"year":2023,"quota":"50","placed":"52","rank":"254.532","rankNumeric":254532,"score":"326,89514","scoreNumeric":326.89514},{"year":2022,"quota":"50","placed":"52","rank":"290.283","rankNumeric":290283,"score":"321,03014","scoreNumeric":321.03014}]},{"university":"İZMİR DEMOKRASİ ÜNİVERSİTESİ","faculty":"İktisadi ve İdari Bilimler Fakültesi","city":"İZMİR","sector":"Devlet","program":"Uluslararası İlişkiler (İngilizce)","programRaw":"Uluslararası İlişkiler (İngilizce) (4 Yıllık)","scoreType":"EA","years":[{"year":2025,"quota":"35","placed":"37","rank":"201.051","rankNumeric":201051,"score":"328,02106","scoreNumeric":328.02106},{"year":2024,"quota":"75","placed":"79","rank":"257.716","rankNumeric":257716,"score":"315,47903","scoreNumeric":315.47903},{"year":2023,"quota":"70","placed":"72","rank":"260.293","rankNumeric":260293,"score":"325,72385","scoreNumeric":325.72385},{"year":2022,"quota":"70","placed":"72","rank":"287.451","rankNumeric":287451,"score":"321,62217","scoreNumeric":321.62217}]},{"university":"İSTANBUL AREL ÜNİVERSİTESİ","faculty":"İktisadi ve İdari Bilimler Fakültesi","city":"İSTANBUL","sector":"Vakıf","program":"Uluslararası İlişkiler (İngilizce) (Burslu)","programRaw":"Uluslararası İlişkiler (İngilizce) (Burslu) (4 Yıllık)","scoreType":"EA","years":[{"year":2025,"quota":"4","placed":"5","rank":"201.433","rankNumeric":201433,"score":"327,91945","scoreNumeric":327.91945},{"year":2024,"quota":"5","placed":"6","rank":"229.775","rankNumeric":229775,"score":"321,17430","scoreNumeric":321.1743},{"year":2023,"quota":"4","placed":"4","rank":"223.153","rankNumeric":223153,"score":"333,74024","scoreNumeric":333.74024},{"year":2022,"quota":"7","placed":"7","rank":"243.572","rankNumeric":243572,"score":"331,47525","scoreNumeric":331.47525}]},{"university":"KARADENİZ TEKNİK ÜNİVERSİTESİ","faculty":"İktisadi ve İdari Bilimler Fakültesi","city":"TRABZON","sector":"Devlet","program":"Uluslararası İlişkiler (İngilizce)","programRaw":"Uluslararası İlişkiler (İngilizce) (4 Yıllık)","scoreType":"EA","years":[{"year":2025,"quota":"45","placed":"47","rank":"203.071","rankNumeric":203071,"score":"327,52174","scoreNumeric":327.52174},{"year":2024,"quota":"65","placed":"67","rank":"265.078","rankNumeric":265078,"score":"314,09294","scoreNumeric":314.09294},{"year":2023,"quota":"60","placed":"62","rank":"286.003","rankNumeric":286003,"score":"320,62668","scoreNumeric":320.62668},{"year":2022,"quota":"60","placed":"62","rank":"313.200","rankNumeric":313200,"score":"316,46269","scoreNumeric":316.46269}]},{"university":"BURSA TEKNİK ÜNİVERSİTESİ","faculty":"İnsan ve Toplum Bilimleri Fakültesi","city":"BURSA","sector":"Devlet","program":"Uluslararası İlişkiler","programRaw":"Uluslararası İlişkiler (4 Yıllık)","scoreType":"EA","years":[{"year":2025,"quota":"45","placed":"49","rank":"213.131","rankNumeric":213131,"score":"325,15784","scoreNumeric":325.15784},{"year":2024,"quota":"70","placed":"74","rank":"291.021","rankNumeric":291021,"score":"309,44568","scoreNumeric":309.44568},{"year":2023,"quota":"60","placed":"62","rank":"371.135","rankNumeric":371135,"score":"306,09364","scoreNumeric":306.09364},{"year":2022,"quota":"60","placed":"62","rank":"378.911","rankNumeric":378911,"score":"304,84969","scoreNumeric":304.84969}]},{"university":"KOCAELİ ÜNİVERSİTESİ","faculty":"Siyasal Bilgiler Fakültesi","city":"KOCAELİ","sector":"Devlet","program":"Uluslararası İlişkiler","programRaw":"Uluslararası İlişkiler (4 Yıllık)","scoreType":"EA","years":[{"year":2025,"quota":"65","placed":"68","rank":"219.586","rankNumeric":219586,"score":"323,6491","scoreNumeric":323.6491},{"year":2024,"quota":"95","placed":"101","rank":"313.560","rankNumeric":313560,"score":"305,67316","scoreNumeric":305.67316},{"year":2023,"quota":"90","placed":"93","rank":"351.499","rankNumeric":351499,"score":"309,16951","scoreNumeric":309.16951},{"year":2022,"quota":"90","placed":"93","rank":"366.287","rankNumeric":366287,"score":"306,93352","scoreNumeric":306.93352}]},{"university":"ÇAĞ ÜNİVERSİTESİ","faculty":"İktisadi ve İdari Bilimler Fakültesi","city":"MERSİN","sector":"Vakıf","program":"Uluslararası İlişkiler (İngilizce) (Burslu)","programRaw":"Uluslararası İlişkiler (İngilizce) (Burslu) (4 Yıllık)","scoreType":"EA","years":[{"year":2025,"quota":"6","placed":"7","rank":"221.614","rankNumeric":221614,"score":"323,20702","scoreNumeric":323.20702},{"year":2024,"quota":"5","placed":"7","rank":"237.708","rankNumeric":237708,"score":"319,48590","scoreNumeric":319.4859},{"year":2023,"quota":"6","placed":"7","rank":"245.156","rankNumeric":245156,"score":"328,85775","scoreNumeric":328.85775},{"year":2022,"quota":"6","placed":"6","rank":"293.160","rankNumeric":293160,"score":"320,45580","scoreNumeric":320.4558}]},{"university":"ERCİYES ÜNİVERSİTESİ","faculty":"İktisadi ve İdari Bilimler Fakültesi","city":"KAYSERİ","sector":"Devlet","program":"Uluslararası İlişkiler (İngilizce)","programRaw":"Uluslararası İlişkiler (İngilizce) (4 Yıllık)","scoreType":"EA","years":[{"year":2025,"quota":"40","placed":"41","rank":"227.747","rankNumeric":227747,"score":"321,84926","scoreNumeric":321.84926},{"year":2024,"quota":"85","placed":"88","rank":"320.432","rankNumeric":320432,"score":"304,54204","scoreNumeric":304.54204},{"year":2023,"quota":"80","placed":"83","rank":"361.444","rankNumeric":361444,"score":"307,58212","scoreNumeric":307.58212},{"year":2022,"quota":"80","placed":"82","rank":"412.688","rankNumeric":412688,"score":"299,59151","scoreNumeric":299.59151}]},{"university":"İSTANBUL NİŞANTAŞI ÜNİVERSİTESİ","faculty":"İktisadi, İdari ve Sosyal Bilimler Fakültesi","city":"İSTANBUL","sector":"Vakıf","program":"Uluslararası İlişkiler (Burslu)","programRaw":"Uluslararası İlişkiler (Burslu) (4 Yıllık)","scoreType":"EA","years":[{"year":2025,"quota":"10","placed":"12","rank":"232.154","rankNumeric":232154,"score":"320,87753","scoreNumeric":320.87753},{"year":2024,"quota":"4","placed":"5","rank":"294.238","rankNumeric":294238,"score":"308,90505","scoreNumeric":308.90505},{"year":2023,"quota":"—","placed":"—","rank":"—","rankNumeric":null,"score":"—","scoreNumeric":null},{"year":2022,"quota":"—","placed":"—","rank":"—","rankNumeric":null,"score":"—","scoreNumeric":null}]},{"university":"SAKARYA ÜNİVERSİTESİ","faculty":"Siyasal Bilgiler Fakültesi","city":"SAKARYA","sector":"Devlet","program":"Uluslararası İlişkiler","programRaw":"Uluslararası İlişkiler (4 Yıllık)","scoreType":"EA","years":[{"year":2025,"quota":"50","placed":"53","rank":"250.813","rankNumeric":250813,"score":"316,98128","scoreNumeric":316.98128},{"year":2024,"quota":"95","placed":"101","rank":"354.002","rankNumeric":354002,"score":"299,35060","scoreNumeric":299.3506},{"year":2023,"quota":"90","placed":"93","rank":"409.674","rankNumeric":409674,"score":"300,40429","scoreNumeric":300.40429},{"year":2022,"quota":"90","placed":"93","rank":"420.096","rankNumeric":420096,"score":"298,48410","scoreNumeric":298.4841}]},{"university":"YALOVA ÜNİVERSİTESİ","faculty":"Yalova İktisadi ve İdari Bilimler Fakültesi","city":"YALOVA","sector":"Devlet","program":"Uluslararası İlişkiler (İngilizce)","programRaw":"Uluslararası İlişkiler (İngilizce) (4 Yıllık)","scoreType":"EA","years":[{"year":2025,"quota":"50","placed":"53","rank":"253.616","rankNumeric":253616,"score":"316,39012","scoreNumeric":316.39012},{"year":2024,"quota":"70","placed":"73","rank":"332.251","rankNumeric":332251,"score":"302,66645","scoreNumeric":302.66645},{"year":2023,"quota":"60","placed":"64","rank":"370.511","rankNumeric":370511,"score":"306,18567","scoreNumeric":306.18567},{"year":2022,"quota":"60","placed":"62","rank":"372.075","rankNumeric":372075,"score":"305,96603","scoreNumeric":305.96603}]},{"university":"MERSİN ÜNİVERSİTESİ","faculty":"İktisadi ve İdari Bilimler Fakültesi","city":"MERSİN","sector":"Devlet","program":"Uluslararası İlişkiler","programRaw":"Uluslararası İlişkiler (4 Yıllık)","scoreType":"EA","years":[{"year":2025,"quota":"40","placed":"42","rank":"271.577","rankNumeric":271577,"score":"312,93066","scoreNumeric":312.93066},{"year":2024,"quota":"65","placed":"69","rank":"391.209","rankNumeric":391209,"score":"294,10169","scoreNumeric":294.10169},{"year":2023,"quota":"60","placed":"62","rank":"427.095","rankNumeric":427095,"score":"297,95507","scoreNumeric":297.95507},{"year":2022,"quota":"60","placed":"62","rank":"432.924","rankNumeric":432924,"score":"296,60483","scoreNumeric":296.60483}]},{"university":"İSTANBUL RUMELİ ÜNİVERSİTESİ","faculty":"İktisadi, İdari ve Sosyal Bilimler Fakültesi","city":"İSTANBUL","sector":"Vakıf","program":"Uluslararası İlişkiler (Burslu)","programRaw":"Uluslararası İlişkiler (Burslu) (4 Yıllık)","scoreType":"EA","years":[{"year":2025,"quota":"8","placed":"8","rank":"272.256","rankNumeric":272256,"score":"312,80261","scoreNumeric":312.80261},{"year":2024,"quota":"8","placed":"9","rank":"315.164","rankNumeric":315164,"score":"305,41116","scoreNumeric":305.41116},{"year":2023,"quota":"16","placed":"17","rank":"407.970","rankNumeric":407970,"score":"300,65406","scoreNumeric":300.65406},{"year":2022,"quota":"30","placed":"30","rank":"468.883","rankNumeric":468883,"score":"291,55011","scoreNumeric":291.55011}]},{"university":"KARADENİZ TEKNİK ÜNİVERSİTESİ","faculty":"İktisadi ve İdari Bilimler Fakültesi","city":"TRABZON","sector":"Devlet","program":"Uluslararası İlişkiler","programRaw":"Uluslararası İlişkiler (4 Yıllık)","scoreType":"EA","years":[{"year":2025,"quota":"60","placed":"62","rank":"288.372","rankNumeric":288372,"score":"309,8617","scoreNumeric":309.8617},{"year":2024,"quota":"115","placed":"118","rank":"468.791","rankNumeric":468791,"score":"284,27235","scoreNumeric":284.27235},{"year":2023,"quota":"110","placed":"113","rank":"532.683","rankNumeric":532683,"score":"284,51771","scoreNumeric":284.51771},{"year":2022,"quota":"110","placed":"113","rank":"530.241","rankNumeric":530241,"score":"283,78008","scoreNumeric":283.78008}]},{"university":"İHSAN DOĞRAMACI BİLKENT ÜNİVERSİTESİ","faculty":"İktisadi, İdari ve Sosyal Bilimler Fakültesi","city":"ANKARA","sector":"Vakıf","program":"Uluslararası İlişkiler (İngilizce) (Ücretli)","programRaw":"Uluslararası İlişkiler (İngilizce) (Ücretli) (4 Yıllık)","scoreType":"EA","years":[{"year":2025,"quota":"39","placed":"39","rank":"304.185","rankNumeric":304185,"score":"307,08918","scoreNumeric":307.08918},{"year":2024,"quota":"40","placed":"40","rank":"180.891","rankNumeric":180891,"score":"332,85542","scoreNumeric":332.85542},{"year":2023,"quota":"40","placed":"40","rank":"210.224","rankNumeric":210224,"score":"336,82300","scoreNumeric":336.823},{"year":2022,"quota":"40","placed":"40","rank":"178.148","rankNumeric":178148,"score":"349,42513","scoreNumeric":349.42513}]},{"university":"ÇANAKKALE ONSEKİZ MART ÜNİVERSİTESİ","faculty":"Biga İktisadi ve İdari Bilimler Fakültesi","city":"ÇANAKKALE","sector":"Devlet","program":"Uluslararası İlişkiler","programRaw":"Uluslararası İlişkiler (4 Yıllık)","scoreType":"EA","years":[{"year":2025,"quota":"45","placed":"47","rank":"304.970","rankNumeric":304970,"score":"306,95123","scoreNumeric":306.95123},{"year":2024,"quota":"95","placed":"98","rank":"435.264","rankNumeric":435264,"score":"288,36265","scoreNumeric":288.36265},{"year":2023,"quota":"90","placed":"93","rank":"522.685","rankNumeric":522685,"score":"285,70474","scoreNumeric":285.70474},{"year":2022,"quota":"90","placed":"93","rank":"517.195","rankNumeric":517195,"score":"285,36533","scoreNumeric":285.36533}]},{"university":"BOLU ABANT İZZET BAYSAL ÜNİVERSİTESİ","faculty":"İktisadi ve İdari Bilimler Fakültesi","city":"BOLU","sector":"Devlet","program":"Uluslararası İlişkiler","programRaw":"Uluslararası İlişkiler (4 Yıllık)","scoreType":"EA","years":[{"year":2025,"quota":"50","placed":"52","rank":"331.208","rankNumeric":331208,"score":"302,62143","scoreNumeric":302.62143},{"year":2024,"quota":"80","placed":"83","rank":"493.625","rankNumeric":493625,"score":"281,38118","scoreNumeric":281.38118},{"year":2023,"quota":"70","placed":"73","rank":"580.029","rankNumeric":580029,"score":"279,13330","scoreNumeric":279.1333},{"year":2022,"quota":"70","placed":"72","rank":"563.283","rankNumeric":563283,"score":"279,87901","scoreNumeric":279.87901}]},{"university":"KOÇ ÜNİVERSİTESİ","faculty":"İktisadi ve İdari Bilimler Fakültesi","city":"İSTANBUL","sector":"Vakıf","program":"Uluslararası İlişkiler (İngilizce) (Ücretli)","programRaw":"Uluslararası İlişkiler (İngilizce) (Ücretli) (4 Yıllık)","scoreType":"EA","years":[{"year":2025,"quota":"41","placed":"41","rank":"350.170","rankNumeric":350170,"score":"299,72111","scoreNumeric":299.72111},{"year":2024,"quota":"71","placed":"71","rank":"321.549","rankNumeric":321549,"score":"304,35656","scoreNumeric":304.35656},{"year":2023,"quota":"82","placed":"82","rank":"338.508","rankNumeric":338508,"score":"311,29151","scoreNumeric":311.29151},{"year":2022,"quota":"85","placed":"85","rank":"306.008","rankNumeric":306008,"score":"317,88437","scoreNumeric":317.88437}]},{"university":"BANDIRMA ONYEDİ EYLÜL ÜNİVERSİTESİ","faculty":"İktisadi ve İdari Bilimler Fakültesi","city":"BALIKESİR","sector":"Devlet","program":"Uluslararası İlişkiler","programRaw":"Uluslararası İlişkiler (4 Yıllık)","scoreType":"EA","years":[{"year":2025,"quota":"50","placed":"53","rank":"350.762","rankNumeric":350762,"score":"299,63411","scoreNumeric":299.63411},{"year":2024,"quota":"70","placed":"72","rank":"494.469","rankNumeric":494469,"score":"281,28461","scoreNumeric":281.28461},{"year":2023,"quota":"60","placed":"62","rank":"591.292","rankNumeric":591292,"score":"277,88661","scoreNumeric":277.88661},{"year":2022,"quota":"60","placed":"62","rank":"595.838","rankNumeric":595838,"score":"276,23385","scoreNumeric":276.23385}]},{"university":"TEKİRDAĞ NAMIK KEMAL ÜNİVERSİTESİ","faculty":"İktisadi ve İdari Bilimler Fakültesi","city":"TEKİRDAĞ","sector":"Devlet","program":"Uluslararası İlişkiler","programRaw":"Uluslararası İlişkiler (4 Yıllık)","scoreType":"EA","years":[{"year":2025,"quota":"40","placed":"42","rank":"352.100","rankNumeric":352100,"score":"299,4399","scoreNumeric":299.4399},{"year":2024,"quota":"70","placed":"74","rank":"503.762","rankNumeric":503762,"score":"280,23789","scoreNumeric":280.23789},{"year":2023,"quota":"60","placed":"62","rank":"583.797","rankNumeric":583797,"score":"278,70793","scoreNumeric":278.70793},{"year":2022,"quota":"60","placed":"62","rank":"571.785","rankNumeric":571785,"score":"278,92471","scoreNumeric":278.92471}]},{"university":"TRAKYA ÜNİVERSİTESİ","faculty":"İktisadi ve İdari Bilimler Fakültesi","city":"EDİRNE","sector":"Devlet","program":"Uluslararası İlişkiler","programRaw":"Uluslararası İlişkiler (4 Yıllık)","scoreType":"EA","years":[{"year":2025,"quota":"50","placed":"52","rank":"356.814","rankNumeric":356814,"score":"298,73192","scoreNumeric":298.73192},{"year":2024,"quota":"75","placed":"78","rank":"469.835","rankNumeric":469835,"score":"284,14526","scoreNumeric":284.14526},{"year":2023,"quota":"70","placed":"72","rank":"579.059","rankNumeric":579059,"score":"279,24351","scoreNumeric":279.24351},{"year":2022,"quota":"70","placed":"72","rank":"564.279","rankNumeric":564279,"score":"279,76542","scoreNumeric":279.76542}]},{"university":"DOĞU AKDENİZ ÜNİVERSİTESİ","faculty":"İşletme ve Ekonomi Fakültesi (KKTC-GAZİMAĞUSA) (KKTC )","city":null,"sector":null,"program":"Uluslararası İlişkiler (İngilizce) (Burslu)","programRaw":"Uluslararası İlişkiler (İngilizce) (Burslu) (4 Yıllık)","scoreType":"EA","years":[{"year":2025,"quota":"8","placed":"8","rank":"362.905","rankNumeric":362905,"score":"297,8191","scoreNumeric":297.8191},{"year":2024,"quota":"8","placed":"8","rank":"438.722","rankNumeric":438722,"score":"287,93764","scoreNumeric":287.93764},{"year":2023,"quota":"8","placed":"8","rank":"483.694","rankNumeric":483694,"score":"290,46198","scoreNumeric":290.46198},{"year":2022,"quota":"10","placed":"10","rank":"529.233","rankNumeric":529233,"score":"283,90646","scoreNumeric":283.90646}]},{"university":"SELÇUK ÜNİVERSİTESİ","faculty":"İktisadi ve İdari Bilimler Fakültesi","city":"KONYA","sector":"Devlet","program":"Uluslararası İlişkiler","programRaw":"Uluslararası İlişkiler (4 Yıllık)","scoreType":"EA","years":[{"year":2025,"quota":"60","placed":"62","rank":"364.478","rankNumeric":364478,"score":"297,59062","scoreNumeric":297.59062},{"year":2024,"quota":"105","placed":"111","rank":"529.600","rankNumeric":529600,"score":"277,41636","scoreNumeric":277.41636},{"year":2023,"quota":"100","placed":"104","rank":"620.419","rankNumeric":620419,"score":"274,75884","scoreNumeric":274.75884},{"year":2022,"quota":"100","placed":"103","rank":"609.467","rankNumeric":609467,"score":"274,77292","scoreNumeric":274.77292}]},{"university":"ÖZYEĞİN ÜNİVERSİTESİ","faculty":"Sosyal Bilimler Fakültesi","city":"İSTANBUL","sector":"Vakıf","program":"Uluslararası İlişkiler (İngilizce) (%50 İndirimli)","programRaw":"Uluslararası İlişkiler (İngilizce) (%50 İndirimli) (4 Yıllık)","scoreType":"EA","years":[{"year":2025,"quota":"41","placed":"41","rank":"374.766","rankNumeric":374766,"score":"296,08513","scoreNumeric":296.08513},{"year":2024,"quota":"38","placed":"38","rank":"405.145","rankNumeric":405145,"score":"292,21917","scoreNumeric":292.21917},{"year":2023,"quota":"43","placed":"43","rank":"565.357","rankNumeric":565357,"score":"280,78347","scoreNumeric":280.78347},{"year":2022,"quota":"42","placed":"42","rank":"315.524","rankNumeric":315524,"score":"316,02755","scoreNumeric":316.02755}]},{"university":"ADANA ALPARSLAN TÜRKEŞ BİLİM VE TEKNOLOJİ ÜNİVERSİTESİ","faculty":"İktisadi, İdari ve Sosyal Bilimler Fakültesi","city":"ADANA","sector":"Devlet","program":"Uluslararası İlişkiler (İngilizce)","programRaw":"Uluslararası İlişkiler (İngilizce) (4 Yıllık)","scoreType":"EA","years":[{"year":2025,"quota":"45","placed":"54","rank":"386.659","rankNumeric":386659,"score":"294,40168","scoreNumeric":294.40168},{"year":2024,"quota":"60","placed":"79","rank":"518.405","rankNumeric":518405,"score":"278,633","scoreNumeric":278.633},{"year":2023,"quota":"55","placed":"73","rank":"541.507","rankNumeric":541507,"score":"283,50263","scoreNumeric":283.50263},{"year":2022,"quota":"55","placed":"57","rank":"569.960","rankNumeric":569960,"score":"279,12566","scoreNumeric":279.12566}]},{"university":"NEVŞEHİR HACI BEKTAŞ VELİ ÜNİVERSİTESİ","faculty":"İktisadi ve İdari Bilimler Fakültesi","city":"NEVŞEHİR","sector":"Devlet","program":"Uluslararası İlişkiler (İngilizce)","programRaw":"Uluslararası İlişkiler (İngilizce) (4 Yıllık)","scoreType":"EA","years":[{"year":2025,"quota":"40","placed":"41","rank":"391.915","rankNumeric":391915,"score":"293,66583","scoreNumeric":293.66583},{"year":2024,"quota":"60","placed":"63","rank":"564.954","rankNumeric":564954,"score":"273,69752","scoreNumeric":273.69752},{"year":2023,"quota":"40","placed":"41","rank":"698.232","rankNumeric":698232,"score":"266,85590","scoreNumeric":266.8559},{"year":2022,"quota":"40","placed":"41","rank":"759.716","rankNumeric":759716,"score":"260,05244","scoreNumeric":260.05244}]},{"university":"AYDIN ADNAN MENDERES ÜNİVERSİTESİ","faculty":"Nazilli İktisadi ve İdari Bilimler Fakültesi","city":"AYDIN","sector":"Devlet","program":"Uluslararası İlişkiler","programRaw":"Uluslararası İlişkiler (4 Yıllık)","scoreType":"EA","years":[{"year":2025,"quota":"40","placed":"41","rank":"397.296","rankNumeric":397296,"score":"292,91063","scoreNumeric":292.91063},{"year":2024,"quota":"85","placed":"89","rank":"566.322","rankNumeric":566322,"score":"273,55630","scoreNumeric":273.5563},{"year":2023,"quota":"80","placed":"83","rank":"643.969","rankNumeric":643969,"score":"272,28402","scoreNumeric":272.28402},{"year":2022,"quota":"80","placed":"82","rank":"616.038","rankNumeric":616038,"score":"274,06134","scoreNumeric":274.06134}]},{"university":"SÜLEYMAN DEMİREL ÜNİVERSİTESİ","faculty":"İktisadi ve İdari Bilimler Fakültesi","city":"ISPARTA","sector":"Devlet","program":"Uluslararası İlişkiler","programRaw":"Uluslararası İlişkiler (4 Yıllık)","scoreType":"EA","years":[{"year":2025,"quota":"45","placed":"48","rank":"404.211","rankNumeric":404211,"score":"291,96259","scoreNumeric":291.96259},{"year":2024,"quota":"80","placed":"82","rank":"555.544","rankNumeric":555544,"score":"274,67703","scoreNumeric":274.67703},{"year":2023,"quota":"80","placed":"82","rank":"635.230","rankNumeric":635230,"score":"273,20213","scoreNumeric":273.20213},{"year":2022,"quota":"80","placed":"82","rank":"640.308","rankNumeric":640308,"score":"271,50004","scoreNumeric":271.50004}]},{"university":"ÖZYEĞİN ÜNİVERSİTESİ","faculty":"Sosyal Bilimler Fakültesi","city":"İSTANBUL","sector":"Vakıf","program":"Uluslararası İlişkiler (İngilizce) (Ücretli)","programRaw":"Uluslararası İlişkiler (İngilizce) (Ücretli) (4 Yıllık)","scoreType":"EA","years":[{"year":2025,"quota":"2","placed":"2","rank":"443.806","rankNumeric":443806,"score":"286,81544","scoreNumeric":286.81544},{"year":2024,"quota":"3","placed":"3","rank":"411.588","rankNumeric":411588,"score":"291,37785","scoreNumeric":291.37785},{"year":2023,"quota":"5","placed":"5","rank":"489.529","rankNumeric":489529,"score":"289,74248","scoreNumeric":289.74248},{"year":2022,"quota":"—","placed":"—","rank":"—","rankNumeric":null,"score":"—","scoreNumeric":null}]},{"university":"RECEP TAYYİP ERDOĞAN ÜNİVERSİTESİ","faculty":"İktisadi ve İdari Bilimler Fakültesi","city":"RİZE","sector":"Devlet","program":"Uluslararası İlişkiler (İngilizce)","programRaw":"Uluslararası İlişkiler (İngilizce) (4 Yıllık)","scoreType":"EA","years":[{"year":2025,"quota":"50","placed":"53","rank":"515.972","rankNumeric":515972,"score":"278,28961","scoreNumeric":278.28961},{"year":2024,"quota":"60","placed":"62","rank":"681.351","rankNumeric":681351,"score":"262,54421","scoreNumeric":262.54421},{"year":2023,"quota":"40","placed":"41","rank":"729.531","rankNumeric":729531,"score":"263,84757","scoreNumeric":263.84757},{"year":2022,"quota":"40","placed":"41","rank":"828.276","rankNumeric":828276,"score":"254,07177","scoreNumeric":254.07177}]},{"university":"KIRIKKALE ÜNİVERSİTESİ","faculty":"İktisadi ve İdari Bilimler Fakültesi","city":"KIRIKKALE","sector":"Devlet","program":"Uluslararası İlişkiler","programRaw":"Uluslararası İlişkiler (4 Yıllık)","scoreType":"EA","years":[{"year":2025,"quota":"45","placed":"47","rank":"537.900","rankNumeric":537900,"score":"275,83702","scoreNumeric":275.83702},{"year":2024,"quota":"85","placed":"91","rank":"742.838","rankNumeric":742838,"score":"257,20177","scoreNumeric":257.20177},{"year":2023,"quota":"80","placed":"83","rank":"828.227","rankNumeric":828227,"score":"254,91411","scoreNumeric":254.91411},{"year":2022,"quota":"80","placed":"82","rank":"852.966","rankNumeric":852966,"score":"252,00841","scoreNumeric":252.00841}]},{"university":"NEVŞEHİR HACI BEKTAŞ VELİ ÜNİVERSİTESİ","faculty":"İktisadi ve İdari Bilimler Fakültesi","city":"NEVŞEHİR","sector":"Devlet","program":"Uluslararası İlişkiler","programRaw":"Uluslararası İlişkiler (4 Yıllık)","scoreType":"EA","years":[{"year":2025,"quota":"50","placed":"52","rank":"550.193","rankNumeric":550193,"score":"274,49906","scoreNumeric":274.49906},{"year":2024,"quota":"75","placed":"78","rank":"779.881","rankNumeric":779881,"score":"254,15211","scoreNumeric":254.15211},{"year":2023,"quota":"70","placed":"72","rank":"954.219","rankNumeric":954219,"score":"244,41724","scoreNumeric":244.41724},{"year":2022,"quota":"60","placed":"62","rank":"993.006","rankNumeric":993006,"score":"240,99875","scoreNumeric":240.99875}]},{"university":"DÜZCE ÜNİVERSİTESİ","faculty":"Akçakoca Bey Siyasal Bilgiler Fakültesi","city":"DÜZCE","sector":"Devlet","program":"Uluslararası İlişkiler","programRaw":"Uluslararası İlişkiler (4 Yıllık)","scoreType":"EA","years":[{"year":2025,"quota":"45","placed":"48","rank":"557.637","rankNumeric":557637,"score":"273,69073","scoreNumeric":273.69073},{"year":2024,"quota":"70","placed":"72","rank":"738.596","rankNumeric":738596,"score":"257,56298","scoreNumeric":257.56298},{"year":2023,"quota":"60","placed":"62","rank":"845.391","rankNumeric":845391,"score":"253,42042","scoreNumeric":253.42042},{"year":2022,"quota":"60","placed":"62","rank":"877.931","rankNumeric":877931,"score":"249,97662","scoreNumeric":249.97662}]},{"university":"YAŞAR ÜNİVERSİTESİ","faculty":"İnsan ve Toplum Bilimleri Fakültesi","city":"İZMİR","sector":"Vakıf","program":"Uluslararası İlişkiler (İngilizce) (%50 İndirimli)","programRaw":"Uluslararası İlişkiler (İngilizce) (%50 İndirimli) (4 Yıllık)","scoreType":"EA","years":[{"year":2025,"quota":"41","placed":"41","rank":"607.790","rankNumeric":607790,"score":"268,4912","scoreNumeric":268.4912},{"year":2024,"quota":"38","placed":"38","rank":"597.240","rankNumeric":597240,"score":"270,44907","scoreNumeric":270.44907},{"year":2023,"quota":"38","placed":"38","rank":"636.757","rankNumeric":636757,"score":"273,04002","scoreNumeric":273.04002},{"year":2022,"quota":"33","placed":"33","rank":"606.542","rankNumeric":606542,"score":"275,08569","scoreNumeric":275.08569}]},{"university":"ATATÜRK ÜNİVERSİTESİ","faculty":"İktisadi ve İdari Bilimler Fakültesi","city":"ERZURUM","sector":"Devlet","program":"Uluslararası İlişkiler","programRaw":"Uluslararası İlişkiler (4 Yıllık)","scoreType":"EA","years":[{"year":2025,"quota":"60","placed":"62","rank":"621.612","rankNumeric":621612,"score":"267,09253","scoreNumeric":267.09253},{"year":2024,"quota":"100","placed":"103","rank":"939.178","rankNumeric":939178,"score":"241,80390","scoreNumeric":241.8039},{"year":2023,"quota":"100","placed":"103","rank":"1.051.459","rankNumeric":1051459,"score":"236,88818","scoreNumeric":236.88818},{"year":2022,"quota":"100","placed":"103","rank":"1.012.695","rankNumeric":1012695,"score":"239,51543","scoreNumeric":239.51543}]},{"university":"KIRKLARELİ ÜNİVERSİTESİ","faculty":"İktisadi ve İdari Bilimler Fakültesi","city":"KIRKLARELİ","sector":"Devlet","program":"Uluslararası İlişkiler","programRaw":"Uluslararası İlişkiler (4 Yıllık)","scoreType":"EA","years":[{"year":2025,"quota":"55","placed":"58","rank":"626.083","rankNumeric":626083,"score":"266,65023","scoreNumeric":266.65023},{"year":2024,"quota":"65","placed":"68","rank":"815.679","rankNumeric":815679,"score":"251,25154","scoreNumeric":251.25154},{"year":2023,"quota":"60","placed":"62","rank":"940.883","rankNumeric":940883,"score":"245,49318","scoreNumeric":245.49318},{"year":2022,"quota":"50","placed":"52","rank":"952.337","rankNumeric":952337,"score":"244,07461","scoreNumeric":244.07461}]},{"university":"ANADOLU ÜNİVERSİTESİ","faculty":"Açıköğretim Fakültesi","city":"ESKİŞEHİR","sector":"Devlet","program":"Uluslararası İlişkiler (Açıköğretim)","programRaw":"Uluslararası İlişkiler (Açıköğretim) (4 Yıllık)","scoreType":"EA","years":[{"year":2025,"quota":"250","placed":"264","rank":"674.312","rankNumeric":674312,"score":"262,01158","scoreNumeric":262.01158},{"year":2024,"quota":"700","placed":"736","rank":"1.089.827","rankNumeric":1089827,"score":"231,01018","scoreNumeric":231.01018},{"year":2023,"quota":"600","placed":"630","rank":"991.684","rankNumeric":991684,"score":"241,48330","scoreNumeric":241.4833},{"year":2022,"quota":"600","placed":"615","rank":"983.311","rankNumeric":983311,"score":"241,73375","scoreNumeric":241.73375}]},{"university":"KARABÜK ÜNİVERSİTESİ","faculty":"İktisadi ve İdari Bilimler Fakültesi","city":"KARABÜK","sector":"Devlet","program":"Uluslararası İlişkiler (İngilizce)","programRaw":"Uluslararası İlişkiler (İngilizce) (4 Yıllık)","scoreType":"EA","years":[{"year":2025,"quota":"45","placed":"47","rank":"677.287","rankNumeric":677287,"score":"261,73786","scoreNumeric":261.73786},{"year":2024,"quota":"55","placed":"57","rank":"733.195","rankNumeric":733195,"score":"258,03212","scoreNumeric":258.03212},{"year":2023,"quota":"50","placed":"53","rank":"677.825","rankNumeric":677825,"score":"268,84952","scoreNumeric":268.84952},{"year":2022,"quota":"50","placed":"52","rank":"677.254","rankNumeric":677254,"score":"267,79934","scoreNumeric":267.79934}]},{"university":"RECEP TAYYİP ERDOĞAN ÜNİVERSİTESİ","faculty":"İktisadi ve İdari Bilimler Fakültesi","city":"RİZE","sector":"Devlet","program":"Uluslararası İlişkiler","programRaw":"Uluslararası İlişkiler (4 Yıllık)","scoreType":"EA","years":[{"year":2025,"quota":"40","placed":"42","rank":"688.402","rankNumeric":688402,"score":"260,68553","scoreNumeric":260.68553},{"year":2024,"quota":"65","placed":"68","rank":"894.814","rankNumeric":894814,"score":"245,11508","scoreNumeric":245.11508},{"year":2023,"quota":"60","placed":"64","rank":"957.910","rankNumeric":957910,"score":"244,12439","scoreNumeric":244.12439},{"year":2022,"quota":"60","placed":"62","rank":"999.171","rankNumeric":999171,"score":"240,53176","scoreNumeric":240.53176}]},{"university":"GİRESUN ÜNİVERSİTESİ","faculty":"İktisadi ve İdari Bilimler Fakültesi","city":"GİRESUN","sector":"Devlet","program":"Uluslararası İlişkiler","programRaw":"Uluslararası İlişkiler (4 Yıllık)","scoreType":"EA","years":[{"year":2025,"quota":"45","placed":"49","rank":"692.153","rankNumeric":692153,"score":"260,32426","scoreNumeric":260.32426},{"year":2024,"quota":"60","placed":"64","rank":"918.207","rankNumeric":918207,"score":"243,36261","scoreNumeric":243.36261},{"year":2023,"quota":"50","placed":"53","rank":"1.007.867","rankNumeric":1007867,"score":"240,23950","scoreNumeric":240.2395},{"year":2022,"quota":"50","placed":"52","rank":"1.005.265","rankNumeric":1005265,"score":"240,07238","scoreNumeric":240.07238}]},{"university":"HİTİT ÜNİVERSİTESİ","faculty":"İktisadi ve İdari Bilimler Fakültesi","city":"ÇORUM","sector":"Devlet","program":"Uluslararası İlişkiler (İngilizce)","programRaw":"Uluslararası İlişkiler (İngilizce) (4 Yıllık)","scoreType":"EA","years":[{"year":2025,"quota":"40","placed":"42","rank":"694.379","rankNumeric":694379,"score":"260,11467","scoreNumeric":260.11467},{"year":2024,"quota":"60","placed":"62","rank":"899.019","rankNumeric":899019,"score":"244,80110","scoreNumeric":244.8011},{"year":2023,"quota":"50","placed":"52","rank":"981.802","rankNumeric":981802,"score":"242,25426","scoreNumeric":242.25426},{"year":2022,"quota":"50","placed":"52","rank":"981.024","rankNumeric":981024,"score":"241,90542","scoreNumeric":241.90542}]},{"university":"AKSARAY ÜNİVERSİTESİ","faculty":"İktisadi ve İdari Bilimler Fakültesi","city":"AKSARAY","sector":"Devlet","program":"Uluslararası İlişkiler","programRaw":"Uluslararası İlişkiler (4 Yıllık)","scoreType":"EA","years":[{"year":2025,"quota":"30","placed":"32","rank":"711.693","rankNumeric":711693,"score":"258,50207","scoreNumeric":258.50207},{"year":2024,"quota":"50","placed":"53","rank":"876.953","rankNumeric":876953,"score":"246,46908","scoreNumeric":246.46908},{"year":2023,"quota":"40","placed":"42","rank":"930.128","rankNumeric":930128,"score":"246,37175","scoreNumeric":246.37175},{"year":2022,"quota":"40","placed":"41","rank":"882.090","rankNumeric":882090,"score":"249,64480","scoreNumeric":249.6448}]},{"university":"ULUSLARARASI KIBRIS ÜNİVERSİTESİ","faculty":"İktisadi ve İdari Bilimler Fakültesi (KKTC-LEFKOŞA) (KKTC )","city":null,"sector":null,"program":"Uluslararası İlişkiler (İngilizce) (Burslu)","programRaw":"Uluslararası İlişkiler (İngilizce) (Burslu) (4 Yıllık)","scoreType":"EA","years":[{"year":2025,"quota":"7","placed":"7","rank":"718.584","rankNumeric":718584,"score":"257,8723","scoreNumeric":257.8723},{"year":2024,"quota":"3","placed":"3","rank":"712.069","rankNumeric":712069,"score":"259,85259","scoreNumeric":259.85259},{"year":2023,"quota":"3","placed":"3","rank":"788.520","rankNumeric":788520,"score":"258,41377","scoreNumeric":258.41377},{"year":2022,"quota":"3","placed":"3","rank":"764.564","rankNumeric":764564,"score":"259,62119","scoreNumeric":259.62119}]},{"university":"VAN YÜZÜNCÜ YIL ÜNİVERSİTESİ","faculty":"İktisadi ve İdari Bilimler Fakültesi","city":"VAN","sector":"Devlet","program":"Uluslararası İlişkiler","programRaw":"Uluslararası İlişkiler (4 Yıllık)","scoreType":"EA","years":[{"year":2025,"quota":"40","placed":"42","rank":"751.148","rankNumeric":751148,"score":"254,9339","scoreNumeric":254.9339},{"year":2024,"quota":"55","placed":"59","rank":"938.018","rankNumeric":938018,"score":"241,88762","scoreNumeric":241.88762},{"year":2023,"quota":"50","placed":"54","rank":"1.037.433","rankNumeric":1037433,"score":"237,95563","scoreNumeric":237.95563},{"year":2022,"quota":"50","placed":"52","rank":"972.173","rankNumeric":972173,"score":"242,56308","scoreNumeric":242.56308}]},{"university":"HATAY MUSTAFA KEMAL ÜNİVERSİTESİ","faculty":"İktisadi ve İdari Bilimler Fakültesi","city":"HATAY","sector":"Devlet","program":"Uluslararası İlişkiler","programRaw":"Uluslararası İlişkiler (4 Yıllık)","scoreType":"EA","years":[{"year":2025,"quota":"30","placed":"34","rank":"754.706","rankNumeric":754706,"score":"254,61191","scoreNumeric":254.61191},{"year":2024,"quota":"35","placed":"46","rank":"989.833","rankNumeric":989833,"score":"238,11440","scoreNumeric":238.1144},{"year":2023,"quota":"30","placed":"40","rank":"1.000.639","rankNumeric":1000639,"score":"240,78847","scoreNumeric":240.78847},{"year":2022,"quota":"40","placed":"41","rank":"796.223","rankNumeric":796223,"score":"256,81675","scoreNumeric":256.81675}]},{"university":"ANADOLU ÜNİVERSİTESİ","faculty":"Açıköğretim Fakültesi","city":"ESKİŞEHİR","sector":"Devlet","program":"Uluslararası İlişkiler (İngilizce) (Açıköğretim)","programRaw":"Uluslararası İlişkiler (İngilizce) (Açıköğretim) (4 Yıllık)","scoreType":"EA","years":[{"year":2025,"quota":"180","placed":"190","rank":"758.156","rankNumeric":758156,"score":"254,30545","scoreNumeric":254.30545},{"year":2024,"quota":"150","placed":"158","rank":"923.565","rankNumeric":923565,"score":"242,965","scoreNumeric":242.965},{"year":2023,"quota":"150","placed":"158","rank":"851.929","rankNumeric":851929,"score":"252,84779","scoreNumeric":252.84779},{"year":2022,"quota":"150","placed":"154","rank":"992.653","rankNumeric":992653,"score":"241,02429","scoreNumeric":241.02429}]},{"university":"KASTAMONU ÜNİVERSİTESİ","faculty":"İktisadi ve İdari Bilimler Fakültesi","city":"KASTAMONU","sector":"Devlet","program":"Uluslararası İlişkiler","programRaw":"Uluslararası İlişkiler (4 Yıllık)","scoreType":"EA","years":[{"year":2025,"quota":"45","placed":"47","rank":"769.132","rankNumeric":769132,"score":"253,31965","scoreNumeric":253.31965},{"year":2024,"quota":"60","placed":"62","rank":"1.060.382","rankNumeric":1060382,"score":"233,09899","scoreNumeric":233.09899},{"year":2023,"quota":"50","placed":"53","rank":"1.129.147","rankNumeric":1129147,"score":"231,14338","scoreNumeric":231.14338},{"year":2022,"quota":"50","placed":"52","rank":"1.180.905","rankNumeric":1180905,"score":"227,47417","scoreNumeric":227.47417}]},{"university":"YAKIN DOĞU ÜNİVERSİTESİ","faculty":"İktisadi ve İdari Bilimler Fakültesi (KKTC-LEFKOŞA) (KKTC )","city":null,"sector":null,"program":"Uluslararası İlişkiler (İngilizce) (Burslu)","programRaw":"Uluslararası İlişkiler (İngilizce) (Burslu) (4 Yıllık)","scoreType":"EA","years":[{"year":2025,"quota":"15","placed":"15","rank":"814.154","rankNumeric":814154,"score":"249,3605","scoreNumeric":249.3605},{"year":2024,"quota":"10","placed":"10","rank":"882.896","rankNumeric":882896,"score":"246,01809","scoreNumeric":246.01809},{"year":2023,"quota":"10","placed":"10","rank":"1.099.988","rankNumeric":1099988,"score":"233,27161","scoreNumeric":233.27161},{"year":2022,"quota":"10","placed":"10","rank":"1.496.591","rankNumeric":1496591,"score":"204,86649","scoreNumeric":204.86649}]},{"university":"ÇANKIRI KARATEKİN ÜNİVERSİTESİ","faculty":"İktisadi ve İdari Bilimler Fakültesi","city":"ÇANKIRI","sector":"Devlet","program":"Uluslararası İlişkiler","programRaw":"Uluslararası İlişkiler (4 Yıllık)","scoreType":"EA","years":[{"year":2025,"quota":"40","placed":"41","rank":"898.762","rankNumeric":898762,"score":"242,13445","scoreNumeric":242.13445},{"year":2024,"quota":"55","placed":"58","rank":"1.092.088","rankNumeric":1092088,"score":"230,85102","scoreNumeric":230.85102},{"year":2023,"quota":"45","placed":"48","rank":"1.196.075","rankNumeric":1196075,"score":"226,34042","scoreNumeric":226.34042},{"year":2022,"quota":"45","placed":"47","rank":"1.221.115","rankNumeric":1221115,"score":"224,67981","scoreNumeric":224.67981}]},{"university":"KARABÜK ÜNİVERSİTESİ","faculty":"İktisadi ve İdari Bilimler Fakültesi","city":"KARABÜK","sector":"Devlet","program":"Uluslararası İlişkiler","programRaw":"Uluslararası İlişkiler (4 Yıllık)","scoreType":"EA","years":[{"year":2025,"quota":"50","placed":"54","rank":"904.803","rankNumeric":904803,"score":"241,62657","scoreNumeric":241.62657},{"year":2024,"quota":"70","placed":"72","rank":"1.206.280","rankNumeric":1206280,"score":"222,84019","scoreNumeric":222.84019},{"year":2023,"quota":"60","placed":"62","rank":"973.607","rankNumeric":973607,"score":"242,89019","scoreNumeric":242.89019},{"year":2022,"quota":"60","placed":"62","rank":"982.007","rankNumeric":982007,"score":"241,83165","scoreNumeric":241.83165}]},{"university":"OSMANİYE KORKUT ATA ÜNİVERSİTESİ","faculty":"İktisadi ve İdari Bilimler Fakültesi","city":"OSMANİYE","sector":"Devlet","program":"Uluslararası İlişkiler","programRaw":"Uluslararası İlişkiler (4 Yıllık)","scoreType":"EA","years":[{"year":2025,"quota":"35","placed":"41","rank":"914.113","rankNumeric":914113,"score":"240,8237","scoreNumeric":240.8237},{"year":2024,"quota":"50","placed":"67","rank":"1.158.650","rankNumeric":1158650,"score":"226,19546","scoreNumeric":226.19546},{"year":2023,"quota":"50","placed":"67","rank":"1.164.980","rankNumeric":1164980,"score":"228,56821","scoreNumeric":228.56821},{"year":2022,"quota":"40","placed":"41","rank":"1.115.913","rankNumeric":1115913,"score":"232,04272","scoreNumeric":232.04272}]},{"university":"KIRŞEHİR AHİ EVRAN ÜNİVERSİTESİ","faculty":"İktisadi ve İdari Bilimler Fakültesi","city":"KIRŞEHİR","sector":"Devlet","program":"Uluslararası İlişkiler","programRaw":"Uluslararası İlişkiler (4 Yıllık)","scoreType":"EA","years":[{"year":2025,"quota":"45","placed":"48","rank":"916.637","rankNumeric":916637,"score":"240,60785","scoreNumeric":240.60785},{"year":2024,"quota":"60","placed":"64","rank":"1.119.897","rankNumeric":1119897,"score":"228,91346","scoreNumeric":228.91346},{"year":2023,"quota":"50","placed":"54","rank":"1.214.697","rankNumeric":1214697,"score":"225,00987","scoreNumeric":225.00987},{"year":2022,"quota":"40","placed":"41","rank":"1.223.076","rankNumeric":1223076,"score":"224,54146","scoreNumeric":224.54146}]},{"university":"GİRNE ÜNİVERSİTESİ","faculty":"İktisadi ve İdari Bilimler Fakültesi (KKTC-GİRNE) (KKTC )","city":null,"sector":null,"program":"Uluslararası İlişkiler (İngilizce) (Burslu)","programRaw":"Uluslararası İlişkiler (İngilizce) (Burslu) (4 Yıllık)","scoreType":"EA","years":[{"year":2025,"quota":"5","placed":"5","rank":"923.309","rankNumeric":923309,"score":"240,04177","scoreNumeric":240.04177},{"year":2024,"quota":"5","placed":"5","rank":"1.092.638","rankNumeric":1092638,"score":"230,81367","scoreNumeric":230.81367},{"year":2023,"quota":"10","placed":"10","rank":"1.133.363","rankNumeric":1133363,"score":"230,83562","scoreNumeric":230.83562},{"year":2022,"quota":"3","placed":"3","rank":"1.091.436","rankNumeric":1091436,"score":"233,79113","scoreNumeric":233.79113}]},{"university":"GİRNE AMERİKAN ÜNİVERSİTESİ","faculty":"Siyasal Bilimler Fakültesi (KKTC-GİRNE) (KKTC )","city":null,"sector":null,"program":"Uluslararası İlişkiler (İngilizce) (Burslu)","programRaw":"Uluslararası İlişkiler (İngilizce) (Burslu) (4 Yıllık)","scoreType":"EA","years":[{"year":2025,"quota":"10","placed":"10","rank":"927.547","rankNumeric":927547,"score":"239,68973","scoreNumeric":239.68973},{"year":2024,"quota":"8","placed":"8","rank":"899.320","rankNumeric":899320,"score":"244,77835","scoreNumeric":244.77835},{"year":2023,"quota":"6","placed":"6","rank":"935.357","rankNumeric":935357,"score":"245,94945","scoreNumeric":245.94945},{"year":2022,"quota":"10","placed":"10","rank":"1.069.416","rankNumeric":1069416,"score":"235,38043","scoreNumeric":235.38043}]},{"university":"KIRGIZİSTAN-TÜRKİYE MANAS ÜNİVERSİTESİ","faculty":"İktisadi ve İdari Bilimler Fakültesi (BİŞKEK-KIRGIZİSTAN) (Yurt Dışı )","city":null,"sector":null,"program":"Uluslararası İlişkiler","programRaw":"Uluslararası İlişkiler (4 Yıllık)","scoreType":"EA","years":[{"year":2025,"quota":"6","placed":"6","rank":"943.900","rankNumeric":943900,"score":"238,31995","scoreNumeric":238.31995},{"year":2024,"quota":"6","placed":"6","rank":"816.657","rankNumeric":816657,"score":"251,17271","scoreNumeric":251.17271},{"year":2023,"quota":"5","placed":"5","rank":"868.691","rankNumeric":868691,"score":"251,42013","scoreNumeric":251.42013},{"year":2022,"quota":"5","placed":"5","rank":"825.047","rankNumeric":825047,"score":"254,34777","scoreNumeric":254.34777}]},{"university":"LEFKE AVRUPA ÜNİVERSİTESİ","faculty":"İktisadi ve İdari Bilimler Fakültesi (KKTC-LEFKE) (KKTC )","city":null,"sector":null,"program":"Uluslararası İlişkiler (İngilizce) (Burslu)","programRaw":"Uluslararası İlişkiler (İngilizce) (Burslu) (4 Yıllık)","scoreType":"EA","years":[{"year":2025,"quota":"20","placed":"20","rank":"984.570","rankNumeric":984570,"score":"234,89019","scoreNumeric":234.89019},{"year":2024,"quota":"20","placed":"20","rank":"1.113.206","rankNumeric":1113206,"score":"229,37923","scoreNumeric":229.37923},{"year":2023,"quota":"15","placed":"15","rank":"890.532","rankNumeric":890532,"score":"249,60582","scoreNumeric":249.60582},{"year":2022,"quota":"10","placed":"10","rank":"932.071","rankNumeric":932071,"score":"245,64760","scoreNumeric":245.6476}]},{"university":"GÜMÜŞHANE ÜNİVERSİTESİ","faculty":"Gümüşhane İktisadi ve İdari Bilimler Fakültesi","city":"GÜMÜŞHANE","sector":"Devlet","program":"Uluslararası İlişkiler","programRaw":"Uluslararası İlişkiler (4 Yıllık)","scoreType":"EA","years":[{"year":2025,"quota":"30","placed":"31","rank":"984.778","rankNumeric":984778,"score":"234,87019","scoreNumeric":234.87019},{"year":2024,"quota":"40","placed":"42","rank":"1.215.836","rankNumeric":1215836,"score":"222,16970","scoreNumeric":222.1697},{"year":2023,"quota":"30","placed":"32","rank":"1.210.749","rankNumeric":1210749,"score":"225,29906","scoreNumeric":225.29906},{"year":2022,"quota":"30","placed":"31","rank":"1.315.933","rankNumeric":1315933,"score":"218,07915","scoreNumeric":218.07915}]},{"university":"HOCA AHMET YESEVİ ULUSLARARASI TÜRK-KAZAK ÜNİVERSİTESİ","faculty":"İktisadi ve İdari Bilimler Fakültesi (TÜRKİSTAN-KAZAKİSTAN) (Yurt Dışı )","city":null,"sector":null,"program":"Uluslararası İlişkiler","programRaw":"Uluslararası İlişkiler (4 Yıllık)","scoreType":"EA","years":[{"year":2025,"quota":"5","placed":"5","rank":"1.006.928","rankNumeric":1006928,"score":"232,98967","scoreNumeric":232.98967},{"year":2024,"quota":"5","placed":"5","rank":"651.543","rankNumeric":651543,"score":"265,24107","scoreNumeric":265.24107},{"year":2023,"quota":"5","placed":"5","rank":"719.560","rankNumeric":719560,"score":"264,80024","scoreNumeric":264.80024},{"year":2022,"quota":"5","placed":"5","rank":"702.748","rankNumeric":702748,"score":"265,34416","scoreNumeric":265.34416}]},{"university":"BATMAN ÜNİVERSİTESİ","faculty":"İktisadi ve İdari Bilimler Fakültesi","city":"BATMAN","sector":"Devlet","program":"Uluslararası İlişkiler","programRaw":"Uluslararası İlişkiler (4 Yıllık)","scoreType":"EA","years":[{"year":2025,"quota":"30","placed":"32","rank":"1.034.653","rankNumeric":1034653,"score":"230,64962","scoreNumeric":230.64962},{"year":2024,"quota":"40","placed":"42","rank":"1.252.575","rankNumeric":1252575,"score":"219,59298","scoreNumeric":219.59298},{"year":2023,"quota":"30","placed":"32","rank":"1.177.480","rankNumeric":1177480,"score":"227,67942","scoreNumeric":227.67942},{"year":2022,"quota":"30","placed":"31","rank":"1.235.419","rankNumeric":1235419,"score":"223,69357","scoreNumeric":223.69357}]},{"university":"YOZGAT BOZOK ÜNİVERSİTESİ","faculty":"İktisadi ve İdari Bilimler Fakültesi","city":"YOZGAT","sector":"Devlet","program":"Uluslararası İlişkiler","programRaw":"Uluslararası İlişkiler (4 Yıllık)","scoreType":"EA","years":[{"year":2025,"quota":"40","placed":"41","rank":"1.065.861","rankNumeric":1065861,"score":"227,99296","scoreNumeric":227.99296},{"year":2024,"quota":"50","placed":"54","rank":"1.238.482","rankNumeric":1238482,"score":"220,58763","scoreNumeric":220.58763},{"year":2023,"quota":"30","placed":"31","rank":"1.236.620","rankNumeric":1236620,"score":"223,45234","scoreNumeric":223.45234},{"year":2022,"quota":"30","placed":"31","rank":"1.261.073","rankNumeric":1261073,"score":"221,90477","scoreNumeric":221.90477}]},{"university":"BİTLİS EREN ÜNİVERSİTESİ","faculty":"İktisadi ve İdari Bilimler Fakültesi","city":"BİTLİS","sector":"Devlet","program":"Uluslararası İlişkiler","programRaw":"Uluslararası İlişkiler (4 Yıllık)","scoreType":"EA","years":[{"year":2025,"quota":"40","placed":"42","rank":"1.202.259","rankNumeric":1202259,"score":"215,82283","scoreNumeric":215.82283},{"year":2024,"quota":"50","placed":"54","rank":"1.363.254","rankNumeric":1363254,"score":"211,66394","scoreNumeric":211.66394},{"year":2023,"quota":"40","placed":"42","rank":"1.345.961","rankNumeric":1345961,"score":"215,81683","scoreNumeric":215.81683},{"year":2022,"quota":"30","placed":"31","rank":"1.379.308","rankNumeric":1379308,"score":"213,60823","scoreNumeric":213.60823}]},{"university":"ARDAHAN ÜNİVERSİTESİ","faculty":"İktisadi ve İdari Bilimler Fakültesi","city":"ARDAHAN","sector":"Devlet","program":"Uluslararası İlişkiler","programRaw":"Uluslararası İlişkiler (4 Yıllık)","scoreType":"EA","years":[{"year":2025,"quota":"30","placed":"32","rank":"1.238.937","rankNumeric":1238937,"score":"212,33654","scoreNumeric":212.33654},{"year":2024,"quota":"30","placed":"32","rank":"1.453.056","rankNumeric":1453056,"score":"204,80928","scoreNumeric":204.80928},{"year":2023,"quota":"—","placed":"—","rank":"—","rankNumeric":null,"score":"—","scoreNumeric":null},{"year":2022,"quota":"—","placed":"—","rank":"—","rankNumeric":null,"score":"—","scoreNumeric":null}]},{"university":"YAŞAR ÜNİVERSİTESİ","faculty":"İnsan ve Toplum Bilimleri Fakültesi","city":"İZMİR","sector":"Vakıf","program":"Uluslararası İlişkiler (İngilizce) (Ücretli)","programRaw":"Uluslararası İlişkiler (İngilizce) (Ücretli) (4 Yıllık)","scoreType":"EA","years":[{"year":2025,"quota":"10","placed":"10","rank":"1.340.738","rankNumeric":1340738,"score":"201,57375","scoreNumeric":201.57375},{"year":2024,"quota":"15","placed":"15","rank":"1.091.831","rankNumeric":1091831,"score":"230,86969","scoreNumeric":230.86969},{"year":2023,"quota":"7","placed":"7","rank":"738.179","rankNumeric":738179,"score":"263,04424","scoreNumeric":263.04424},{"year":2022,"quota":"4","placed":"4","rank":"715.121","rankNumeric":715121,"score":"264,17182","scoreNumeric":264.17182}]},{"university":"KIBRIS AMERİKAN ÜNİVERSİTESİ","faculty":"Siyasal Bilgiler Fakültesi (KKTC-LEFKOŞA) (KKTC )","city":null,"sector":null,"program":"Uluslararası İlişkiler (İngilizce) (Burslu)","programRaw":"Uluslararası İlişkiler (İngilizce) (Burslu) (4 Yıllık)","scoreType":"EA","years":[{"year":2025,"quota":"10","placed":"10","rank":"1.417.938","rankNumeric":1417938,"score":"191,26066","scoreNumeric":191.26066},{"year":2024,"quota":"10","placed":"10","rank":"1.519.061","rankNumeric":1519061,"score":"199,28706","scoreNumeric":199.28706},{"year":2023,"quota":"10","placed":"10","rank":"1.812.802","rankNumeric":1812802,"score":"176,94272","scoreNumeric":176.94272},{"year":2022,"quota":"10","placed":"1","rank":"Dolmadı","rankNumeric":null,"score":"Dolmadı","scoreNumeric":null}]},{"university":"ALTINBAŞ ÜNİVERSİTESİ","faculty":"İktisadi, İdari ve Sosyal Bilimler Fakültesi","city":"İSTANBUL","sector":"Vakıf","program":"Uluslararası İlişkiler (İngilizce) (%50 İndirimli)","programRaw":"Uluslararası İlişkiler (İngilizce) (%50 İndirimli) (4 Yıllık)","scoreType":"EA","years":[{"year":2025,"quota":"21","placed":"1","rank":"Dolmadı","rankNumeric":null,"score":"Dolmadı","scoreNumeric":null},{"year":2024,"quota":"—","placed":"—","rank":"…","rankNumeric":null,"score":"—","scoreNumeric":null},{"year":2023,"quota":"—","placed":"—","rank":"—","rankNumeric":null,"score":"—","scoreNumeric":null},{"year":2022,"quota":"—","placed":"—","rank":"—","rankNumeric":null,"score":"—","scoreNumeric":null}]},{"university":"ATILIM ÜNİVERSİTESİ","faculty":"İşletme Fakültesi","city":"ANKARA","sector":"Vakıf","program":"Uluslararası İlişkiler (İngilizce) (%50 İndirimli)","programRaw":"Uluslararası İlişkiler (İngilizce) (%50 İndirimli) (4 Yıllık)","scoreType":"EA","years":[{"year":2025,"quota":"31","placed":"19","rank":"Dolmadı","rankNumeric":null,"score":"Dolmadı","scoreNumeric":null},{"year":2024,"quota":"31","placed":"31","rank":"731.911","rankNumeric":731911,"score":"258,14360","scoreNumeric":258.1436},{"year":2023,"quota":"31","placed":"31","rank":"859.724","rankNumeric":859724,"score":"252,19503","scoreNumeric":252.19503},{"year":2022,"quota":"25","placed":"25","rank":"545.225","rankNumeric":545225,"score":"281,98173","scoreNumeric":281.98173}]},{"university":"ÇAĞ ÜNİVERSİTESİ","faculty":"İktisadi ve İdari Bilimler Fakültesi","city":"MERSİN","sector":"Vakıf","program":"Uluslararası İlişkiler (İngilizce) (%50 İndirimli)","programRaw":"Uluslararası İlişkiler (İngilizce) (%50 İndirimli) (4 Yıllık)","scoreType":"EA","years":[{"year":2025,"quota":"38","placed":"35","rank":"Dolmadı","rankNumeric":null,"score":"Dolmadı","scoreNumeric":null},{"year":2024,"quota":"34","placed":"23","rank":"Dolmadı","rankNumeric":null,"score":"Dolmadı","scoreNumeric":null},{"year":2023,"quota":"33","placed":"33","rank":"935.949","rankNumeric":935949,"score":"245,90096","scoreNumeric":245.90096},{"year":2022,"quota":"24","placed":"24","rank":"927.054","rankNumeric":927054,"score":"246,04336","scoreNumeric":246.04336}]},{"university":"DOĞU AKDENİZ ÜNİVERSİTESİ","faculty":"İşletme ve Ekonomi Fakültesi (KKTC-GAZİMAĞUSA) (KKTC )","city":null,"sector":null,"program":"Uluslararası İlişkiler (İngilizce) (%50 İndirimli)","programRaw":"Uluslararası İlişkiler (İngilizce) (%50 İndirimli) (4 Yıllık)","scoreType":"EA","years":[{"year":2025,"quota":"11","placed":"3","rank":"Dolmadı","rankNumeric":null,"score":"Dolmadı","scoreNumeric":null},{"year":2024,"quota":"11","placed":"6","rank":"Dolmadı","rankNumeric":null,"score":"Dolmadı","scoreNumeric":null},{"year":2023,"quota":"3","placed":"3","rank":"1.125.741","rankNumeric":1125741,"score":"231,39353","scoreNumeric":231.39353},{"year":2022,"quota":"—","placed":"—","rank":"—","rankNumeric":null,"score":"—","scoreNumeric":null}]},{"university":"DOĞU AKDENİZ ÜNİVERSİTESİ","faculty":"İşletme ve Ekonomi Fakültesi (KKTC-GAZİMAĞUSA) (KKTC )","city":null,"sector":null,"program":"Uluslararası İlişkiler (İngilizce) (Ücretli)","programRaw":"Uluslararası İlişkiler (İngilizce) (Ücretli) (4 Yıllık)","scoreType":"EA","years":[{"year":2025,"quota":"15","placed":"5","rank":"Dolmadı","rankNumeric":null,"score":"Dolmadı","scoreNumeric":null},{"year":2024,"quota":"15","placed":"7","rank":"Dolmadı","rankNumeric":null,"score":"Dolmadı","scoreNumeric":null},{"year":2023,"quota":"14","placed":"8","rank":"Dolmadı","rankNumeric":null,"score":"Dolmadı","scoreNumeric":null},{"year":2022,"quota":"5","placed":"5","rank":"721.104","rankNumeric":721104,"score":"263,60870","scoreNumeric":263.6087}]},{"university":"DOĞUŞ ÜNİVERSİTESİ","faculty":"İktisadi ve İdari Bilimler Fakültesi","city":"İSTANBUL","sector":"Vakıf","program":"Uluslararası İlişkiler (İngilizce) (%50 İndirimli)","programRaw":"Uluslararası İlişkiler (İngilizce) (%50 İndirimli) (4 Yıllık)","scoreType":"EA","years":[{"year":2025,"quota":"40","placed":"15","rank":"Dolmadı","rankNumeric":null,"score":"Dolmadı","scoreNumeric":null},{"year":2024,"quota":"42","placed":"42","rank":"1.589.996","rankNumeric":1589996,"score":"192,32710","scoreNumeric":192.3271},{"year":2023,"quota":"34","placed":"34","rank":"1.641.104","rankNumeric":1641104,"score":"194,61333","scoreNumeric":194.61333},{"year":2022,"quota":"25","placed":"25","rank":"845.961","rankNumeric":845961,"score":"252,59722","scoreNumeric":252.59722}]},{"university":"IŞIK ÜNİVERSİTESİ","faculty":"İktisadi, İdari ve Sosyal Bilimler Fakültesi","city":"İSTANBUL","sector":"Vakıf","program":"Uluslararası İlişkiler (İngilizce) (%50 İndirimli)","programRaw":"Uluslararası İlişkiler (İngilizce) (%50 İndirimli) (4 Yıllık)","scoreType":"EA","years":[{"year":2025,"quota":"19","placed":"4","rank":"Dolmadı","rankNumeric":null,"score":"Dolmadı","scoreNumeric":null},{"year":2024,"quota":"20","placed":"20","rank":"1.528.451","rankNumeric":1528451,"score":"198,44150","scoreNumeric":198.4415},{"year":2023,"quota":"18","placed":"18","rank":"1.842.416","rankNumeric":1842416,"score":"169,97635","scoreNumeric":169.97635},{"year":2022,"quota":"15","placed":"15","rank":"705.444","rankNumeric":705444,"score":"265,08396","scoreNumeric":265.08396}]},{"university":"İSTANBUL AREL ÜNİVERSİTESİ","faculty":"İktisadi ve İdari Bilimler Fakültesi","city":"İSTANBUL","sector":"Vakıf","program":"Uluslararası İlişkiler (İngilizce) (%50 İndirimli)","programRaw":"Uluslararası İlişkiler (İngilizce) (%50 İndirimli) (4 Yıllık)","scoreType":"EA","years":[{"year":2025,"quota":"30","placed":"5","rank":"Dolmadı","rankNumeric":null,"score":"Dolmadı","scoreNumeric":null},{"year":2024,"quota":"34","placed":"3","rank":"Dolmadı","rankNumeric":null,"score":"Dolmadı","scoreNumeric":null},{"year":2023,"quota":"24","placed":"20","rank":"Dolmadı","rankNumeric":null,"score":"Dolmadı","scoreNumeric":null},{"year":2022,"quota":"13","placed":"13","rank":"961.894","rankNumeric":961894,"score":"243,34016","scoreNumeric":243.34016}]},{"university":"İSTANBUL AREL ÜNİVERSİTESİ","faculty":"İktisadi ve İdari Bilimler Fakültesi","city":"İSTANBUL","sector":"Vakıf","program":"Uluslararası İlişkiler (%50 İndirimli)","programRaw":"Uluslararası İlişkiler (%50 İndirimli) (4 Yıllık)","scoreType":"EA","years":[{"year":2025,"quota":"25","placed":"9","rank":"Dolmadı","rankNumeric":null,"score":"Dolmadı","scoreNumeric":null},{"year":2024,"quota":"23","placed":"9","rank":"Dolmadı","rankNumeric":null,"score":"Dolmadı","scoreNumeric":null},{"year":2023,"quota":"—","placed":"—","rank":"—","rankNumeric":null,"score":"—","scoreNumeric":null},{"year":2022,"quota":"—","placed":"—","rank":"—","rankNumeric":null,"score":"—","scoreNumeric":null}]},{"university":"İSTANBUL BEYKENT ÜNİVERSİTESİ","faculty":"İktisadi ve İdari Bilimler Fakültesi","city":"İSTANBUL","sector":"Vakıf","program":"Uluslararası İlişkiler (İngilizce) (%50 İndirimli)","programRaw":"Uluslararası İlişkiler (İngilizce) (%50 İndirimli) (4 Yıllık)","scoreType":"EA","years":[{"year":2025,"quota":"37","placed":"13","rank":"Dolmadı","rankNumeric":null,"score":"Dolmadı","scoreNumeric":null},{"year":2024,"quota":"42","placed":"31","rank":"Dolmadı","rankNumeric":null,"score":"Dolmadı","scoreNumeric":null},{"year":2023,"quota":"34","placed":"34","rank":"1.394.115","rankNumeric":1394115,"score":"212,46684","scoreNumeric":212.46684},{"year":2022,"quota":"25","placed":"25","rank":"811.145","rankNumeric":811145,"score":"255,52360","scoreNumeric":255.5236}]},{"university":"İSTANBUL BİLGİ ÜNİVERSİTESİ","faculty":"Sosyal ve Beşeri Bilimler Fakültesi","city":"İSTANBUL","sector":"Vakıf","program":"Uluslararası İlişkiler (İngilizce) (%50 İndirimli)","programRaw":"Uluslararası İlişkiler (İngilizce) (%50 İndirimli) (4 Yıllık)","scoreType":"EA","years":[{"year":2025,"quota":"93","placed":"68","rank":"Dolmadı","rankNumeric":null,"score":"Dolmadı","scoreNumeric":null},{"year":2024,"quota":"93","placed":"93","rank":"919.158","rankNumeric":919158,"score":"243,29056","scoreNumeric":243.29056},{"year":2023,"quota":"90","placed":"90","rank":"906.390","rankNumeric":906390,"score":"248,28723","scoreNumeric":248.28723},{"year":2022,"quota":"82","placed":"82","rank":"566.781","rankNumeric":566781,"score":"279,48034","scoreNumeric":279.48034}]},{"university":"İSTANBUL KENT ÜNİVERSİTESİ","faculty":"İktisadi, İdari ve Sosyal Bilimler Fakültesi","city":"İSTANBUL","sector":"Vakıf","program":"Uluslararası İlişkiler (İngilizce) (%50 İndirimli)","programRaw":"Uluslararası İlişkiler (İngilizce) (%50 İndirimli) (4 Yıllık)","scoreType":"EA","years":[{"year":2025,"quota":"21","placed":"8","rank":"Dolmadı","rankNumeric":null,"score":"Dolmadı","scoreNumeric":null},{"year":2024,"quota":"24","placed":"12","rank":"Dolmadı","rankNumeric":null,"score":"Dolmadı","scoreNumeric":null},{"year":2023,"quota":"—","placed":"—","rank":"—","rankNumeric":null,"score":"—","scoreNumeric":null},{"year":2022,"quota":"—","placed":"—","rank":"—","rankNumeric":null,"score":"—","scoreNumeric":null}]},{"university":"İSTANBUL NİŞANTAŞI ÜNİVERSİTESİ","faculty":"İktisadi, İdari ve Sosyal Bilimler Fakültesi","city":"İSTANBUL","sector":"Vakıf","program":"Uluslararası İlişkiler (%50 İndirimli)","programRaw":"Uluslararası İlişkiler (%50 İndirimli) (4 Yıllık)","scoreType":"EA","years":[{"year":2025,"quota":"58","placed":"36","rank":"Dolmadı","rankNumeric":null,"score":"Dolmadı","scoreNumeric":null},{"year":2024,"quota":"24","placed":"24","rank":"1.122.032","rankNumeric":1122032,"score":"228,75888","scoreNumeric":228.75888},{"year":2023,"quota":"—","placed":"—","rank":"—","rankNumeric":null,"score":"—","scoreNumeric":null},{"year":2022,"quota":"—","placed":"—","rank":"—","rankNumeric":null,"score":"—","scoreNumeric":null}]},{"university":"İSTANBUL NİŞANTAŞI ÜNİVERSİTESİ","faculty":"İktisadi, İdari ve Sosyal Bilimler Fakültesi","city":"İSTANBUL","sector":"Vakıf","program":"Uluslararası İlişkiler (İngilizce) (%50 İndirimli)","programRaw":"Uluslararası İlişkiler (İngilizce) (%50 İndirimli) (4 Yıllık)","scoreType":"EA","years":[{"year":2025,"quota":"58","placed":"28","rank":"Dolmadı","rankNumeric":null,"score":"Dolmadı","scoreNumeric":null},{"year":2024,"quota":"50","placed":"50","rank":"1.123.492","rankNumeric":1123492,"score":"228,65538","scoreNumeric":228.65538},{"year":2023,"quota":"41","placed":"41","rank":"782.620","rankNumeric":782620,"score":"258,95625","scoreNumeric":258.95625},{"year":2022,"quota":"33","placed":"33","rank":"701.860","rankNumeric":701860,"score":"265,42978","scoreNumeric":265.42978}]},{"university":"İSTANBUL RUMELİ ÜNİVERSİTESİ","faculty":"İktisadi, İdari ve Sosyal Bilimler Fakültesi","city":"İSTANBUL","sector":"Vakıf","program":"Uluslararası İlişkiler (%50 İndirimli)","programRaw":"Uluslararası İlişkiler (%50 İndirimli) (4 Yıllık)","scoreType":"EA","years":[{"year":2025,"quota":"48","placed":"5","rank":"Dolmadı","rankNumeric":null,"score":"Dolmadı","scoreNumeric":null},{"year":2024,"quota":"51","placed":"25","rank":"Dolmadı","rankNumeric":null,"score":"Dolmadı","scoreNumeric":null},{"year":2023,"quota":"53","placed":"53","rank":"1.671.013","rankNumeric":1671013,"score":"192,20115","scoreNumeric":192.20115},{"year":2022,"quota":"30","placed":"30","rank":"1.542.252","rankNumeric":1542252,"score":"201,21055","scoreNumeric":201.21055}]},{"university":"İSTİNYE ÜNİVERSİTESİ","faculty":"İktisadi, İdari ve Sosyal Bilimler Fakültesi","city":"İSTANBUL","sector":"Vakıf","program":"Uluslararası İlişkiler (İngilizce) (%50 İndirimli)","programRaw":"Uluslararası İlişkiler (İngilizce) (%50 İndirimli) (4 Yıllık)","scoreType":"EA","years":[{"year":2025,"quota":"34","placed":"26","rank":"Dolmadı","rankNumeric":null,"score":"Dolmadı","scoreNumeric":null},{"year":2024,"quota":"30","placed":"30","rank":"1.490.415","rankNumeric":1490415,"score":"201,75523","scoreNumeric":201.75523},{"year":2023,"quota":"25","placed":"25","rank":"852.727","rankNumeric":852727,"score":"252,78253","scoreNumeric":252.78253},{"year":2022,"quota":"25","placed":"25","rank":"825.279","rankNumeric":825279,"score":"254,32757","scoreNumeric":254.32757}]},{"university":"LEFKE AVRUPA ÜNİVERSİTESİ","faculty":"İktisadi ve İdari Bilimler Fakültesi (KKTC-LEFKE) (KKTC )","city":null,"sector":null,"program":"Uluslararası İlişkiler (İngilizce) (%50 İndirimli)","programRaw":"Uluslararası İlişkiler (İngilizce) (%50 İndirimli) (4 Yıllık)","scoreType":"EA","years":[{"year":2025,"quota":"20","placed":"2","rank":"Dolmadı","rankNumeric":null,"score":"Dolmadı","scoreNumeric":null},{"year":2024,"quota":"20","placed":"3","rank":"Dolmadı","rankNumeric":null,"score":"Dolmadı","scoreNumeric":null},{"year":2023,"quota":"15","placed":"8","rank":"Dolmadı","rankNumeric":null,"score":"Dolmadı","scoreNumeric":null},{"year":2022,"quota":"10","placed":"4","rank":"Dolmadı","rankNumeric":null,"score":"Dolmadı","scoreNumeric":null}]},{"university":"RAUF DENKTAŞ ÜNİVERSİTESİ","faculty":"İşletme ve Ekonomi Fakültesi (KKTC-LEFKOŞA) (KKTC )","city":null,"sector":null,"program":"Uluslararası İlişkiler (İngilizce) (%50 İndirimli)","programRaw":"Uluslararası İlişkiler (İngilizce) (%50 İndirimli) (4 Yıllık)","scoreType":"EA","years":[{"year":2025,"quota":"2","placed":"1","rank":"Dolmadı","rankNumeric":null,"score":"Dolmadı","scoreNumeric":null},{"year":2024,"quota":"4","placed":"—","rank":"Dolmadı","rankNumeric":null,"score":"Dolmadı","scoreNumeric":null},{"year":2023,"quota":"2","placed":"—","rank":"Dolmadı","rankNumeric":null,"score":"Dolmadı","scoreNumeric":null},{"year":2022,"quota":"3","placed":"—","rank":"Dolmadı","rankNumeric":null,"score":"Dolmadı","scoreNumeric":null}]},{"university":"RAUF DENKTAŞ ÜNİVERSİTESİ","faculty":"İşletme ve Ekonomi Fakültesi (KKTC-LEFKOŞA) (KKTC )","city":null,"sector":null,"program":"Uluslararası İlişkiler (İngilizce) (Burslu)","programRaw":"Uluslararası İlişkiler (İngilizce) (Burslu) (4 Yıllık)","scoreType":"EA","years":[{"year":2025,"quota":"8","placed":"6","rank":"Dolmadı","rankNumeric":null,"score":"Dolmadı","scoreNumeric":null},{"year":2024,"quota":"8","placed":"8","rank":"1.695.017","rankNumeric":1695017,"score":"171,72772","scoreNumeric":171.72772},{"year":2023,"quota":"5","placed":"4","rank":"Dolmadı","rankNumeric":null,"score":"Dolmadı","scoreNumeric":null},{"year":2022,"quota":"5","placed":"2","rank":"Dolmadı","rankNumeric":null,"score":"Dolmadı","scoreNumeric":null}]},{"university":"ULUSLARARASI KIBRIS ÜNİVERSİTESİ","faculty":"İktisadi ve İdari Bilimler Fakültesi (KKTC-LEFKOŞA) (KKTC )","city":null,"sector":null,"program":"Uluslararası İlişkiler (İngilizce) (%50 İndirimli)","programRaw":"Uluslararası İlişkiler (İngilizce) (%50 İndirimli) (4 Yıllık)","scoreType":"EA","years":[{"year":2025,"quota":"3","placed":"1","rank":"Dolmadı","rankNumeric":null,"score":"Dolmadı","scoreNumeric":null},{"year":2024,"quota":"7","placed":"2","rank":"Dolmadı","rankNumeric":null,"score":"Dolmadı","scoreNumeric":null},{"year":2023,"quota":"—","placed":"—","rank":"—","rankNumeric":null,"score":"—","scoreNumeric":null},{"year":2022,"quota":"—","placed":"—","rank":"—","rankNumeric":null,"score":"—","scoreNumeric":null}]},{"university":"GİRNE AMERİKAN ÜNİVERSİTESİ","faculty":"Siyasal Bilimler Fakültesi (KKTC-GİRNE) (KKTC )","city":null,"sector":null,"program":"Uluslararası İlişkiler (İngilizce) (%50 İndirimli)","programRaw":"Uluslararası İlişkiler (İngilizce) (%50 İndirimli) (4 Yıllık)","scoreType":"EA","years":[{"year":2025,"quota":"10","placed":"—","rank":"Dolmadı","rankNumeric":null,"score":"Dolmadı","scoreNumeric":null},{"year":2024,"quota":"11","placed":"—","rank":"Dolmadı","rankNumeric":null,"score":"Dolmadı","scoreNumeric":null},{"year":2023,"quota":"7","placed":"5","rank":"Dolmadı","rankNumeric":null,"score":"Dolmadı","scoreNumeric":null},{"year":2022,"quota":"10","placed":"2","rank":"Dolmadı","rankNumeric":null,"score":"Dolmadı","scoreNumeric":null}]},{"university":"GİRNE ÜNİVERSİTESİ","faculty":"İktisadi ve İdari Bilimler Fakültesi (KKTC-GİRNE) (KKTC )","city":null,"sector":null,"program":"Uluslararası İlişkiler (İngilizce) (%50 İndirimli)","programRaw":"Uluslararası İlişkiler (İngilizce) (%50 İndirimli) (4 Yıllık)","scoreType":"EA","years":[{"year":2025,"quota":"5","placed":"—","rank":"Dolmadı","rankNumeric":null,"score":"Dolmadı","scoreNumeric":null},{"year":2024,"quota":"5","placed":"1","rank":"Dolmadı","rankNumeric":null,"score":"Dolmadı","scoreNumeric":null},{"year":2023,"quota":"—","placed":"—","rank":"—","rankNumeric":null,"score":"—","scoreNumeric":null},{"year":2022,"quota":"—","placed":"—","rank":"—","rankNumeric":null,"score":"—","scoreNumeric":null}]},{"university":"İSTANBUL NİŞANTAŞI ÜNİVERSİTESİ","faculty":"İktisadi, İdari ve Sosyal Bilimler Fakültesi","city":"İSTANBUL","sector":"Vakıf","program":"Uluslararası İlişkiler (İngilizce) (Ücretli)","programRaw":"Uluslararası İlişkiler (İngilizce) (Ücretli) (4 Yıllık)","scoreType":"EA","years":[{"year":2025,"quota":"1","placed":"—","rank":"Dolmadı","rankNumeric":null,"score":"Dolmadı","scoreNumeric":null},{"year":2024,"quota":"1","placed":"1","rank":"1.087.495","rankNumeric":1087495,"score":"231,17149","scoreNumeric":231.17149},{"year":2023,"quota":"1","placed":"1","rank":"791.010","rankNumeric":791010,"score":"258,19169","scoreNumeric":258.19169},{"year":2022,"quota":"1","placed":"1","rank":"365.918","rankNumeric":365918,"score":"306,99935","scoreNumeric":306.99935}]},{"university":"İSTANBUL NİŞANTAŞI ÜNİVERSİTESİ","faculty":"İktisadi, İdari ve Sosyal Bilimler Fakültesi","city":"İSTANBUL","sector":"Vakıf","program":"Uluslararası İlişkiler (Ücretli)","programRaw":"Uluslararası İlişkiler (Ücretli) (4 Yıllık)","scoreType":"EA","years":[{"year":2025,"quota":"1","placed":"—","rank":"Dolmadı","rankNumeric":null,"score":"Dolmadı","scoreNumeric":null},{"year":2024,"quota":"1","placed":"1","rank":"1.000.582","rankNumeric":1000582,"score":"237,33753","scoreNumeric":237.33753},{"year":2023,"quota":"—","placed":"—","rank":"—","rankNumeric":null,"score":"—","scoreNumeric":null},{"year":2022,"quota":"—","placed":"—","rank":"—","rankNumeric":null,"score":"—","scoreNumeric":null}]},{"university":"KIBRIS AMERİKAN ÜNİVERSİTESİ","faculty":"Siyasal Bilgiler Fakültesi (KKTC-LEFKOŞA) (KKTC )","city":null,"sector":null,"program":"Uluslararası İlişkiler (İngilizce) (%50 İndirimli)","programRaw":"Uluslararası İlişkiler (İngilizce) (%50 İndirimli) (4 Yıllık)","scoreType":"EA","years":[{"year":2025,"quota":"10","placed":"—","rank":"Dolmadı","rankNumeric":null,"score":"Dolmadı","scoreNumeric":null},{"year":2024,"quota":"10","placed":"1","rank":"Dolmadı","rankNumeric":null,"score":"Dolmadı","scoreNumeric":null},{"year":2023,"quota":"10","placed":"2","rank":"Dolmadı","rankNumeric":null,"score":"Dolmadı","scoreNumeric":null},{"year":2022,"quota":"10","placed":"—","rank":"Dolmadı","rankNumeric":null,"score":"Dolmadı","scoreNumeric":null}]},{"university":"KIBRIS AMERİKAN ÜNİVERSİTESİ","faculty":"Siyasal Bilgiler Fakültesi (KKTC-LEFKOŞA) (KKTC )","city":null,"sector":null,"program":"Uluslararası İlişkiler (İngilizce) (Ücretli)","programRaw":"Uluslararası İlişkiler (İngilizce) (Ücretli) (4 Yıllık)","scoreType":"EA","years":[{"year":2025,"quota":"10","placed":"—","rank":"Dolmadı","rankNumeric":null,"score":"Dolmadı","scoreNumeric":null},{"year":2024,"quota":"10","placed":"—","rank":"Dolmadı","rankNumeric":null,"score":"Dolmadı","scoreNumeric":null},{"year":2023,"quota":"10","placed":"1","rank":"Dolmadı","rankNumeric":null,"score":"Dolmadı","scoreNumeric":null},{"year":2022,"quota":"10","placed":"2","rank":"Dolmadı","rankNumeric":null,"score":"Dolmadı","scoreNumeric":null}]},{"university":"YAKIN DOĞU ÜNİVERSİTESİ","faculty":"İktisadi ve İdari Bilimler Fakültesi (KKTC-LEFKOŞA) (KKTC )","city":null,"sector":null,"program":"Uluslararası İlişkiler (İngilizce) (%50 İndirimli)","programRaw":"Uluslararası İlişkiler (İngilizce) (%50 İndirimli) (4 Yıllık)","scoreType":"EA","years":[{"year":2025,"quota":"15","placed":"—","rank":"Dolmadı","rankNumeric":null,"score":"Dolmadı","scoreNumeric":null},{"year":2024,"quota":"20","placed":"4","rank":"Dolmadı","rankNumeric":null,"score":"Dolmadı","scoreNumeric":null},{"year":2023,"quota":"10","placed":"7","rank":"Dolmadı","rankNumeric":null,"score":"Dolmadı","scoreNumeric":null},{"year":2022,"quota":"10","placed":"3","rank":"Dolmadı","rankNumeric":null,"score":"Dolmadı","scoreNumeric":null}]}],"warnings":["20/126 satırda il yok"]}